Workbook

Sheet Cover
B2: Premium Longevity Resort — Capex Benchmark Study
B3: Equipment, Software, Spa, Kitchen & Medical Infrastructure across 4 regions
B5: Date issued | C5: 2026-05-03
B6: Tier coverage | C6: Lanserhof/CLP (full medical depth) | SHA/Chenot (medical-light) | Six Senses Place (wellness+)
B7: Property profile | C7: 80–100 keys (model uses 90 keys mid-point); premium-luxury positioning
B8: Regions priced | C8: Western Europe (EUR) | North America (USD) | Asia (USD, country-tagged) | Russia (RUB est.)
B9: Items priced | C9: 134 line items across 16 categories
B11: WORKBOOK CONTENTS
B12: Cover | C12: This page — methodology, tier definitions, color legend
B13: Equipment Master List | C13: All 134 line items with brand, prices in 4 regions, tier assignment, source, confidence
B14: Capex Summary by Tier | C14: Roll-up by tier x group x region. Live formulas — change Master List or keys_count to refresh.
B15: Payback & Revenue Logic | C15: Equipment payback blocks, procedure & package pricing, ADR uplift logic, payback bands
B16: Regional Cost Drivers | C16: Sanctions, customs/VAT, parallel import, domestic alternatives — Russia detail
B17: Sources & Methodology | C17: All sources cited + confidence assessment + recommended verification path
B20: TIER DEFINITIONS
B21: Six Senses Place-tier | C21: Wellness-plus. Premium spa, full thermal, full Pilates+gym, full kitchen, PMS+IT. NO medical center, no imaging, no in-house lab, no EHR. Items here are present in EVERY tier (the operational floor).
B22: SHA/Chenot-tier | C22: Medical-light. Adds ultrasound, DEXA, X-ray, basic lab analyzers, ECG suite, HSAT, IV chairs, FibroScan, RMR, mid-market EHR, basic medical infra.
B23: Lanserhof/CLP-tier | C23: Full medical depth. Adds MRI 3T+1.5T, CT, OCT, mammography, full PSG/EEG, ozone/IHHT/HBOT, aesthetic lasers, full PACS, full medical gas + generator + HEPA.
B24: Optional upsell | C24: Reported separately — Epic EHR, Cryolipolysis, ECG patch fleet, WHOOP/Garmin enterprise. NOT in tier base totals.
B27: COLOR-CODE LEGEND
B28: Hardcoded input | C28: Numbers a user can change for scenarios (unit prices, keys_count, FX)
B29: Formula / calculated | C29: Cells computed by the workbook from inputs above
B30: Cross-sheet link | C30: References to other sheets — keeps roll-ups in sync with the Master List
B31: Confidence fills | C31: Green = High, Yellow = Medium, Orange = Low — applied to Master List Confidence column.
B33: READING THIS WORKBOOK
C34: 1. The Master List is the single source of truth. Edit a price or quantity there — the Capex Summary updates via SUMPRODUCT.
C35: 2. Capex Summary uses tier inclusion logic: Six Senses items count in ALL 3 tiers; SHA items count in CLP + SHA; CLP items count only in CLP.
C36: 3. Software shows upfront capex AND annual subscription separately. Annual figures are opex (excluded from capex totals).
C37: 4. The Russia (RUB) column carries the LOWEST confidence — see Sources & Methodology for verification recommendations.
C38: 5. 'Capex per key' uses keys_count in cell B3 of the Capex Summary sheet (default 90 — editable).

Sheet Equipment Master List
A1: ID | B1: Category | C1: Subcategory | D1: Equipment item | E1: Brand examples | F1: Function | G1: Tier (corrected) | H1: Tier (research-assigned) | I1: Price — Western Europe (€) | J1: Price — North America (USD) | K1: Price — Asia (USD) | L1: Asia country | M1: Price — Russia est. (₽) | N1: Quantity (80–100 keys) | O1: Useful life (yrs) | P1: Annual maint (% capex) | Q1: Operator FTE | R1: Source | S1: Confidence | T1: Last verified | U1: Notes | V1: EU annual € (sw) | W1: NA annual $ (sw) | X1: Asia annual $ (sw) | Y1: Russia annual ₽ (sw)
A2: 1 | B2: Aesthetic & Regenerative | C2: Ablative/non-ablative platform | D2: Modular aesthetic laser platform (BBL+Halo+ProFractional) | E2: Sciton JOULE X / Lumenis M22 | F2: Skin resurfacing, pigment, vascular - workhorse aesthetic platform | G2: Lanserhof/CLP-tier | H2: Lanserhof/CLP-tier | I2: 180000 | J2: 215000 | K2: 175000 | L2: UAE | M2: 25000000 | N2: 1 | O2: 8 | P2: 0.1 | Q2: 0.6 | R2: Sciton dealer; pre-owned mJOULE $149,950 (mrp.io); Lumenis dealer 2024 | S2: Medium | T2: 2026-05 | U2: REGULATORY FLAG: US-OEM. Russian import via parallel channels +20-30%. Consider European alternatives (Asclepion, Quantel).
A3: 2 | B3: Aesthetic & Regenerative | C3: Cryolipolysis | D3: Cryolipolysis system (fat reduction) | E3: Allergan CoolSculpting Elite / Cooltech Define | F3: Non-invasive fat reduction - high-margin aesthetic service | G3: Optional upsell | H3: Optional upsell | I3: 100000 | J3: 120000 | K3: 95000 | L3: UAE | M3: 14000000 | N3: 1 | O3: 7 | P3: 0.1 | Q3: 0.4 | R3: Allergan dealer 2024; Offer Aesthetic refurbished CoolSculpting Elite listings | S3: Medium | T3: 2026-05 | U3: REGULATORY FLAG: Allergan/AbbVie US-controlled. Cooltech (Spain, now Cocoon Medical) preferable for Russia.
A4: 3 | B4: Aesthetic & Regenerative | C4: EMSculpt / muscle stim | D4: Electromagnetic muscle stimulation (HIFEM) | E4: BTL EMSculpt NEO | F4: Muscle building + fat reduction - popular spa add-on | G4: Lanserhof/CLP-tier | H4: SHA/Chenot-tier | I4: 130000 | J4: 150000 | K4: 125000 | L4: UAE | M4: 18000000 | N4: 1 | O4: 7 | P4: 0.1 | Q4: 0.4 | R4: BTL Industries dealer quotes 2024-25 | S4: Medium | T4: 2026-05 | U4: BTL is Czech-owned - Russia route relatively clean.
A5: 4 | B5: Aesthetic & Regenerative | C5: HIFU skin lifting | D5: Microfocused ultrasound skin lifting (HIFU) | E5: Merz Ultherapy Prime / Ulthera | F5: Non-surgical skin tightening - high demand procedure | G5: SHA/Chenot-tier | H5: SHA/Chenot-tier | I5: 65000 | J5: 75000 | K5: 60000 | L5: UAE | M5: 9000000 | N5: 1 | O5: 7 | P5: 0.12 | Q5: 0.4 | R5: konmison Ultherapy machine cost guide 2025; vsquareclinic Ulthera Prime | S5: Medium | T5: 2026-05 | U5: Cartridge consumables ~$300/treatment. Russia: Merz EU-OEM, lower sanctions risk than US.
A6: 5 | B6: Aesthetic & Regenerative | C6: LED light therapy | D6: LED light therapy bed / panel (medical) | E6: NovoTHOR / Celluma PRO panels | F6: Photobiomodulation for skin/recovery/longevity | G6: SHA/Chenot-tier | H6: SHA/Chenot-tier | I6: 65000 | J6: 78000 | K6: 60000 | L6: UAE | M6: 9000000 | N6: 1 | O6: 10 | P6: 0.04 | Q6: 0.2 | R6: NovoTHOR retail 2024 (~$70-90k); Celluma Pro $3-5k panels alt | S6: Medium | T6: 2026-05 | U6: NovoTHOR full-body bed is signature offering at premium clinics.
A7: 6 | B7: Aesthetic & Regenerative | C7: Radiofrequency therapy | D7: Radiofrequency therapy device (448 kHz Tecar) | E7: Indiba Activ Elite NS / Indiba CT9 | F7: Tissue regeneration, recovery, body contouring - rehab+aesthetic dual use | G7: SHA/Chenot-tier | H7: SHA/Chenot-tier | I7: 35000 | J7: 42000 | K7: 33000 | L7: UAE | M7: 4800000 | N7: 2 | O7: 8 | P7: 0.07 | Q7: 0.6 | R7: Indiba dealer references; NYDNRehab clinical pricing; eBay used listings ~$55k | S7: Medium | T7: 2026-05 | U7: Spanish OEM, cleaner Russia route than US lasers.
A8: 7 | B8: Aesthetic & Regenerative | C8: Vascular/pigment laser platform | D8: Multi-wavelength aesthetic laser platform (KTP+Nd:YAG) | E8: Cutera Excel V+ / Candela GentleMax Pro | F8: Vascular lesions, pigmentation, skin rejuvenation | G8: Lanserhof/CLP-tier | H8: Lanserhof/CLP-tier | I8: 90000 | J8: 105000 | K8: 85000 | L8: UAE | M8: 12500000 | N8: 1 | O8: 8 | P8: 0.1 | Q8: 0.5 | R8: The Laser Agent 2025 new Cutera Excel V+ listings, Bimedis range $18,613-$49,950 used | S8: Medium | T8: 2026-05 | U8: REGULATORY FLAG: US/Israel-OEM aesthetic lasers face Russian import constraints. Source via Turkey/UAE re-export, expect +15-25% markup and parallel-import warranty risk.
A9: 8 | B9: Body Composition & Performance | C9: Body composition - air displacement | D9: BodPod GS-X air displacement plethysmograph | E9: Cosmed BodPod GS-X | F9: Gold-standard 2-compartment body composition; differentiator vs InBody | G9: Six Senses Place-tier | H9: Lanserhof/CLP-tier | I9: 50000 | J9: 58000 | K9: 48000 | L9: UAE | M9: 6600000 | N9: 1 | O9: 12 | P9: 0.05 | Q9: 0.2 | R9: Cosmed dealer quotes, MedicalExpo 2024 | S9: Medium | T9: 2026-05 | U9: Used by Lanserhof, CLP. Heavy unit, dedicated room with stable temperature required.
A10: 9 | B10: Body Composition & Performance | C10: Body composition - bioimpedance | D10: Medical-grade body composition analyzer (BIA, multi-frequency) | E10: InBody 970 / Seca mBCA 555 (medical-grade) | F10: Segmental body composition, ECW/ICW, phase angle - foundational longevity assessment | G10: Six Senses Place-tier | H10: Lanserhof/CLP-tier | I10: 28000 | J10: 32600 | K10: 26000 | L10: UAE | M10: 3700000 | N10: 2 | O10: 8 | P10: 0.05 | Q10: 0.3 | R10: InBody USA shop list 2025 ($32,605); Seca mBCA Pro $9,599 base; HaB Direct mBCA 555 listing | S10: High | T10: 2026-05 | U10: InBody 970 is the workhorse; Seca mBCA 555 is medical-CE class. Russia: distributors in Moscow available, no sanctions issues.
A11: 10 | B11: Body Composition & Performance | C11: Cardiopulmonary | D11: VO2 max / metabolic cart (CPET) | E11: Cosmed K5 / Cosmed Quark CPET / MGC Diagnostics | F11: VO2max, RMR - central healthy-aging metric | G11: SHA/Chenot-tier | H11: Lanserhof/CLP-tier | I11: 45000 | J11: 52000 | K11: 42000 | L11: UAE | M11: 6000000 | N11: 1 | O11: 10 | P11: 0.08 | Q11: 0.4 | R11: Cosmed dealer 2024, MedicalExpo listings | S11: Medium | T11: 2026-05 | U11: Lanserhof/SHA both run CPET. Includes treadmill or cycle ergometer.
A12: 11 | B12: Body Composition & Performance | C12: DEXA scanner | D12: DEXA body composition / bone density scanner | E12: Hologic Horizon / GE Lunar iDXA | F12: Bone density + body composition gold standard | G12: SHA/Chenot-tier | H12: Lanserhof/CLP-tier | I12: 95000 | J12: 115000 | K12: 90000 | L12: UAE | M12: 13100000 | N12: 1 | O12: 12 | P12: 0.07 | Q12: 0.4 | R12: Hologic/GE dealer 2024 | S12: Medium | T12: 2026-05 | U12: May overlap with Phase 1 medical imaging - verify single source to avoid double-count.
A13: 12 | B13: Body Composition & Performance | C13: Force/gait analysis | D13: Force plate system (dual, embedded) | E13: AMTI BMS400600 / Bertec FP4060 | F13: Ground reaction force, balance, gait kinetics | G13: SHA/Chenot-tier | H13: Lanserhof/CLP-tier | I13: 45000 | J13: 52000 | K13: 42000 | L13: UAE | M13: 6000000 | N13: 1 | O13: 15 | P13: 0.04 | Q13: 0.2 | R13: AMTI dealer quotes, Noraxon partner pricing 2024 | S13: Medium | T13: 2026-05 | U13: Pair of plates; install requires recessed floor pit. Often paired with Vicon.
... A66: 65 | B66: IT, EHR, Patient Software | C66: Access control & RFID locks | D66: Electronic guest room locks + back-of-house access | E66: Salto, Assa Abloy VingCard, dormakaba | F66: RFID/mobile keys per door; staff zones | G66: Six Senses Place-tier | H66: Lanserhof/CLP-tier | I66: 165000 | J66: 200000 | K66: 130000 | L66: China | M66: 20500000 | N66: 1 | O66: 12 | P66: 0.04 | Q66: 0 | R66: Kompareit hotel access $1500-2500/door; 100 doors + 30 BoH | S66: High | T66: 2026-05 | U66: Premium spec (BLE+mobile key). Russia: VingCard via parallel import; +20-25%.
A67: 66 | B67: IT, EHR, Patient Software | C67: EHR System | D67: Mid-market EHR (Athenahealth-tier) | E67: Athenahealth athenaOne, Tebra, ModMed; Russian: МИС МедОфис, qMS | F67: Clinical record-keeping for medical center; integrates lab/imaging | G67: SHA/Chenot-tier | H67: Lanserhof/CLP-tier | I67: 180000 | J67: 220000 | K67: 150000 | L67: Singapore | M67: 12000000 | N67: 1 | O67: 7 | P67: 0 | Q67: 0.5 | R67: Athenahealth $140/provider/mo + 4-8% collections; impl $2-5k/provider; emrguides.com 2025 | S67: Medium | T67: 2026-05 | U67: Russia: 152-FZ data localization blocks Western cloud EHR. qMS/МедОфис ~50% Western cost; needs custom integration. | V67: 90000 | W67: 110000 | X67: 75000 | Y67: 6000000
A68: 67 | B68: IT, EHR, Patient Software | C68: EHR System (Optional Epic-tier) | D68: Enterprise EHR (Epic/Cerner) | E68: Epic Hyperspace, Oracle Health (Cerner Millennium) | F68: Full enterprise EHR for hospital-grade resort medical center | G68: Optional upsell | H68: Optional upsell | I68: 1800000 | J68: 2200000 | K68: 1500000 | L68: Singapore | M68: 0 | N68: 0 | O68: 10 | P68: 0 | Q68: 1 | R68: Tactionsoft 2025 ($500k-$10M); arkenea.com Cerner; Veterans Memorial Hospital $3.88M | S68: Medium | T68: 2026-05 | U68: Overkill for 80-100 keys; only relevant if hospital-grade. Not deployable in Russia. | V68: 350000 | W68: 420000 | X68: 300000 | Y68: 0
A69: 68 | B69: IT, EHR, Patient Software | C69: Guest experience / mobile app | D69: Guest mobile app + in-room tablet platform | E69: Crave Interactive, SuitePad, Hudini, INTELITY | F69: Mobile check-in, in-room ordering, treatment booking, content | G69: Six Senses Place-tier | H69: Lanserhof/CLP-tier | I69: 90000 | J69: 110000 | K69: 75000 | L69: Singapore | M69: 9500000 | N69: 1 | O69: 5 | P69: 0 | Q69: 0 | R69: Hospitality tech benchmark; tablet $600-1200/room + license $25-40/room/mo | S69: Medium | T69: 2026-05 | U69: Includes tablets per room, license, and PMS/spa integration. | V69: 35000 | W69: 42000 | X69: 28000 | Y69: 2800000
A70: 69 | B70: IT, EHR, Patient Software | C70: Longevity patient platform | D70: Longevity-specific patient/wellness platform | E70: Function Health (B2B), Hone Health, Healthspan; alt: custom | F70: Biomarker tracking, member portal, longitudinal results, AI insights | G70: Six Senses Place-tier | H70: Lanserhof/CLP-tier | I70: 75000 | J70: 90000 | K70: 65000 | L70: Singapore | M70: 8500000 | N70: 1 | O70: 5 | P70: 0 | Q70: 0.5 | R70: Function Health B2B (Equinox $249, Higginbotham $334/yr/member); sacra.com | S70: Low | T70: 2026-05 | U70: Annual = ~200-300 active members at $250-$350/yr. Russia: must build custom or isolated instance. | V70: 60000 | W70: 72000 | X70: 55000 | Y70: 4000000
A71: 70 | B71: IT, EHR, Patient Software | C71: Network infrastructure | D71: Wired + Wi-Fi 6/7 backbone (enterprise) | E71: Cisco Meraki, RUCKUS Networks, Aruba; Russian: Eltex, QTECH | F71: Guest + back-of-house network, segmented VLANs incl. medical | G71: Six Senses Place-tier | H71: Lanserhof/CLP-tier | I71: 220000 | J71: 260000 | K71: 170000 | L71: Singapore | M71: 28000000 | N71: 1 | O71: 8 | P71: 0.1 | Q71: 0 | R71: RUCKUS/Cisco hospitality vertical; ~EUR 2-3k per AP installed, 80 APs + switching | S71: Medium | T71: 2026-05 | U71: Russia: Cisco/Aruba sanctioned post-2022. Eltex/QTECH or grey-market.
A72: 71 | B72: IT, EHR, Patient Software | C72: PMS - Hotel side | D72: Cloud PMS (luxury 80-100 keys) | E72: Mews Enterprise, Oracle Opera Cloud, Protel; Russian: Bnovo, Shelter, TravelLine | F72: Reservations, guest folio, housekeeping, channel mgmt, POS integration | G72: Six Senses Place-tier | H72: Lanserhof/CLP-tier | I72: 45000 | J72: 55000 | K72: 38000 | L72: Singapore | M72: 2500000 | N72: 1 | O72: 7 | P72: 0 | Q72: 0 | R72: Mews Enterprise tier (hoteltechreport, roommaster); Mews EUR 300/mo standalone reference | S72: Medium | T72: 2026-05 | U72: Russia 2026: Mews/Opera withdrew post-2022 sanctions. Russian alts (Shelter, Bnovo) ~50-60% cost but limited luxury feature parity. | V72: 36000 | W72: 45000 | X72: 32000 | Y72: 1500000
A73: 72 | B73: IT, EHR, Patient Software | C73: Security - cameras | D73: IP CCTV system (40-60 cameras + NVR) | E73: Avigilon, Axis, Hanwha; Russian: TRASSIR, Macroscop | F73: Perimeter + back-of-house security | G73: Six Senses Place-tier | H73: Lanserhof/CLP-tier | I73: 75000 | J73: 90000 | K73: 55000 | L73: China | M73: 7800000 | N73: 1 | O73: 10 | P73: 0.05 | Q73: 0 | R73: Avigilon/Axis dealer; ~EUR 1-1.5k per camera installed | S73: High | T73: 2026-05 | U73: Russia: TRASSIR dominant local; pricing favorable vs Western.
A74: 73 | B74: IT, EHR, Patient Software | C74: Spa/medical booking system | D74: Integrated spa & treatment booking | E74: Book4Time, Agilysys Spa, ResortSuite | F74: Therapist scheduling, room utilization, package mgmt, retail | G74: Six Senses Place-tier | H74: Lanserhof/CLP-tier | I74: 55000 | J74: 68000 | K74: 45000 | L74: Singapore | M74: 3500000 | N74: 1 | O74: 7 | P74: 0 | Q74: 0 | R74: Book4Time/Agilysys/ResortSuite indicative dealer 2025 | S74: Medium | T74: 2026-05 | U74: Critical at premium wellness resorts; integrates with PMS and EHR. | V74: 28000 | W74: 35000 | X74: 22000 | Y74: 1500000
A75: 74 | B75: IT, EHR, Patient Software | C75: Telephony / IPTV | D75: VoIP telephony + IPTV system | E75: Mitel, Cisco; LG/Samsung Pro:Idiom IPTV | F75: In-room phone, IPTV, BoH telephony | G75: Six Senses Place-tier | H75: Lanserhof/CLP-tier | I75: 95000 | J75: 115000 | K75: 75000 | L75: China | M75: 12500000 | N75: 1 | O75: 10 | P75: 0.06 | Q75: 0 | R75: Hospitality AV/IT integrator benchmark | S75: Medium | T75: 2026-05 | U75: Mid-tier resorts may go phone-light/streaming-only.
A76: 75 | B76: IV & Infusion | C76: Hyperbaric | D76: Hyperbaric oxygen chamber - mild HBOT (1.3-1.5 ATA) | E76: OxyHealth Vitaeris 320, Hyperbaric Centrales OxyVita, Summit to Sea Dive | F76: Soft-shell mild hyperbaric oxygen therapy for recovery / longevity protocols. | G76: Lanserhof/CLP-tier | H76: Lanserhof/CLP-tier | I76: 35000 | J76: 40000 | K76: 28000 | L76: China | M76: 4800000 | N76: 2 | O76: 10 | P76: 0.05 | Q76: 0.5 | R76: OxyHealth Vitaeris 320 dealer list $20-35k; soft-shell mild HBOT typical EUR 25-45k. Hard-shell medical-grade chambers (2.0+ ATA) are 5-10x more. | S76: Medium | T76: 2026-05 | U76: Soft-shell mild HBOT scope (regulatory simpler, no pressurised oxygen). Hard-shell HBOT excluded - different category. Russia: domestic BLKS chambers and OxyHealth via parallel import.
A77: 76 | B77: IV & Infusion | C77: IHHT | D77: IHHT intermittent hypoxic-hyperoxic training device | E77: Cellgym Pro / Lounge, Hypoxico Everest Summit II, GO2Altitude Biomedtech | F77: Intermittent hypoxia-hyperoxia therapy - mitochondrial training, longevity protocol. | G77: Lanserhof/CLP-tier | H77: Lanserhof/CLP-tier | I77: 35000 | J77: 40000 | K77: 28000 | L77: China | M77: 4800000 | N77: 3 | O77: 8 | P77: 0.05 | Q77: 0.3 | R77: Cellgym dealer quotes EUR 30-45k for Pro/Lounge unit; Hypoxico distributor pricing; Cocoon Medical Spa public Cellgym installation references. | S77: Low | T77: 2026-05 | U77: ESTIMATE - Cellgym list price not public. Per-session retail EUR 50-80 cited. 3 units cover 25-30 sessions/day. Russia: Russian-developed Bio-Nova MTI/IHT is domestic alternative at EUR 12-18k.
A78: 77 | B78: IV & Infusion | C78: IV Suite | D78: IV therapy lounge chair (clinical recliner) | E78: Champion Manufacturing 56 series, Stance Healthcare Bari, Winco CareCliner | F78: Comfortable reclining infusion chair for IV drips / NAD+ / vitamin therapy lounge. | G78: SHA/Chenot-tier | H78: Lanserhof/CLP-tier | I78: 3500 | J78: 4000 | K78: 2500 | L78: China | M78: 480000 | N78: 6 | O78: 10 | P78: 0.04 | Q78: 0 | R78: Champion / Stance / Winco published dealer pricing $2,500-$5,000 per clinical recliner; common dealer quote EUR 3,000-4,500. | S78: High | T78: 2026-05 | U78: 6-8 chairs for an 80-100 key longevity resort IV lounge. Russia: domestic Med-Mos and import via Turkey both feasible.
A79: 78 | B79: IV & Infusion | C79: Infusion Pumps | D79: Smart infusion pump | E79: B.Braun Infusomat Space, Baxter Sigma Spectrum IQ, BD Alaris | F79: Smart infusion pump with DERS for IV vitamins, NAD+, chelation, peptides. | G79: SHA/Chenot-tier | H79: Lanserhof/CLP-tier | I79: 3500 | J79: 4000 | K79: 2500 | L79: China | M79: 480000 | N79: 8 | O79: 7 | P79: 0.06 | Q79: 0 | R79: Outfront Medical / Coast Biomed Baxter Sigma Spectrum refurb $1.5-2.5k; B.Braun new ~EUR 3-4k list. | S79: High | T79: 2026-05 | U79: 8 pumps to cover 6-chair IV lounge + 2 spares. Russia: B.Braun (German) still distributed but wait times extended; Russian Yelatma pumps also used.
A80: 79 | B80: IV & Infusion | C80: Ozone Therapy | D80: Medical ozone therapy generator | E80: Herrmann Apparatebau Hyper Medozon comfort, Zotzmann + Stahl OzonoSan, Humares Medozon | F80: Major/minor autohemotherapy, ozone insufflation, ozonated saline. | G80: Lanserhof/CLP-tier | H80: Lanserhof/CLP-tier | I80: 18000 | J80: 0 | K80: 14000 | L80: China | M80: 2500000 | N80: 2 | O80: 10 | P80: 0.05 | Q80: 0.3 | R80: MedicalExpo Herrmann Hyper Medozon comfort; HealthManagement.org Hyper Medozon comfort listing; secondary market Medbidding refurb 6-9k EUR; new list EUR 15-22k from German dealers. | S80: Medium | T80: 2026-05 | U80: Heavily regulated - banned/restricted in US (FDA), allowed in Germany/Austria/CH/Spain/Russia under medical supervision. Russia: ozone therapy is well-established (Russian Federal MoH-registered indications); Russian Medozons-BM domestic alternative.
A81: 80 | B81: Kitchen & F&B | C81: Bakery oven | D81: Deck/convection bakery oven | E81: MIWE Condo 3.0608, MIWE econo, Wachtel | F81: In-house bread, pastry, gluten-free baking | G81: Six Senses Place-tier | H81: Lanserhof/CLP-tier | I81: 42000 | J81: 52000 | K81: 38000 | L81: China | M81: 5300000 | N81: 1 | O81: 15 | P81: 0.04 | Q81: 0 | R81: MIWE/Wachtel dealer indicative (archiexpo, bakeryequipment.com); 3-deck unit | S81: Medium | T81: 2026-05 | U81: Lanserhof-style organic/gluten-free bakery requires deck oven + proofer.
A82: 81 | B82: Kitchen & F&B | C82: Cold kitchen / garde manger | D82: Cold kitchen station (refrigerated prep + plating) | E82: Inomak, True, Hoshizaki | F82: Salads, raw, sashimi, plating for clean cuisine | G82: Six Senses Place-tier | H82: SHA/Chenot-tier | I82: 35000 | J82: 42000 | K82: 28000 | L82: China | M82: 4400000 | N82: 1 | O82: 12 | P82: 0.04 | Q82: 0 | R82: Inomak/True dealer EU; 6-8 m linear cold prep + worktops | S82: Medium | T82: 2026-05 | U82: Critical for raw/clean cuisine programs (Chenot-style).
A83: 82 | B83: Kitchen & F&B | C83: Combi oven | D83: Premium combi oven (10-grid 1/1) | E83: Rational iCombi Pro 10-1/1, Convotherm 4 easyTouch | F83: Therapeutic + restaurant cooking; steam, convection, low-temp | G83: Six Senses Place-tier | H83: Lanserhof/CLP-tier | I83: 22000 | J83: 27000 | K83: 19000 | L83: China | M83: 2750000 | N83: 3 | O83: 12 | P83: 0.05 | Q83: 0 | R83: Rational dealer indicative (WebstaurantStore, Buzz Catering, Nella) 2025; Russian dealer markup ~1.25x EU | S83: High | T83: 2026-05 | U83: Three units cover therapeutic, hot kitchen, and banqueting.
A84: 83 | B84: Kitchen & F&B | C84: Combi oven (small) | D84: Compact combi oven (6-grid 1/1) | E84: Rational iCombi Pro 6-1/1, UNOX ChefTop | F84: Pastry, fish, dietary station, room service line | G84: Six Senses Place-tier | H84: SHA/Chenot-tier | I84: 14500 | J84: 18000 | K84: 12000 | L84: China | M84: 1800000 | N84: 2 | O84: 12 | P84: 0.05 | Q84: 0 | R84: Rational price list indicative; UNOX dealer EU 2025 | S84: High | T84: 2026-05 | U84: Used for pastry/cold-finishing kitchen and dietary line.
A85: 84 | B85: Kitchen & F&B | C85: Dishwasher (flight/conveyor) | D85: Conveyor/flight dishwasher | E85: Hobart FT1000e, Winterhalter MTF, Meiko M-iQ | F85: Main banquet/restaurant dish line | G85: Six Senses Place-tier | H85: Lanserhof/CLP-tier | I85: 75000 | J85: 90000 | K85: 60000 | L85: China | M85: 9500000 | N85: 1 | O85: 12 | P85: 0.05 | Q85: 0 | R85: Hobart, Winterhalter dealer EU 2025; hobartcorp.com | S85: High | T85: 2026-05 | U85: Required at 80-100 keys for banquet capacity.
A86: 85 | B86: Kitchen & F&B | C86: Dishwasher (under-counter & pass-through) | D86: Pass-through and undercounter glasswashers/dishwashers (set) | E86: Hobart, Winterhalter UC-M, Meiko | F86: Bar, juice bar, prep stations | G86: Six Senses Place-tier | H86: Lanserhof/CLP-tier | I86: 28000 | J86: 34000 | K86: 22000 | L86: China | M86: 3500000 | N86: 4 | O86: 10 | P86: 0.05 | Q86: 0 | R86: Hobart/Winterhalter dealer EU 2025 | S86: High | T86: 2026-05 | U86: Set of 4 covers bar, juice bar, banqueting, satellite.
... A130: 129 | B130: Sleep & Neurology | C130: Wearables | D130: Premium wearables (Oura / WHOOP / Apple Watch fleet for guests) | E130: Oura Ring Gen 4, WHOOP 5.0, Apple Watch Ultra 2 | F130: Sleep stages, HRV, recovery, training load - guest take-home wearable as part of programme. | G130: SHA/Chenot-tier | H130: Lanserhof/CLP-tier | I130: 8000 | J130: 9000 | K130: 6500 | L130: China | M130: 1100000 | N130: 25 | O130: 3 | P130: 0.1 | Q130: 0 | R130: Oura Ring $349-$499 retail; WHOOP $239 + $30/mo subscription; Apple Watch Ultra 2 $799. 25-unit fleet at avg EUR 320 per device. | S130: High | T130: 2026-05 | U130: Loaner fleet for in-residence guests. Subscription costs flow as OPEX. Russia: Apple Watch / Oura via parallel import (30% premium); WHOOP not available officially.
A131: 130 | B131: Telemedicine & Digital Health | C131: CGM data integration | D131: CGM platform integration (Levels-style) | E131: Levels Health API, Nutrisense, Veri | F131: Continuous glucose monitor data into longevity platform | G131: Six Senses Place-tier | H131: SHA/Chenot-tier | I131: 18000 | J131: 22000 | K131: 15000 | L131: Singapore | M131: 2200000 | N131: 1 | O131: 5 | P131: 0 | Q131: 0 | R131: Levels API B2B / Nutrisense partner; partner integration estimate | S131: Low | T131: 2026-05 | U131: Sensors charged per guest separately. Russia: Abbott Libre via parallel import; Russian dev for portal. | V131: 14000 | W131: 17000 | X131: 11000 | Y131: 1400000
A132: 131 | B132: Telemedicine & Digital Health | C132: Post-stay coaching platform | D132: Coaching/concierge app (post-stay continuum) | E132: MindBody Plus, Healthie, custom on Twilio | F132: 1:1 coaching, content, member retention 6-12 months post-stay | G132: Six Senses Place-tier | H132: Lanserhof/CLP-tier | I132: 65000 | J132: 80000 | K132: 55000 | L132: Singapore | M132: 7500000 | N132: 1 | O132: 5 | P132: 0 | Q132: 1 | R132: Healthie / custom dev estimate; Lanserhof@home model reference | S132: Low | T132: 2026-05 | U132: Critical revenue/retention driver - drives ARR via subscription. Operator headcount = coaches. | V132: 30000 | W132: 38000 | X132: 24000 | Y132: 2400000
A133: 132 | B133: Telemedicine & Digital Health | C133: Video consultation platform | D133: HIPAA/GDPR-compliant telemedicine platform | E133: Doxy.me Enterprise, Teladoc B2B, Amwell | F133: Post-stay video consults with longevity physicians | G133: Six Senses Place-tier | H133: Lanserhof/CLP-tier | I133: 25000 | J133: 32000 | K133: 22000 | L133: Singapore | M133: 2500000 | N133: 1 | O133: 5 | P133: 0 | Q133: 0 | R133: Doxy.me Clinic $50/user/mo; Enterprise custom; ~30-40 users | S133: High | T133: 2026-05 | U133: Russia: Russian alt (Mednote, Doctis) due to GDPR/152-FZ + sanctions. | V133: 22000 | W133: 28000 | X133: 18000 | Y133: 1800000
A134: 133 | B134: Telemedicine & Digital Health | C134: Wearable program - WHOOP/Garmin | D134: WHOOP Unite + Garmin Health enterprise | E134: WHOOP Unite, Garmin Health enterprise | F134: Strain/recovery tracking, performance/longevity coaching | G134: Optional upsell | H134: Optional upsell | I134: 35000 | J134: 42000 | K134: 28000 | L134: Singapore | M134: 4200000 | N134: 1 | O134: 4 | P134: 0 | Q134: 0 | R134: WHOOP Unite (200+ enterprise customers, prnewswire 2022); Garmin Health B2B | S134: Low | T134: 2026-05 | U134: Optional supplement to Oura. Russia: parallel import for hardware. | V134: 25000 | W134: 30000 | X134: 20000 | Y134: 2400000
A135: 134 | B135: Telemedicine & Digital Health | C135: Wearable program - rings | D135: Oura Ring Business deployment | E135: Oura for Business, Ultrahuman Ring, RingConn | F135: Member sleep/HRV/recovery tracking; lifelong engagement hook | G135: Six Senses Place-tier | H135: Lanserhof/CLP-tier | I135: 65000 | J135: 80000 | K135: 55000 | L135: Singapore | M135: 7500000 | N135: 1 | O135: 4 | P135: 0 | Q135: 0 | R135: Oura for Business B2B (sacra.com 23% revenue); ~200 rings @ $300 + dashboard | S135: Medium | T135: 2026-05 | U135: Initial fleet 150-250 rings + B2B dashboard; replenishment ~25%/yr. | V135: 18000 | W135: 22000 | X135: 14000 | Y135: 1800000

Sheet Capex Summary by Tier
A1: CAPEX SUMMARY BY TIER
A2: Live roll-up from Master List via SUMPRODUCT. Edit prices in Master List → totals refresh.
A3: keys_count | B3: 90 | C3: ← editable input (mid-point of 80–100 keys range)
A4: FX RUB / EUR | B4: 92
A5: FX RUB / USD | B5: 85
A7: REGION — Europe (€)
A8: Group | B8: Lanserhof/CLP-tier | C8: SHA/Chenot-tier | D8: Six Senses Place-tier
A9: Total Medical capex | B9: =SUMPRODUCT((((1*('Equipment Master List'!$G$2:$G$135="Six Senses Place-tier")+2*('Equipment Master List'!$G$2:$G$135="SHA/Chenot-tier")+3*('Equipment Master List'!$G$2:$G$135="Lanserhof/CLP-tier"))>0)*((1*('Equipment Master List'!$G$2:$G$135="Six Senses Place-tier")+2*('Equipment Master List'!$G$2:$G$135="SHA/Chenot-tier")+3*('Equipment Master List'!$G$2:$G$135="Lanserhof/CLP-tier"))<=3))*(('Equipment Master List'!$B$2:$B$135="Diagnostic Imaging")+('Equipment Master List'!$B$2:$B$135="Laboratory & Biomarkers")+('Equipment Master List'!$B$2:$B$135="Cardiology & Pulmonology")+('Equipment Master List'!$B$2:$B$135="Sleep & Neurology")+('Equipment Master List'!$B$2:$B$135="IV & Infusion")+('Equipment Master List'!$B$2:$B$135="Aesthetic & Regenerative")+('Equipment Master List'!$B$2:$B$135="Nutrition & GI Diagnostics")+('Equipment Master List'!$B$2:$B$135="Body Composition & Performance")+('Equipment Master List'!$B$2:$B$135="Telemedicine & Digital Health"))*IFERROR('Equipment Master List'!$N$2:$N$135+0,0)*IFERROR('Equipment Master List'!$I$2:$I$135+0,0)) -> 7636500 | C9: =SUMPRODUCT((((1*('Equipment Master List'!$G$2:$G$135="Six Senses Place-tier")+2*('Equipment Master List'!$G$2:$G$135="SHA/Chenot-tier")+3*('Equipment Master List'!$G$2:$G$135="Lanserhof/CLP-tier"))>0)*((1*('Equipment Master List'!$G$2:$G$135="Six Senses Place-tier")+2*('Equipment Master List'!$G$2:$G$135="SHA/Chenot-tier")+3*('Equipment Master List'!$G$2:$G$135="Lanserhof/CLP-tier"))<=2))*(('Equipment Master List'!$B$2:$B$135="Diagnostic Imaging")+('Equipment Master List'!$B$2:$B$135="Laboratory & Biomarkers")+('Equipment Master List'!$B$2:$B$135="Cardiology & Pulmonology")+('Equipment Master List'!$B$2:$B$135="Sleep & Neurology")+('Equipment Master List'!$B$2:$B$135="IV & Infusion")+('Equipment Master List'!$B$2:$B$135="Aesthetic & Regenerative")+('Equipment Master List'!$B$2:$B$135="Nutrition & GI Diagnostics")+('Equipment Master List'!$B$2:$B$135="Body Composition & Performance")+('Equipment Master List'!$B$2:$B$135="Telemedicine & Digital Health"))*IFERROR('Equipment Master List'!$N$2:$N$135+0,0)*IFERROR('Equipment Master List'!$I$2:$I$135+0,0)) -> 2222500 | D9: =SUMPRODUCT((((1*('Equipment Master List'!$G$2:$G$135="Six Senses Place-tier")+2*('Equipment Master List'!$G$2:$G$135="SHA/Chenot-tier")+3*('Equipment Master List'!$G$2:$G$135="Lanserhof/CLP-tier"))>0)*((1*('Equipment Master List'!$G$2:$G$135="Six Senses Place-tier")+2*('Equipment Master List'!$G$2:$G$135="SHA/Chenot-tier")+3*('Equipment Master List'!$G$2:$G$135="Lanserhof/CLP-tier"))<=1))*(('Equipment Master List'!$B$2:$B$135="Diagnostic Imaging")+('Equipment Master List'!$B$2:$B$135="Laboratory & Biomarkers")+('Equipment Master List'!$B$2:$B$135="Cardiology & Pulmonology")+('Equipment Master List'!$B$2:$B$135="Sleep & Neurology")+('Equipment Master List'!$B$2:$B$135="IV & Infusion")+('Equipment Master List'!$B$2:$B$135="Aesthetic & Regenerative")+('Equipment Master List'!$B$2:$B$135="Nutrition & GI Diagnostics")+('Equipment Master List'!$B$2:$B$135="Body Composition & Performance")+('Equipment Master List'!$B$2:$B$135="Telemedicine & Digital Health"))*IFERROR('Equipment Master List'!$N$2:$N$135+0,0)*IFERROR('Equipment Master List'!$I$2:$I$135+0,0)) -> 279000
A10: Total Spa & Recovery capex | B10: =SUMPRODUCT((((1*('Equipment Master List'!$G$2:$G$135="Six Senses Place-tier")+2*('Equipment Master List'!$G$2:$G$135="SHA/Chenot-tier")+3*('Equipment Master List'!$G$2:$G$135="Lanserhof/CLP-tier"))>0)*((1*('Equipment Master List'!$G$2:$G$135="Six Senses Place-tier")+2*('Equipment Master List'!$G$2:$G$135="SHA/Chenot-tier")+3*('Equipment Master List'!$G$2:$G$135="Lanserhof/CLP-tier"))<=3))*(('Equipment Master List'!$B$2:$B$135="Hydrotherapy & Spa")+('Equipment Master List'!$B$2:$B$135="Cryo & Thermal"))*IFERROR('Equipment Master List'!$N$2:$N$135+0,0)*IFERROR('Equipment Master List'!$I$2:$I$135+0,0)) -> 1626000 | C10: =SUMPRODUCT((((1*('Equipment Master List'!$G$2:$G$135="Six Senses Place-tier")+2*('Equipment Master List'!$G$2:$G$135="SHA/Chenot-tier")+3*('Equipment Master List'!$G$2:$G$135="Lanserhof/CLP-tier"))>0)*((1*('Equipment Master List'!$G$2:$G$135="Six Senses Place-tier")+2*('Equipment Master List'!$G$2:$G$135="SHA/Chenot-tier")+3*('Equipment Master List'!$G$2:$G$135="Lanserhof/CLP-tier"))<=2))*(('Equipment Master List'!$B$2:$B$135="Hydrotherapy & Spa")+('Equipment Master List'!$B$2:$B$135="Cryo & Thermal"))*IFERROR('Equipment Master List'!$N$2:$N$135+0,0)*IFERROR('Equipment Master List'!$I$2:$I$135+0,0)) -> 1626000 | D10: =SUMPRODUCT((((1*('Equipment Master List'!$G$2:$G$135="Six Senses Place-tier")+2*('Equipment Master List'!$G$2:$G$135="SHA/Chenot-tier")+3*('Equipment Master List'!$G$2:$G$135="Lanserhof/CLP-tier"))>0)*((1*('Equipment Master List'!$G$2:$G$135="Six Senses Place-tier")+2*('Equipment Master List'!$G$2:$G$135="SHA/Chenot-tier")+3*('Equipment Master List'!$G$2:$G$135="Lanserhof/CLP-tier"))<=1))*(('Equipment Master List'!$B$2:$B$135="Hydrotherapy & Spa")+('Equipment Master List'!$B$2:$B$135="Cryo & Thermal"))*IFERROR('Equipment Master List'!$N$2:$N$135+0,0)*IFERROR('Equipment Master List'!$I$2:$I$135+0,0)) -> 1626000
A11: Total Fitness & Movement capex | B11: =SUMPRODUCT((((1*('Equipment Master List'!$G$2:$G$135="Six Senses Place-tier")+2*('Equipment Master List'!$G$2:$G$135="SHA/Chenot-tier")+3*('Equipment Master List'!$G$2:$G$135="Lanserhof/CLP-tier"))>0)*((1*('Equipment Master List'!$G$2:$G$135="Six Senses Place-tier")+2*('Equipment Master List'!$G$2:$G$135="SHA/Chenot-tier")+3*('Equipment Master List'!$G$2:$G$135="Lanserhof/CLP-tier"))<=3))*(('Equipment Master List'!$B$2:$B$135="Movement & Rehab")+('Equipment Master List'!$B$2:$B$135="Gym & Strength"))*IFERROR('Equipment Master List'!$N$2:$N$135+0,0)*IFERROR('Equipment Master List'!$I$2:$I$135+0,0)) -> 1335000 | C11: =SUMPRODUCT((((1*('Equipment Master List'!$G$2:$G$135="Six Senses Place-tier")+2*('Equipment Master List'!$G$2:$G$135="SHA/Chenot-tier")+3*('Equipment Master List'!$G$2:$G$135="Lanserhof/CLP-tier"))>0)*((1*('Equipment Master List'!$G$2:$G$135="Six Senses Place-tier")+2*('Equipment Master List'!$G$2:$G$135="SHA/Chenot-tier")+3*('Equipment Master List'!$G$2:$G$135="Lanserhof/CLP-tier"))<=2))*(('Equipment Master List'!$B$2:$B$135="Movement & Rehab")+('Equipment Master List'!$B$2:$B$135="Gym & Strength"))*IFERROR('Equipment Master List'!$N$2:$N$135+0,0)*IFERROR('Equipment Master List'!$I$2:$I$135+0,0)) -> 581000 | D11: =SUMPRODUCT((((1*('Equipment Master List'!$G$2:$G$135="Six Senses Place-tier")+2*('Equipment Master List'!$G$2:$G$135="SHA/Chenot-tier")+3*('Equipment Master List'!$G$2:$G$135="Lanserhof/CLP-tier"))>0)*((1*('Equipment Master List'!$G$2:$G$135="Six Senses Place-tier")+2*('Equipment Master List'!$G$2:$G$135="SHA/Chenot-tier")+3*('Equipment Master List'!$G$2:$G$135="Lanserhof/CLP-tier"))<=1))*(('Equipment Master List'!$B$2:$B$135="Movement & Rehab")+('Equipment Master List'!$B$2:$B$135="Gym & Strength"))*IFERROR('Equipment Master List'!$N$2:$N$135+0,0)*IFERROR('Equipment Master List'!$I$2:$I$135+0,0)) -> 581000
A12: Total IT & Software capex (upfront) | B12: =SUMPRODUCT((((1*('Equipment Master List'!$G$2:$G$135="Six Senses Place-tier")+2*('Equipment Master List'!$G$2:$G$135="SHA/Chenot-tier")+3*('Equipment Master List'!$G$2:$G$135="Lanserhof/CLP-tier"))>0)*((1*('Equipment Master List'!$G$2:$G$135="Six Senses Place-tier")+2*('Equipment Master List'!$G$2:$G$135="SHA/Chenot-tier")+3*('Equipment Master List'!$G$2:$G$135="Lanserhof/CLP-tier"))<=3))*(('Equipment Master List'!$B$2:$B$135="IT, EHR, Patient Software"))*IFERROR('Equipment Master List'!$N$2:$N$135+0,0)*IFERROR('Equipment Master List'!$I$2:$I$135+0,0)) -> 1000000 | C12: =SUMPRODUCT((((1*('Equipment Master List'!$G$2:$G$135="Six Senses Place-tier")+2*('Equipment Master List'!$G$2:$G$135="SHA/Chenot-tier")+3*('Equipment Master List'!$G$2:$G$135="Lanserhof/CLP-tier"))>0)*((1*('Equipment Master List'!$G$2:$G$135="Six Senses Place-tier")+2*('Equipment Master List'!$G$2:$G$135="SHA/Chenot-tier")+3*('Equipment Master List'!$G$2:$G$135="Lanserhof/CLP-tier"))<=2))*(('Equipment Master List'!$B$2:$B$135="IT, EHR, Patient Software"))*IFERROR('Equipment Master List'!$N$2:$N$135+0,0)*IFERROR('Equipment Master List'!$I$2:$I$135+0,0)) -> 1000000 | D12: =SUMPRODUCT((((1*('Equipment Master List'!$G$2:$G$135="Six Senses Place-tier")+2*('Equipment Master List'!$G$2:$G$135="SHA/Chenot-tier")+3*('Equipment Master List'!$G$2:$G$135="Lanserhof/CLP-tier"))>0)*((1*('Equipment Master List'!$G$2:$G$135="Six Senses Place-tier")+2*('Equipment Master List'!$G$2:$G$135="SHA/Chenot-tier")+3*('Equipment Master List'!$G$2:$G$135="Lanserhof/CLP-tier"))<=1))*(('Equipment Master List'!$B$2:$B$135="IT, EHR, Patient Software"))*IFERROR('Equipment Master List'!$N$2:$N$135+0,0)*IFERROR('Equipment Master List'!$I$2:$I$135+0,0)) -> 820000
A13: Total Kitchen & F&B capex | B13: =SUMPRODUCT((((1*('Equipment Master List'!$G$2:$G$135="Six Senses Place-tier")+2*('Equipment Master List'!$G$2:$G$135="SHA/Chenot-tier")+3*('Equipment Master List'!$G$2:$G$135="Lanserhof/CLP-tier"))>0)*((1*('Equipment Master List'!$G$2:$G$135="Six Senses Place-tier")+2*('Equipment Master List'!$G$2:$G$135="SHA/Chenot-tier")+3*('Equipment Master List'!$G$2:$G$135="Lanserhof/CLP-tier"))<=3))*(('Equipment Master List'!$B$2:$B$135="Kitchen & F&B"))*IFERROR('Equipment Master List'!$N$2:$N$135+0,0)*IFERROR('Equipment Master List'!$I$2:$I$135+0,0)) -> 1056000 | C13: =SUMPRODUCT((((1*('Equipment Master List'!$G$2:$G$135="Six Senses Place-tier")+2*('Equipment Master List'!$G$2:$G$135="SHA/Chenot-tier")+3*('Equipment Master List'!$G$2:$G$135="Lanserhof/CLP-tier"))>0)*((1*('Equipment Master List'!$G$2:$G$135="Six Senses Place-tier")+2*('Equipment Master List'!$G$2:$G$135="SHA/Chenot-tier")+3*('Equipment Master List'!$G$2:$G$135="Lanserhof/CLP-tier"))<=2))*(('Equipment Master List'!$B$2:$B$135="Kitchen & F&B"))*IFERROR('Equipment Master List'!$N$2:$N$135+0,0)*IFERROR('Equipment Master List'!$I$2:$I$135+0,0)) -> 1056000 | D13: =SUMPRODUCT((((1*('Equipment Master List'!$G$2:$G$135="Six Senses Place-tier")+2*('Equipment Master List'!$G$2:$G$135="SHA/Chenot-tier")+3*('Equipment Master List'!$G$2:$G$135="Lanserhof/CLP-tier"))>0)*((1*('Equipment Master List'!$G$2:$G$135="Six Senses Place-tier")+2*('Equipment Master List'!$G$2:$G$135="SHA/Chenot-tier")+3*('Equipment Master List'!$G$2:$G$135="Lanserhof/CLP-tier"))<=1))*(('Equipment Master List'!$B$2:$B$135="Kitchen & F&B"))*IFERROR('Equipment Master List'!$N$2:$N$135+0,0)*IFERROR('Equipment Master List'!$I$2:$I$135+0,0)) -> 1056000
A14: Total Medical Infrastructure capex | B14: =SUMPRODUCT((((1*('Equipment Master List'!$G$2:$G$135="Six Senses Place-tier")+2*('Equipment Master List'!$G$2:$G$135="SHA/Chenot-tier")+3*('Equipment Master List'!$G$2:$G$135="Lanserhof/CLP-tier"))>0)*((1*('Equipment Master List'!$G$2:$G$135="Six Senses Place-tier")+2*('Equipment Master List'!$G$2:$G$135="SHA/Chenot-tier")+3*('Equipment Master List'!$G$2:$G$135="Lanserhof/CLP-tier"))<=3))*(('Equipment Master List'!$B$2:$B$135="Medical Infrastructure"))*IFERROR('Equipment Master List'!$N$2:$N$135+0,0)*IFERROR('Equipment Master List'!$I$2:$I$135+0,0)) -> 1077000 | C14: =SUMPRODUCT((((1*('Equipment Master List'!$G$2:$G$135="Six Senses Place-tier")+2*('Equipment Master List'!$G$2:$G$135="SHA/Chenot-tier")+3*('Equipment Master List'!$G$2:$G$135="Lanserhof/CLP-tier"))>0)*((1*('Equipment Master List'!$G$2:$G$135="Six Senses Place-tier")+2*('Equipment Master List'!$G$2:$G$135="SHA/Chenot-tier")+3*('Equipment Master List'!$G$2:$G$135="Lanserhof/CLP-tier"))<=2))*(('Equipment Master List'!$B$2:$B$135="Medical Infrastructure"))*IFERROR('Equipment Master List'!$N$2:$N$135+0,0)*IFERROR('Equipment Master List'!$I$2:$I$135+0,0)) -> 127000 | D14: =SUMPRODUCT((((1*('Equipment Master List'!$G$2:$G$135="Six Senses Place-tier")+2*('Equipment Master List'!$G$2:$G$135="SHA/Chenot-tier")+3*('Equipment Master List'!$G$2:$G$135="Lanserhof/CLP-tier"))>0)*((1*('Equipment Master List'!$G$2:$G$135="Six Senses Place-tier")+2*('Equipment Master List'!$G$2:$G$135="SHA/Chenot-tier")+3*('Equipment Master List'!$G$2:$G$135="Lanserhof/CLP-tier"))<=1))*(('Equipment Master List'!$B$2:$B$135="Medical Infrastructure"))*IFERROR('Equipment Master List'!$N$2:$N$135+0,0)*IFERROR('Equipment Master List'!$I$2:$I$135+0,0)) -> 0
A15: TOTAL CAPEX | B15: =SUM(B9:B14) -> 13730500 | C15: =SUM(C9:C14) -> 6612500 | D15: =SUM(D9:D14) -> 4362000
A16: Capex per key | B16: =B15/$B$3 -> 152561.11 | C16: =C15/$B$3 -> 73472.222 | D16: =D15/$B$3 -> 48466.667
A18: REGION — North America ($)
A19: Group | B19: Lanserhof/CLP-tier | C19: SHA/Chenot-tier | D19: Six Senses Place-tier
A20: Total Medical capex | B20: =SUMPRODUCT((((1*('Equipment Master List'!$G$2:$G$135="Six Senses Place-tier")+2*('Equipment Master List'!$G$2:$G$135="SHA/Chenot-tier")+3*('Equipment Master List'!$G$2:$G$135="Lanserhof/CLP-tier"))>0)*((1*('Equipment Master List'!$G$2:$G$135="Six Senses Place-tier")+2*('Equipment Master List'!$G$2:$G$135="SHA/Chenot-tier")+3*('Equipment Master List'!$G$2:$G$135="Lanserhof/CLP-tier"))<=3))*(('Equipment Master List'!$B$2:$B$135="Diagnostic Imaging")+('Equipment Master List'!$B$2:$B$135="Laboratory & Biomarkers")+('Equipment Master List'!$B$2:$B$135="Cardiology & Pulmonology")+('Equipment Master List'!$B$2:$B$135="Sleep & Neurology")+('Equipment Master List'!$B$2:$B$135="IV & Infusion")+('Equipment Master List'!$B$2:$B$135="Aesthetic & Regenerative")+('Equipment Master List'!$B$2:$B$135="Nutrition & GI Diagnostics")+('Equipment Master List'!$B$2:$B$135="Body Composition & Performance")+('Equipment Master List'!$B$2:$B$135="Telemedicine & Digital Health"))*IFERROR('Equipment Master List'!$N$2:$N$135+0,0)*IFERROR('Equipment Master List'!$J$2:$J$135+0,0)) -> 8738700 | C20: =SUMPRODUCT((((1*('Equipment Master List'!$G$2:$G$135="Six Senses Place-tier")+2*('Equipment Master List'!$G$2:$G$135="SHA/Chenot-tier")+3*('Equipment Master List'!$G$2:$G$135="Lanserhof/CLP-tier"))>0)*((1*('Equipment Master List'!$G$2:$G$135="Six Senses Place-tier")+2*('Equipment Master List'!$G$2:$G$135="SHA/Chenot-tier")+3*('Equipment Master List'!$G$2:$G$135="Lanserhof/CLP-tier"))<=2))*(('Equipment Master List'!$B$2:$B$135="Diagnostic Imaging")+('Equipment Master List'!$B$2:$B$135="Laboratory & Biomarkers")+('Equipment Master List'!$B$2:$B$135="Cardiology & Pulmonology")+('Equipment Master List'!$B$2:$B$135="Sleep & Neurology")+('Equipment Master List'!$B$2:$B$135="IV & Infusion")+('Equipment Master List'!$B$2:$B$135="Aesthetic & Regenerative")+('Equipment Master List'!$B$2:$B$135="Nutrition & GI Diagnostics")+('Equipment Master List'!$B$2:$B$135="Body Composition & Performance")+('Equipment Master List'!$B$2:$B$135="Telemedicine & Digital Health"))*IFERROR('Equipment Master List'!$N$2:$N$135+0,0)*IFERROR('Equipment Master List'!$J$2:$J$135+0,0)) -> 2577700 | D20: =SUMPRODUCT((((1*('Equipment Master List'!$G$2:$G$135="Six Senses Place-tier")+2*('Equipment Master List'!$G$2:$G$135="SHA/Chenot-tier")+3*('Equipment Master List'!$G$2:$G$135="Lanserhof/CLP-tier"))>0)*((1*('Equipment Master List'!$G$2:$G$135="Six Senses Place-tier")+2*('Equipment Master List'!$G$2:$G$135="SHA/Chenot-tier")+3*('Equipment Master List'!$G$2:$G$135="Lanserhof/CLP-tier"))<=1))*(('Equipment Master List'!$B$2:$B$135="Diagnostic Imaging")+('Equipment Master List'!$B$2:$B$135="Laboratory & Biomarkers")+('Equipment Master List'!$B$2:$B$135="Cardiology & Pulmonology")+('Equipment Master List'!$B$2:$B$135="Sleep & Neurology")+('Equipment Master List'!$B$2:$B$135="IV & Infusion")+('Equipment Master List'!$B$2:$B$135="Aesthetic & Regenerative")+('Equipment Master List'!$B$2:$B$135="Nutrition & GI Diagnostics")+('Equipment Master List'!$B$2:$B$135="Body Composition & Performance")+('Equipment Master List'!$B$2:$B$135="Telemedicine & Digital Health"))*IFERROR('Equipment Master List'!$N$2:$N$135+0,0)*IFERROR('Equipment Master List'!$J$2:$J$135+0,0)) -> 337200
A21: Total Spa & Recovery capex | B21: =SUMPRODUCT((((1*('Equipment Master List'!$G$2:$G$135="Six Senses Place-tier")+2*('Equipment Master List'!$G$2:$G$135="SHA/Chenot-tier")+3*('Equipment Master List'!$G$2:$G$135="Lanserhof/CLP-tier"))>0)*((1*('Equipment Master List'!$G$2:$G$135="Six Senses Place-tier")+2*('Equipment Master List'!$G$2:$G$135="SHA/Chenot-tier")+3*('Equipment Master List'!$G$2:$G$135="Lanserhof/CLP-tier"))<=3))*(('Equipment Master List'!$B$2:$B$135="Hydrotherapy & Spa")+('Equipment Master List'!$B$2:$B$135="Cryo & Thermal"))*IFERROR('Equipment Master List'!$N$2:$N$135+0,0)*IFERROR('Equipment Master List'!$J$2:$J$135+0,0)) -> 1945200 | C21: =SUMPRODUCT((((1*('Equipment Master List'!$G$2:$G$135="Six Senses Place-tier")+2*('Equipment Master List'!$G$2:$G$135="SHA/Chenot-tier")+3*('Equipment Master List'!$G$2:$G$135="Lanserhof/CLP-tier"))>0)*((1*('Equipment Master List'!$G$2:$G$135="Six Senses Place-tier")+2*('Equipment Master List'!$G$2:$G$135="SHA/Chenot-tier")+3*('Equipment Master List'!$G$2:$G$135="Lanserhof/CLP-tier"))<=2))*(('Equipment Master List'!$B$2:$B$135="Hydrotherapy & Spa")+('Equipment Master List'!$B$2:$B$135="Cryo & Thermal"))*IFERROR('Equipment Master List'!$N$2:$N$135+0,0)*IFERROR('Equipment Master List'!$J$2:$J$135+0,0)) -> 1945200 | D21: =SUMPRODUCT((((1*('Equipment Master List'!$G$2:$G$135="Six Senses Place-tier")+2*('Equipment Master List'!$G$2:$G$135="SHA/Chenot-tier")+3*('Equipment Master List'!$G$2:$G$135="Lanserhof/CLP-tier"))>0)*((1*('Equipment Master List'!$G$2:$G$135="Six Senses Place-tier")+2*('Equipment Master List'!$G$2:$G$135="SHA/Chenot-tier")+3*('Equipment Master List'!$G$2:$G$135="Lanserhof/CLP-tier"))<=1))*(('Equipment Master List'!$B$2:$B$135="Hydrotherapy & Spa")+('Equipment Master List'!$B$2:$B$135="Cryo & Thermal"))*IFERROR('Equipment Master List'!$N$2:$N$135+0,0)*IFERROR('Equipment Master List'!$J$2:$J$135+0,0)) -> 1945200
A22: Total Fitness & Movement capex | B22: =SUMPRODUCT((((1*('Equipment Master List'!$G$2:$G$135="Six Senses Place-tier")+2*('Equipment Master List'!$G$2:$G$135="SHA/Chenot-tier")+3*('Equipment Master List'!$G$2:$G$135="Lanserhof/CLP-tier"))>0)*((1*('Equipment Master List'!$G$2:$G$135="Six Senses Place-tier")+2*('Equipment Master List'!$G$2:$G$135="SHA/Chenot-tier")+3*('Equipment Master List'!$G$2:$G$135="Lanserhof/CLP-tier"))<=3))*(('Equipment Master List'!$B$2:$B$135="Movement & Rehab")+('Equipment Master List'!$B$2:$B$135="Gym & Strength"))*IFERROR('Equipment Master List'!$N$2:$N$135+0,0)*IFERROR('Equipment Master List'!$J$2:$J$135+0,0)) -> 1585000 | C22: =SUMPRODUCT((((1*('Equipment Master List'!$G$2:$G$135="Six Senses Place-tier")+2*('Equipment Master List'!$G$2:$G$135="SHA/Chenot-tier")+3*('Equipment Master List'!$G$2:$G$135="Lanserhof/CLP-tier"))>0)*((1*('Equipment Master List'!$G$2:$G$135="Six Senses Place-tier")+2*('Equipment Master List'!$G$2:$G$135="SHA/Chenot-tier")+3*('Equipment Master List'!$G$2:$G$135="Lanserhof/CLP-tier"))<=2))*(('Equipment Master List'!$B$2:$B$135="Movement & Rehab")+('Equipment Master List'!$B$2:$B$135="Gym & Strength"))*IFERROR('Equipment Master List'!$N$2:$N$135+0,0)*IFERROR('Equipment Master List'!$J$2:$J$135+0,0)) -> 687000 | D22: =SUMPRODUCT((((1*('Equipment Master List'!$G$2:$G$135="Six Senses Place-tier")+2*('Equipment Master List'!$G$2:$G$135="SHA/Chenot-tier")+3*('Equipment Master List'!$G$2:$G$135="Lanserhof/CLP-tier"))>0)*((1*('Equipment Master List'!$G$2:$G$135="Six Senses Place-tier")+2*('Equipment Master List'!$G$2:$G$135="SHA/Chenot-tier")+3*('Equipment Master List'!$G$2:$G$135="Lanserhof/CLP-tier"))<=1))*(('Equipment Master List'!$B$2:$B$135="Movement & Rehab")+('Equipment Master List'!$B$2:$B$135="Gym & Strength"))*IFERROR('Equipment Master List'!$N$2:$N$135+0,0)*IFERROR('Equipment Master List'!$J$2:$J$135+0,0)) -> 687000
A23: Total IT & Software capex (upfront) | B23: =SUMPRODUCT((((1*('Equipment Master List'!$G$2:$G$135="Six Senses Place-tier")+2*('Equipment Master List'!$G$2:$G$135="SHA/Chenot-tier")+3*('Equipment Master List'!$G$2:$G$135="Lanserhof/CLP-tier"))>0)*((1*('Equipment Master List'!$G$2:$G$135="Six Senses Place-tier")+2*('Equipment Master List'!$G$2:$G$135="SHA/Chenot-tier")+3*('Equipment Master List'!$G$2:$G$135="Lanserhof/CLP-tier"))<=3))*(('Equipment Master List'!$B$2:$B$135="IT, EHR, Patient Software"))*IFERROR('Equipment Master List'!$N$2:$N$135+0,0)*IFERROR('Equipment Master List'!$J$2:$J$135+0,0)) -> 1208000 | C23: =SUMPRODUCT((((1*('Equipment Master List'!$G$2:$G$135="Six Senses Place-tier")+2*('Equipment Master List'!$G$2:$G$135="SHA/Chenot-tier")+3*('Equipment Master List'!$G$2:$G$135="Lanserhof/CLP-tier"))>0)*((1*('Equipment Master List'!$G$2:$G$135="Six Senses Place-tier")+2*('Equipment Master List'!$G$2:$G$135="SHA/Chenot-tier")+3*('Equipment Master List'!$G$2:$G$135="Lanserhof/CLP-tier"))<=2))*(('Equipment Master List'!$B$2:$B$135="IT, EHR, Patient Software"))*IFERROR('Equipment Master List'!$N$2:$N$135+0,0)*IFERROR('Equipment Master List'!$J$2:$J$135+0,0)) -> 1208000 | D23: =SUMPRODUCT((((1*('Equipment Master List'!$G$2:$G$135="Six Senses Place-tier")+2*('Equipment Master List'!$G$2:$G$135="SHA/Chenot-tier")+3*('Equipment Master List'!$G$2:$G$135="Lanserhof/CLP-tier"))>0)*((1*('Equipment Master List'!$G$2:$G$135="Six Senses Place-tier")+2*('Equipment Master List'!$G$2:$G$135="SHA/Chenot-tier")+3*('Equipment Master List'!$G$2:$G$135="Lanserhof/CLP-tier"))<=1))*(('Equipment Master List'!$B$2:$B$135="IT, EHR, Patient Software"))*IFERROR('Equipment Master List'!$N$2:$N$135+0,0)*IFERROR('Equipment Master List'!$J$2:$J$135+0,0)) -> 988000
A24: Total Kitchen & F&B capex | B24: =SUMPRODUCT((((1*('Equipment Master List'!$G$2:$G$135="Six Senses Place-tier")+2*('Equipment Master List'!$G$2:$G$135="SHA/Chenot-tier")+3*('Equipment Master List'!$G$2:$G$135="Lanserhof/CLP-tier"))>0)*((1*('Equipment Master List'!$G$2:$G$135="Six Senses Place-tier")+2*('Equipment Master List'!$G$2:$G$135="SHA/Chenot-tier")+3*('Equipment Master List'!$G$2:$G$135="Lanserhof/CLP-tier"))<=3))*(('Equipment Master List'!$B$2:$B$135="Kitchen & F&B"))*IFERROR('Equipment Master List'!$N$2:$N$135+0,0)*IFERROR('Equipment Master List'!$J$2:$J$135+0,0)) -> 1243800 | C24: =SUMPRODUCT((((1*('Equipment Master List'!$G$2:$G$135="Six Senses Place-tier")+2*('Equipment Master List'!$G$2:$G$135="SHA/Chenot-tier")+3*('Equipment Master List'!$G$2:$G$135="Lanserhof/CLP-tier"))>0)*((1*('Equipment Master List'!$G$2:$G$135="Six Senses Place-tier")+2*('Equipment Master List'!$G$2:$G$135="SHA/Chenot-tier")+3*('Equipment Master List'!$G$2:$G$135="Lanserhof/CLP-tier"))<=2))*(('Equipment Master List'!$B$2:$B$135="Kitchen & F&B"))*IFERROR('Equipment Master List'!$N$2:$N$135+0,0)*IFERROR('Equipment Master List'!$J$2:$J$135+0,0)) -> 1243800 | D24: =SUMPRODUCT((((1*('Equipment Master List'!$G$2:$G$135="Six Senses Place-tier")+2*('Equipment Master List'!$G$2:$G$135="SHA/Chenot-tier")+3*('Equipment Master List'!$G$2:$G$135="Lanserhof/CLP-tier"))>0)*((1*('Equipment Master List'!$G$2:$G$135="Six Senses Place-tier")+2*('Equipment Master List'!$G$2:$G$135="SHA/Chenot-tier")+3*('Equipment Master List'!$G$2:$G$135="Lanserhof/CLP-tier"))<=1))*(('Equipment Master List'!$B$2:$B$135="Kitchen & F&B"))*IFERROR('Equipment Master List'!$N$2:$N$135+0,0)*IFERROR('Equipment Master List'!$J$2:$J$135+0,0)) -> 1243800
A25: Total Medical Infrastructure capex | B25: =SUMPRODUCT((((1*('Equipment Master List'!$G$2:$G$135="Six Senses Place-tier")+2*('Equipment Master List'!$G$2:$G$135="SHA/Chenot-tier")+3*('Equipment Master List'!$G$2:$G$135="Lanserhof/CLP-tier"))>0)*((1*('Equipment Master List'!$G$2:$G$135="Six Senses Place-tier")+2*('Equipment Master List'!$G$2:$G$135="SHA/Chenot-tier")+3*('Equipment Master List'!$G$2:$G$135="Lanserhof/CLP-tier"))<=3))*(('Equipment Master List'!$B$2:$B$135="Medical Infrastructure"))*IFERROR('Equipment Master List'!$N$2:$N$135+0,0)*IFERROR('Equipment Master List'!$J$2:$J$135+0,0)) -> 1295000 | C25: =SUMPRODUCT((((1*('Equipment Master List'!$G$2:$G$135="Six Senses Place-tier")+2*('Equipment Master List'!$G$2:$G$135="SHA/Chenot-tier")+3*('Equipment Master List'!$G$2:$G$135="Lanserhof/CLP-tier"))>0)*((1*('Equipment Master List'!$G$2:$G$135="Six Senses Place-tier")+2*('Equipment Master List'!$G$2:$G$135="SHA/Chenot-tier")+3*('Equipment Master List'!$G$2:$G$135="Lanserhof/CLP-tier"))<=2))*(('Equipment Master List'!$B$2:$B$135="Medical Infrastructure"))*IFERROR('Equipment Master List'!$N$2:$N$135+0,0)*IFERROR('Equipment Master List'!$J$2:$J$135+0,0)) -> 155000 | D25: =SUMPRODUCT((((1*('Equipment Master List'!$G$2:$G$135="Six Senses Place-tier")+2*('Equipment Master List'!$G$2:$G$135="SHA/Chenot-tier")+3*('Equipment Master List'!$G$2:$G$135="Lanserhof/CLP-tier"))>0)*((1*('Equipment Master List'!$G$2:$G$135="Six Senses Place-tier")+2*('Equipment Master List'!$G$2:$G$135="SHA/Chenot-tier")+3*('Equipment Master List'!$G$2:$G$135="Lanserhof/CLP-tier"))<=1))*(('Equipment Master List'!$B$2:$B$135="Medical Infrastructure"))*IFERROR('Equipment Master List'!$N$2:$N$135+0,0)*IFERROR('Equipment Master List'!$J$2:$J$135+0,0)) -> 0
A26: TOTAL CAPEX | B26: =SUM(B20:B25) -> 16015700 | C26: =SUM(C20:C25) -> 7816700 | D26: =SUM(D20:D25) -> 5201200
A27: Capex per key | B27: =B26/$B$3 -> 177952.22 | C27: =C26/$B$3 -> 86852.222 | D27: =D26/$B$3 -> 57791.111
A29: REGION — Asia ($)
A30: Group | B30: Lanserhof/CLP-tier | C30: SHA/Chenot-tier | D30: Six Senses Place-tier
A31: Total Medical capex | B31: =SUMPRODUCT((((1*('Equipment Master List'!$G$2:$G$135="Six Senses Place-tier")+2*('Equipment Master List'!$G$2:$G$135="SHA/Chenot-tier")+3*('Equipment Master List'!$G$2:$G$135="Lanserhof/CLP-tier"))>0)*((1*('Equipment Master List'!$G$2:$G$135="Six Senses Place-tier")+2*('Equipment Master List'!$G$2:$G$135="SHA/Chenot-tier")+3*('Equipment Master List'!$G$2:$G$135="Lanserhof/CLP-tier"))<=3))*(('Equipment Master List'!$B$2:$B$135="Diagnostic Imaging")+('Equipment Master List'!$B$2:$B$135="Laboratory & Biomarkers")+('Equipment Master List'!$B$2:$B$135="Cardiology & Pulmonology")+('Equipment Master List'!$B$2:$B$135="Sleep & Neurology")+('Equipment Master List'!$B$2:$B$135="IV & Infusion")+('Equipment Master List'!$B$2:$B$135="Aesthetic & Regenerative")+('Equipment Master List'!$B$2:$B$135="Nutrition & GI Diagnostics")+('Equipment Master List'!$B$2:$B$135="Body Composition & Performance")+('Equipment Master List'!$B$2:$B$135="Telemedicine & Digital Health"))*IFERROR('Equipment Master List'!$N$2:$N$135+0,0)*IFERROR('Equipment Master List'!$K$2:$K$135+0,0)) -> 6556200 | C31: =SUMPRODUCT((((1*('Equipment Master List'!$G$2:$G$135="Six Senses Place-tier")+2*('Equipment Master List'!$G$2:$G$135="SHA/Chenot-tier")+3*('Equipment Master List'!$G$2:$G$135="Lanserhof/CLP-tier"))>0)*((1*('Equipment Master List'!$G$2:$G$135="Six Senses Place-tier")+2*('Equipment Master List'!$G$2:$G$135="SHA/Chenot-tier")+3*('Equipment Master List'!$G$2:$G$135="Lanserhof/CLP-tier"))<=2))*(('Equipment Master List'!$B$2:$B$135="Diagnostic Imaging")+('Equipment Master List'!$B$2:$B$135="Laboratory & Biomarkers")+('Equipment Master List'!$B$2:$B$135="Cardiology & Pulmonology")+('Equipment Master List'!$B$2:$B$135="Sleep & Neurology")+('Equipment Master List'!$B$2:$B$135="IV & Infusion")+('Equipment Master List'!$B$2:$B$135="Aesthetic & Regenerative")+('Equipment Master List'!$B$2:$B$135="Nutrition & GI Diagnostics")+('Equipment Master List'!$B$2:$B$135="Body Composition & Performance")+('Equipment Master List'!$B$2:$B$135="Telemedicine & Digital Health"))*IFERROR('Equipment Master List'!$N$2:$N$135+0,0)*IFERROR('Equipment Master List'!$K$2:$K$135+0,0)) -> 1883200 | D31: =SUMPRODUCT((((1*('Equipment Master List'!$G$2:$G$135="Six Senses Place-tier")+2*('Equipment Master List'!$G$2:$G$135="SHA/Chenot-tier")+3*('Equipment Master List'!$G$2:$G$135="Lanserhof/CLP-tier"))>0)*((1*('Equipment Master List'!$G$2:$G$135="Six Senses Place-tier")+2*('Equipment Master List'!$G$2:$G$135="SHA/Chenot-tier")+3*('Equipment Master List'!$G$2:$G$135="Lanserhof/CLP-tier"))<=1))*(('Equipment Master List'!$B$2:$B$135="Diagnostic Imaging")+('Equipment Master List'!$B$2:$B$135="Laboratory & Biomarkers")+('Equipment Master List'!$B$2:$B$135="Cardiology & Pulmonology")+('Equipment Master List'!$B$2:$B$135="Sleep & Neurology")+('Equipment Master List'!$B$2:$B$135="IV & Infusion")+('Equipment Master List'!$B$2:$B$135="Aesthetic & Regenerative")+('Equipment Master List'!$B$2:$B$135="Nutrition & GI Diagnostics")+('Equipment Master List'!$B$2:$B$135="Body Composition & Performance")+('Equipment Master List'!$B$2:$B$135="Telemedicine & Digital Health"))*IFERROR('Equipment Master List'!$N$2:$N$135+0,0)*IFERROR('Equipment Master List'!$K$2:$K$135+0,0)) -> 247000
A32: Total Spa & Recovery capex | B32: =SUMPRODUCT((((1*('Equipment Master List'!$G$2:$G$135="Six Senses Place-tier")+2*('Equipment Master List'!$G$2:$G$135="SHA/Chenot-tier")+3*('Equipment Master List'!$G$2:$G$135="Lanserhof/CLP-tier"))>0)*((1*('Equipment Master List'!$G$2:$G$135="Six Senses Place-tier")+2*('Equipment Master List'!$G$2:$G$135="SHA/Chenot-tier")+3*('Equipment Master List'!$G$2:$G$135="Lanserhof/CLP-tier"))<=3))*(('Equipment Master List'!$B$2:$B$135="Hydrotherapy & Spa")+('Equipment Master List'!$B$2:$B$135="Cryo & Thermal"))*IFERROR('Equipment Master List'!$N$2:$N$135+0,0)*IFERROR('Equipment Master List'!$K$2:$K$135+0,0)) -> 1528800 | C32: =SUMPRODUCT((((1*('Equipment Master List'!$G$2:$G$135="Six Senses Place-tier")+2*('Equipment Master List'!$G$2:$G$135="SHA/Chenot-tier")+3*('Equipment Master List'!$G$2:$G$135="Lanserhof/CLP-tier"))>0)*((1*('Equipment Master List'!$G$2:$G$135="Six Senses Place-tier")+2*('Equipment Master List'!$G$2:$G$135="SHA/Chenot-tier")+3*('Equipment Master List'!$G$2:$G$135="Lanserhof/CLP-tier"))<=2))*(('Equipment Master List'!$B$2:$B$135="Hydrotherapy & Spa")+('Equipment Master List'!$B$2:$B$135="Cryo & Thermal"))*IFERROR('Equipment Master List'!$N$2:$N$135+0,0)*IFERROR('Equipment Master List'!$K$2:$K$135+0,0)) -> 1528800 | D32: =SUMPRODUCT((((1*('Equipment Master List'!$G$2:$G$135="Six Senses Place-tier")+2*('Equipment Master List'!$G$2:$G$135="SHA/Chenot-tier")+3*('Equipment Master List'!$G$2:$G$135="Lanserhof/CLP-tier"))>0)*((1*('Equipment Master List'!$G$2:$G$135="Six Senses Place-tier")+2*('Equipment Master List'!$G$2:$G$135="SHA/Chenot-tier")+3*('Equipment Master List'!$G$2:$G$135="Lanserhof/CLP-tier"))<=1))*(('Equipment Master List'!$B$2:$B$135="Hydrotherapy & Spa")+('Equipment Master List'!$B$2:$B$135="Cryo & Thermal"))*IFERROR('Equipment Master List'!$N$2:$N$135+0,0)*IFERROR('Equipment Master List'!$K$2:$K$135+0,0)) -> 1528800
A33: Total Fitness & Movement capex | B33: =SUMPRODUCT((((1*('Equipment Master List'!$G$2:$G$135="Six Senses Place-tier")+2*('Equipment Master List'!$G$2:$G$135="SHA/Chenot-tier")+3*('Equipment Master List'!$G$2:$G$135="Lanserhof/CLP-tier"))>0)*((1*('Equipment Master List'!$G$2:$G$135="Six Senses Place-tier")+2*('Equipment Master List'!$G$2:$G$135="SHA/Chenot-tier")+3*('Equipment Master List'!$G$2:$G$135="Lanserhof/CLP-tier"))<=3))*(('Equipment Master List'!$B$2:$B$135="Movement & Rehab")+('Equipment Master List'!$B$2:$B$135="Gym & Strength"))*IFERROR('Equipment Master List'!$N$2:$N$135+0,0)*IFERROR('Equipment Master List'!$K$2:$K$135+0,0)) -> 1265000 | C33: =SUMPRODUCT((((1*('Equipment Master List'!$G$2:$G$135="Six Senses Place-tier")+2*('Equipment Master List'!$G$2:$G$135="SHA/Chenot-tier")+3*('Equipment Master List'!$G$2:$G$135="Lanserhof/CLP-tier"))>0)*((1*('Equipment Master List'!$G$2:$G$135="Six Senses Place-tier")+2*('Equipment Master List'!$G$2:$G$135="SHA/Chenot-tier")+3*('Equipment Master List'!$G$2:$G$135="Lanserhof/CLP-tier"))<=2))*(('Equipment Master List'!$B$2:$B$135="Movement & Rehab")+('Equipment Master List'!$B$2:$B$135="Gym & Strength"))*IFERROR('Equipment Master List'!$N$2:$N$135+0,0)*IFERROR('Equipment Master List'!$K$2:$K$135+0,0)) -> 547000 | D33: =SUMPRODUCT((((1*('Equipment Master List'!$G$2:$G$135="Six Senses Place-tier")+2*('Equipment Master List'!$G$2:$G$135="SHA/Chenot-tier")+3*('Equipment Master List'!$G$2:$G$135="Lanserhof/CLP-tier"))>0)*((1*('Equipment Master List'!$G$2:$G$135="Six Senses Place-tier")+2*('Equipment Master List'!$G$2:$G$135="SHA/Chenot-tier")+3*('Equipment Master List'!$G$2:$G$135="Lanserhof/CLP-tier"))<=1))*(('Equipment Master List'!$B$2:$B$135="Movement & Rehab")+('Equipment Master List'!$B$2:$B$135="Gym & Strength"))*IFERROR('Equipment Master List'!$N$2:$N$135+0,0)*IFERROR('Equipment Master List'!$K$2:$K$135+0,0)) -> 547000
A34: Total IT & Software capex (upfront) | B34: =SUMPRODUCT((((1*('Equipment Master List'!$G$2:$G$135="Six Senses Place-tier")+2*('Equipment Master List'!$G$2:$G$135="SHA/Chenot-tier")+3*('Equipment Master List'!$G$2:$G$135="Lanserhof/CLP-tier"))>0)*((1*('Equipment Master List'!$G$2:$G$135="Six Senses Place-tier")+2*('Equipment Master List'!$G$2:$G$135="SHA/Chenot-tier")+3*('Equipment Master List'!$G$2:$G$135="Lanserhof/CLP-tier"))<=3))*(('Equipment Master List'!$B$2:$B$135="IT, EHR, Patient Software"))*IFERROR('Equipment Master List'!$N$2:$N$135+0,0)*IFERROR('Equipment Master List'!$K$2:$K$135+0,0)) -> 803000 | C34: =SUMPRODUCT((((1*('Equipment Master List'!$G$2:$G$135="Six Senses Place-tier")+2*('Equipment Master List'!$G$2:$G$135="SHA/Chenot-tier")+3*('Equipment Master List'!$G$2:$G$135="Lanserhof/CLP-tier"))>0)*((1*('Equipment Master List'!$G$2:$G$135="Six Senses Place-tier")+2*('Equipment Master List'!$G$2:$G$135="SHA/Chenot-tier")+3*('Equipment Master List'!$G$2:$G$135="Lanserhof/CLP-tier"))<=2))*(('Equipment Master List'!$B$2:$B$135="IT, EHR, Patient Software"))*IFERROR('Equipment Master List'!$N$2:$N$135+0,0)*IFERROR('Equipment Master List'!$K$2:$K$135+0,0)) -> 803000 | D34: =SUMPRODUCT((((1*('Equipment Master List'!$G$2:$G$135="Six Senses Place-tier")+2*('Equipment Master List'!$G$2:$G$135="SHA/Chenot-tier")+3*('Equipment Master List'!$G$2:$G$135="Lanserhof/CLP-tier"))>0)*((1*('Equipment Master List'!$G$2:$G$135="Six Senses Place-tier")+2*('Equipment Master List'!$G$2:$G$135="SHA/Chenot-tier")+3*('Equipment Master List'!$G$2:$G$135="Lanserhof/CLP-tier"))<=1))*(('Equipment Master List'!$B$2:$B$135="IT, EHR, Patient Software"))*IFERROR('Equipment Master List'!$N$2:$N$135+0,0)*IFERROR('Equipment Master List'!$K$2:$K$135+0,0)) -> 653000
A35: Total Kitchen & F&B capex | B35: =SUMPRODUCT((((1*('Equipment Master List'!$G$2:$G$135="Six Senses Place-tier")+2*('Equipment Master List'!$G$2:$G$135="SHA/Chenot-tier")+3*('Equipment Master List'!$G$2:$G$135="Lanserhof/CLP-tier"))>0)*((1*('Equipment Master List'!$G$2:$G$135="Six Senses Place-tier")+2*('Equipment Master List'!$G$2:$G$135="SHA/Chenot-tier")+3*('Equipment Master List'!$G$2:$G$135="Lanserhof/CLP-tier"))<=3))*(('Equipment Master List'!$B$2:$B$135="Kitchen & F&B"))*IFERROR('Equipment Master List'!$N$2:$N$135+0,0)*IFERROR('Equipment Master List'!$K$2:$K$135+0,0)) -> 823000 | C35: =SUMPRODUCT((((1*('Equipment Master List'!$G$2:$G$135="Six Senses Place-tier")+2*('Equipment Master List'!$G$2:$G$135="SHA/Chenot-tier")+3*('Equipment Master List'!$G$2:$G$135="Lanserhof/CLP-tier"))>0)*((1*('Equipment Master List'!$G$2:$G$135="Six Senses Place-tier")+2*('Equipment Master List'!$G$2:$G$135="SHA/Chenot-tier")+3*('Equipment Master List'!$G$2:$G$135="Lanserhof/CLP-tier"))<=2))*(('Equipment Master List'!$B$2:$B$135="Kitchen & F&B"))*IFERROR('Equipment Master List'!$N$2:$N$135+0,0)*IFERROR('Equipment Master List'!$K$2:$K$135+0,0)) -> 823000 | D35: =SUMPRODUCT((((1*('Equipment Master List'!$G$2:$G$135="Six Senses Place-tier")+2*('Equipment Master List'!$G$2:$G$135="SHA/Chenot-tier")+3*('Equipment Master List'!$G$2:$G$135="Lanserhof/CLP-tier"))>0)*((1*('Equipment Master List'!$G$2:$G$135="Six Senses Place-tier")+2*('Equipment Master List'!$G$2:$G$135="SHA/Chenot-tier")+3*('Equipment Master List'!$G$2:$G$135="Lanserhof/CLP-tier"))<=1))*(('Equipment Master List'!$B$2:$B$135="Kitchen & F&B"))*IFERROR('Equipment Master List'!$N$2:$N$135+0,0)*IFERROR('Equipment Master List'!$K$2:$K$135+0,0)) -> 823000
A36: Total Medical Infrastructure capex | B36: =SUMPRODUCT((((1*('Equipment Master List'!$G$2:$G$135="Six Senses Place-tier")+2*('Equipment Master List'!$G$2:$G$135="SHA/Chenot-tier")+3*('Equipment Master List'!$G$2:$G$135="Lanserhof/CLP-tier"))>0)*((1*('Equipment Master List'!$G$2:$G$135="Six Senses Place-tier")+2*('Equipment Master List'!$G$2:$G$135="SHA/Chenot-tier")+3*('Equipment Master List'!$G$2:$G$135="Lanserhof/CLP-tier"))<=3))*(('Equipment Master List'!$B$2:$B$135="Medical Infrastructure"))*IFERROR('Equipment Master List'!$N$2:$N$135+0,0)*IFERROR('Equipment Master List'!$K$2:$K$135+0,0)) -> 834000 | C36: =SUMPRODUCT((((1*('Equipment Master List'!$G$2:$G$135="Six Senses Place-tier")+2*('Equipment Master List'!$G$2:$G$135="SHA/Chenot-tier")+3*('Equipment Master List'!$G$2:$G$135="Lanserhof/CLP-tier"))>0)*((1*('Equipment Master List'!$G$2:$G$135="Six Senses Place-tier")+2*('Equipment Master List'!$G$2:$G$135="SHA/Chenot-tier")+3*('Equipment Master List'!$G$2:$G$135="Lanserhof/CLP-tier"))<=2))*(('Equipment Master List'!$B$2:$B$135="Medical Infrastructure"))*IFERROR('Equipment Master List'!$N$2:$N$135+0,0)*IFERROR('Equipment Master List'!$K$2:$K$135+0,0)) -> 94000 | D36: =SUMPRODUCT((((1*('Equipment Master List'!$G$2:$G$135="Six Senses Place-tier")+2*('Equipment Master List'!$G$2:$G$135="SHA/Chenot-tier")+3*('Equipment Master List'!$G$2:$G$135="Lanserhof/CLP-tier"))>0)*((1*('Equipment Master List'!$G$2:$G$135="Six Senses Place-tier")+2*('Equipment Master List'!$G$2:$G$135="SHA/Chenot-tier")+3*('Equipment Master List'!$G$2:$G$135="Lanserhof/CLP-tier"))<=1))*(('Equipment Master List'!$B$2:$B$135="Medical Infrastructure"))*IFERROR('Equipment Master List'!$N$2:$N$135+0,0)*IFERROR('Equipment Master List'!$K$2:$K$135+0,0)) -> 0
A37: TOTAL CAPEX | B37: =SUM(B31:B36) -> 11810000 | C37: =SUM(C31:C36) -> 5679000 | D37: =SUM(D31:D36) -> 3798800
A38: Capex per key | B38: =B37/$B$3 -> 131222.22 | C38: =C37/$B$3 -> 63100 | D38: =D37/$B$3 -> 42208.889
A40: REGION — Russia (₽)
A41: Group | B41: Lanserhof/CLP-tier | C41: SHA/Chenot-tier | D41: Six Senses Place-tier
A42: Total Medical capex | B42: =SUMPRODUCT((((1*('Equipment Master List'!$G$2:$G$135="Six Senses Place-tier")+2*('Equipment Master List'!$G$2:$G$135="SHA/Chenot-tier")+3*('Equipment Master List'!$G$2:$G$135="Lanserhof/CLP-tier"))>0)*((1*('Equipment Master List'!$G$2:$G$135="Six Senses Place-tier")+2*('Equipment Master List'!$G$2:$G$135="SHA/Chenot-tier")+3*('Equipment Master List'!$G$2:$G$135="Lanserhof/CLP-tier"))<=3))*(('Equipment Master List'!$B$2:$B$135="Diagnostic Imaging")+('Equipment Master List'!$B$2:$B$135="Laboratory & Biomarkers")+('Equipment Master List'!$B$2:$B$135="Cardiology & Pulmonology")+('Equipment Master List'!$B$2:$B$135="Sleep & Neurology")+('Equipment Master List'!$B$2:$B$135="IV & Infusion")+('Equipment Master List'!$B$2:$B$135="Aesthetic & Regenerative")+('Equipment Master List'!$B$2:$B$135="Nutrition & GI Diagnostics")+('Equipment Master List'!$B$2:$B$135="Body Composition & Performance")+('Equipment Master List'!$B$2:$B$135="Telemedicine & Digital Health"))*IFERROR('Equipment Master List'!$N$2:$N$135+0,0)*IFERROR('Equipment Master List'!$M$2:$M$135+0,0)) -> 1046550000 | C42: =SUMPRODUCT((((1*('Equipment Master List'!$G$2:$G$135="Six Senses Place-tier")+2*('Equipment Master List'!$G$2:$G$135="SHA/Chenot-tier")+3*('Equipment Master List'!$G$2:$G$135="Lanserhof/CLP-tier"))>0)*((1*('Equipment Master List'!$G$2:$G$135="Six Senses Place-tier")+2*('Equipment Master List'!$G$2:$G$135="SHA/Chenot-tier")+3*('Equipment Master List'!$G$2:$G$135="Lanserhof/CLP-tier"))<=2))*(('Equipment Master List'!$B$2:$B$135="Diagnostic Imaging")+('Equipment Master List'!$B$2:$B$135="Laboratory & Biomarkers")+('Equipment Master List'!$B$2:$B$135="Cardiology & Pulmonology")+('Equipment Master List'!$B$2:$B$135="Sleep & Neurology")+('Equipment Master List'!$B$2:$B$135="IV & Infusion")+('Equipment Master List'!$B$2:$B$135="Aesthetic & Regenerative")+('Equipment Master List'!$B$2:$B$135="Nutrition & GI Diagnostics")+('Equipment Master List'!$B$2:$B$135="Body Composition & Performance")+('Equipment Master List'!$B$2:$B$135="Telemedicine & Digital Health"))*IFERROR('Equipment Master List'!$N$2:$N$135+0,0)*IFERROR('Equipment Master List'!$M$2:$M$135+0,0)) -> 300450000 | D42: =SUMPRODUCT((((1*('Equipment Master List'!$G$2:$G$135="Six Senses Place-tier")+2*('Equipment Master List'!$G$2:$G$135="SHA/Chenot-tier")+3*('Equipment Master List'!$G$2:$G$135="Lanserhof/CLP-tier"))>0)*((1*('Equipment Master List'!$G$2:$G$135="Six Senses Place-tier")+2*('Equipment Master List'!$G$2:$G$135="SHA/Chenot-tier")+3*('Equipment Master List'!$G$2:$G$135="Lanserhof/CLP-tier"))<=1))*(('Equipment Master List'!$B$2:$B$135="Diagnostic Imaging")+('Equipment Master List'!$B$2:$B$135="Laboratory & Biomarkers")+('Equipment Master List'!$B$2:$B$135="Cardiology & Pulmonology")+('Equipment Master List'!$B$2:$B$135="Sleep & Neurology")+('Equipment Master List'!$B$2:$B$135="IV & Infusion")+('Equipment Master List'!$B$2:$B$135="Aesthetic & Regenerative")+('Equipment Master List'!$B$2:$B$135="Nutrition & GI Diagnostics")+('Equipment Master List'!$B$2:$B$135="Body Composition & Performance")+('Equipment Master List'!$B$2:$B$135="Telemedicine & Digital Health"))*IFERROR('Equipment Master List'!$N$2:$N$135+0,0)*IFERROR('Equipment Master List'!$M$2:$M$135+0,0)) -> 33700000
A43: Total Spa & Recovery capex | B43: =SUMPRODUCT((((1*('Equipment Master List'!$G$2:$G$135="Six Senses Place-tier")+2*('Equipment Master List'!$G$2:$G$135="SHA/Chenot-tier")+3*('Equipment Master List'!$G$2:$G$135="Lanserhof/CLP-tier"))>0)*((1*('Equipment Master List'!$G$2:$G$135="Six Senses Place-tier")+2*('Equipment Master List'!$G$2:$G$135="SHA/Chenot-tier")+3*('Equipment Master List'!$G$2:$G$135="Lanserhof/CLP-tier"))<=3))*(('Equipment Master List'!$B$2:$B$135="Hydrotherapy & Spa")+('Equipment Master List'!$B$2:$B$135="Cryo & Thermal"))*IFERROR('Equipment Master List'!$N$2:$N$135+0,0)*IFERROR('Equipment Master List'!$M$2:$M$135+0,0)) -> 215440000 | C43: =SUMPRODUCT((((1*('Equipment Master List'!$G$2:$G$135="Six Senses Place-tier")+2*('Equipment Master List'!$G$2:$G$135="SHA/Chenot-tier")+3*('Equipment Master List'!$G$2:$G$135="Lanserhof/CLP-tier"))>0)*((1*('Equipment Master List'!$G$2:$G$135="Six Senses Place-tier")+2*('Equipment Master List'!$G$2:$G$135="SHA/Chenot-tier")+3*('Equipment Master List'!$G$2:$G$135="Lanserhof/CLP-tier"))<=2))*(('Equipment Master List'!$B$2:$B$135="Hydrotherapy & Spa")+('Equipment Master List'!$B$2:$B$135="Cryo & Thermal"))*IFERROR('Equipment Master List'!$N$2:$N$135+0,0)*IFERROR('Equipment Master List'!$M$2:$M$135+0,0)) -> 215440000 | D43: =SUMPRODUCT((((1*('Equipment Master List'!$G$2:$G$135="Six Senses Place-tier")+2*('Equipment Master List'!$G$2:$G$135="SHA/Chenot-tier")+3*('Equipment Master List'!$G$2:$G$135="Lanserhof/CLP-tier"))>0)*((1*('Equipment Master List'!$G$2:$G$135="Six Senses Place-tier")+2*('Equipment Master List'!$G$2:$G$135="SHA/Chenot-tier")+3*('Equipment Master List'!$G$2:$G$135="Lanserhof/CLP-tier"))<=1))*(('Equipment Master List'!$B$2:$B$135="Hydrotherapy & Spa")+('Equipment Master List'!$B$2:$B$135="Cryo & Thermal"))*IFERROR('Equipment Master List'!$N$2:$N$135+0,0)*IFERROR('Equipment Master List'!$M$2:$M$135+0,0)) -> 215440000
A44: Total Fitness & Movement capex | B44: =SUMPRODUCT((((1*('Equipment Master List'!$G$2:$G$135="Six Senses Place-tier")+2*('Equipment Master List'!$G$2:$G$135="SHA/Chenot-tier")+3*('Equipment Master List'!$G$2:$G$135="Lanserhof/CLP-tier"))>0)*((1*('Equipment Master List'!$G$2:$G$135="Six Senses Place-tier")+2*('Equipment Master List'!$G$2:$G$135="SHA/Chenot-tier")+3*('Equipment Master List'!$G$2:$G$135="Lanserhof/CLP-tier"))<=3))*(('Equipment Master List'!$B$2:$B$135="Movement & Rehab")+('Equipment Master List'!$B$2:$B$135="Gym & Strength"))*IFERROR('Equipment Master List'!$N$2:$N$135+0,0)*IFERROR('Equipment Master List'!$M$2:$M$135+0,0)) -> 183670000 | C44: =SUMPRODUCT((((1*('Equipment Master List'!$G$2:$G$135="Six Senses Place-tier")+2*('Equipment Master List'!$G$2:$G$135="SHA/Chenot-tier")+3*('Equipment Master List'!$G$2:$G$135="Lanserhof/CLP-tier"))>0)*((1*('Equipment Master List'!$G$2:$G$135="Six Senses Place-tier")+2*('Equipment Master List'!$G$2:$G$135="SHA/Chenot-tier")+3*('Equipment Master List'!$G$2:$G$135="Lanserhof/CLP-tier"))<=2))*(('Equipment Master List'!$B$2:$B$135="Movement & Rehab")+('Equipment Master List'!$B$2:$B$135="Gym & Strength"))*IFERROR('Equipment Master List'!$N$2:$N$135+0,0)*IFERROR('Equipment Master List'!$M$2:$M$135+0,0)) -> 80170000 | D44: =SUMPRODUCT((((1*('Equipment Master List'!$G$2:$G$135="Six Senses Place-tier")+2*('Equipment Master List'!$G$2:$G$135="SHA/Chenot-tier")+3*('Equipment Master List'!$G$2:$G$135="Lanserhof/CLP-tier"))>0)*((1*('Equipment Master List'!$G$2:$G$135="Six Senses Place-tier")+2*('Equipment Master List'!$G$2:$G$135="SHA/Chenot-tier")+3*('Equipment Master List'!$G$2:$G$135="Lanserhof/CLP-tier"))<=1))*(('Equipment Master List'!$B$2:$B$135="Movement & Rehab")+('Equipment Master List'!$B$2:$B$135="Gym & Strength"))*IFERROR('Equipment Master List'!$N$2:$N$135+0,0)*IFERROR('Equipment Master List'!$M$2:$M$135+0,0)) -> 80170000
A45: Total IT & Software capex (upfront) | B45: =SUMPRODUCT((((1*('Equipment Master List'!$G$2:$G$135="Six Senses Place-tier")+2*('Equipment Master List'!$G$2:$G$135="SHA/Chenot-tier")+3*('Equipment Master List'!$G$2:$G$135="Lanserhof/CLP-tier"))>0)*((1*('Equipment Master List'!$G$2:$G$135="Six Senses Place-tier")+2*('Equipment Master List'!$G$2:$G$135="SHA/Chenot-tier")+3*('Equipment Master List'!$G$2:$G$135="Lanserhof/CLP-tier"))<=3))*(('Equipment Master List'!$B$2:$B$135="IT, EHR, Patient Software"))*IFERROR('Equipment Master List'!$N$2:$N$135+0,0)*IFERROR('Equipment Master List'!$M$2:$M$135+0,0)) -> 104800000 | C45: =SUMPRODUCT((((1*('Equipment Master List'!$G$2:$G$135="Six Senses Place-tier")+2*('Equipment Master List'!$G$2:$G$135="SHA/Chenot-tier")+3*('Equipment Master List'!$G$2:$G$135="Lanserhof/CLP-tier"))>0)*((1*('Equipment Master List'!$G$2:$G$135="Six Senses Place-tier")+2*('Equipment Master List'!$G$2:$G$135="SHA/Chenot-tier")+3*('Equipment Master List'!$G$2:$G$135="Lanserhof/CLP-tier"))<=2))*(('Equipment Master List'!$B$2:$B$135="IT, EHR, Patient Software"))*IFERROR('Equipment Master List'!$N$2:$N$135+0,0)*IFERROR('Equipment Master List'!$M$2:$M$135+0,0)) -> 104800000 | D45: =SUMPRODUCT((((1*('Equipment Master List'!$G$2:$G$135="Six Senses Place-tier")+2*('Equipment Master List'!$G$2:$G$135="SHA/Chenot-tier")+3*('Equipment Master List'!$G$2:$G$135="Lanserhof/CLP-tier"))>0)*((1*('Equipment Master List'!$G$2:$G$135="Six Senses Place-tier")+2*('Equipment Master List'!$G$2:$G$135="SHA/Chenot-tier")+3*('Equipment Master List'!$G$2:$G$135="Lanserhof/CLP-tier"))<=1))*(('Equipment Master List'!$B$2:$B$135="IT, EHR, Patient Software"))*IFERROR('Equipment Master List'!$N$2:$N$135+0,0)*IFERROR('Equipment Master List'!$M$2:$M$135+0,0)) -> 92800000
A46: Total Kitchen & F&B capex | B46: =SUMPRODUCT((((1*('Equipment Master List'!$G$2:$G$135="Six Senses Place-tier")+2*('Equipment Master List'!$G$2:$G$135="SHA/Chenot-tier")+3*('Equipment Master List'!$G$2:$G$135="Lanserhof/CLP-tier"))>0)*((1*('Equipment Master List'!$G$2:$G$135="Six Senses Place-tier")+2*('Equipment Master List'!$G$2:$G$135="SHA/Chenot-tier")+3*('Equipment Master List'!$G$2:$G$135="Lanserhof/CLP-tier"))<=3))*(('Equipment Master List'!$B$2:$B$135="Kitchen & F&B"))*IFERROR('Equipment Master List'!$N$2:$N$135+0,0)*IFERROR('Equipment Master List'!$M$2:$M$135+0,0)) -> 130950000 | C46: =SUMPRODUCT((((1*('Equipment Master List'!$G$2:$G$135="Six Senses Place-tier")+2*('Equipment Master List'!$G$2:$G$135="SHA/Chenot-tier")+3*('Equipment Master List'!$G$2:$G$135="Lanserhof/CLP-tier"))>0)*((1*('Equipment Master List'!$G$2:$G$135="Six Senses Place-tier")+2*('Equipment Master List'!$G$2:$G$135="SHA/Chenot-tier")+3*('Equipment Master List'!$G$2:$G$135="Lanserhof/CLP-tier"))<=2))*(('Equipment Master List'!$B$2:$B$135="Kitchen & F&B"))*IFERROR('Equipment Master List'!$N$2:$N$135+0,0)*IFERROR('Equipment Master List'!$M$2:$M$135+0,0)) -> 130950000 | D46: =SUMPRODUCT((((1*('Equipment Master List'!$G$2:$G$135="Six Senses Place-tier")+2*('Equipment Master List'!$G$2:$G$135="SHA/Chenot-tier")+3*('Equipment Master List'!$G$2:$G$135="Lanserhof/CLP-tier"))>0)*((1*('Equipment Master List'!$G$2:$G$135="Six Senses Place-tier")+2*('Equipment Master List'!$G$2:$G$135="SHA/Chenot-tier")+3*('Equipment Master List'!$G$2:$G$135="Lanserhof/CLP-tier"))<=1))*(('Equipment Master List'!$B$2:$B$135="Kitchen & F&B"))*IFERROR('Equipment Master List'!$N$2:$N$135+0,0)*IFERROR('Equipment Master List'!$M$2:$M$135+0,0)) -> 130950000
A47: Total Medical Infrastructure capex | B47: =SUMPRODUCT((((1*('Equipment Master List'!$G$2:$G$135="Six Senses Place-tier")+2*('Equipment Master List'!$G$2:$G$135="SHA/Chenot-tier")+3*('Equipment Master List'!$G$2:$G$135="Lanserhof/CLP-tier"))>0)*((1*('Equipment Master List'!$G$2:$G$135="Six Senses Place-tier")+2*('Equipment Master List'!$G$2:$G$135="SHA/Chenot-tier")+3*('Equipment Master List'!$G$2:$G$135="Lanserhof/CLP-tier"))<=3))*(('Equipment Master List'!$B$2:$B$135="Medical Infrastructure"))*IFERROR('Equipment Master List'!$N$2:$N$135+0,0)*IFERROR('Equipment Master List'!$M$2:$M$135+0,0)) -> 134000000 | C47: =SUMPRODUCT((((1*('Equipment Master List'!$G$2:$G$135="Six Senses Place-tier")+2*('Equipment Master List'!$G$2:$G$135="SHA/Chenot-tier")+3*('Equipment Master List'!$G$2:$G$135="Lanserhof/CLP-tier"))>0)*((1*('Equipment Master List'!$G$2:$G$135="Six Senses Place-tier")+2*('Equipment Master List'!$G$2:$G$135="SHA/Chenot-tier")+3*('Equipment Master List'!$G$2:$G$135="Lanserhof/CLP-tier"))<=2))*(('Equipment Master List'!$B$2:$B$135="Medical Infrastructure"))*IFERROR('Equipment Master List'!$N$2:$N$135+0,0)*IFERROR('Equipment Master List'!$M$2:$M$135+0,0)) -> 16000000 | D47: =SUMPRODUCT((((1*('Equipment Master List'!$G$2:$G$135="Six Senses Place-tier")+2*('Equipment Master List'!$G$2:$G$135="SHA/Chenot-tier")+3*('Equipment Master List'!$G$2:$G$135="Lanserhof/CLP-tier"))>0)*((1*('Equipment Master List'!$G$2:$G$135="Six Senses Place-tier")+2*('Equipment Master List'!$G$2:$G$135="SHA/Chenot-tier")+3*('Equipment Master List'!$G$2:$G$135="Lanserhof/CLP-tier"))<=1))*(('Equipment Master List'!$B$2:$B$135="Medical Infrastructure"))*IFERROR('Equipment Master List'!$N$2:$N$135+0,0)*IFERROR('Equipment Master List'!$M$2:$M$135+0,0)) -> 0
A48: TOTAL CAPEX | B48: =SUM(B42:B47) -> 1815410000 | C48: =SUM(C42:C47) -> 847810000 | D48: =SUM(D42:D47) -> 553060000
A49: Capex per key | B49: =B48/$B$3 -> 20171222 | C49: =C48/$B$3 -> 9420111.1 | D49: =D48/$B$3 -> 6145111.1
A51: BENCHMARKS
A52: Luxury hotel capex/key (HVS global) | B52: $400,000 – $1,100,000 | D52: HVS Hotel Development Cost Survey (luxury segment)
A53: Premium longevity resort total capex/key (estimated) | B53: $700,000 – $1,500,000 | D53: Equipment shown in this workbook is INCREMENTAL on top of base hotel build.
A54: Equipment-only capex/key by tier (this study) | B54: Computed live from the Master List per region above. | D54: Edit prices in Master List → all roll-ups update.
A55: Citation note | B55: All operator price points (Lanserhof, SHA, CLP, Chenot) cross-referenced 2025–2026. | D55: See 'Sources & Methodology' sheet for full bibliography.

Sheet Payback & Revenue Logic
A1: PAYBACK & REVENUE MODEL
A2: Equipment-level payback under Russia/RUB cost base; EU/USD prices reference the Master List.
A4: ASSUMPTIONS
A5: Keys | B5: 90
A6: Year-5 occupancy | B6: 0.65
A7: Annual room nights @ Yr5 | B7: 21352
A8: Avg guest stays / yr (7-night assumed) | B8: 3050
A9: FX RUB / EUR | B9: 92
A10: Operating days / yr | B10: 320
A11: Operating hours / day | B11: 10
A12: Operating hours / yr | B12: 3200
A14: EQUIPMENT PAYBACK BLOCKS (Russia / RUB basis)
A15: Block | B15: Tier | C15: Capex (₽) | D15: Annual cost (₽) | E15: Procedure price (₽) | F15: Annual procedures | G15: Direct revenue (₽) | H15: Annual contribution (₽) | I15: Payback (yrs) | J15: Character | K15: Notes
A16: MRI 3T scanner (premium screening) | B16: Lanserhof/CLP-tier | C16: 290000000 | D16: 32200000 | E16: 110000 | F16: 1210 | G16: 133100000 | H16: 100900000 | I16: 2.87 | J16: Direct - bills per procedure | K16: Capacity-capped at 2,200 scans/yr (~50% of guests + 30% external). Sanctions-driven capex; high-margin executive screening. EU benchmark EUR 1,800-2,500; Russia target RUB 110k = ~EUR 1,200.
A17: MRI 1.5T workhorse | B17: Lanserhof/CLP-tier | C17: 130000000 | D17: 16300000 | E17: 70000 | F17: 810 | G17: 56700000 | H17: 40400000 | I17: 3.22 | J17: Direct - bills per procedure | K17: Targeted MSK/neuro/cardiac; lower premium than 3T. Capacity capped at 1,800 scans/yr.
A18: CT scanner 128-256 slice | B18: Lanserhof/CLP-tier | C18: 117000000 | D18: 16660000 | E18: 45000 | F18: 800 | G18: 36000000 | H18: 19340000 | I18: 6.05 | J18: Direct - bills per procedure | K18: Cardiac Ca scoring + low-dose lung screen; ~30% of guests. Lower utilization than MRI; faster throughput.
A19: DEXA scanner (body comp + bone density) | B19: Lanserhof/CLP-tier | C19: 13000000 | D19: 2010000 | E19: 12000 | F19: 1375 | G19: 16500000 | H19: 14490000 | I19: 0.9 | J19: Direct - bills per procedure | K19: Longevity staple - near-universal among guests. Russia procedure RUB 12k = ~EUR 130.
A20: Full polysomnography (PSG) suite | B20: Lanserhof/CLP-tier | C20: 12500000 | D20: 4950000 | E20: 80000 | F20: 192 | G20: 15360000 | H20: 10410000 | I20: 1.2 | J20: Direct - bills per procedure | K20: Single-bed PSG; capacity = 1 study/night x 320 operating nights. Multi-bed expansion possible. Russia target RUB 80k vs EU EUR 800-2500.
A21: CPET / VO2max metabolic cart | B21: Lanserhof/CLP-tier | C21: 9000000 | D21: 4450000 | E21: 25000 | F21: 990 | G21: 24750000 | H21: 20300000 | I21: 0.44 | J21: Direct - bills per procedure | K21: Lanserhof Classic Plus bundles this; in Russia priced ~50% of EU EUR 350-500.
A22: Premium cardiac ultrasound (echo) | B22: Lanserhof/CLP-tier | C22: 18000000 | D22: 6040000 | E22: 15000 | F22: 800 | G22: 12000000 | H22: 5960000 | I22: 3.02 | J22: Direct - bills per procedure | K22: Cardiology cornerstone; bundled into executive panel + per-study billing.
A23: Hormone / immunoassay analyzer | B23: Lanserhof/CLP-tier | C23: 10400000 | D23: 4840000 | E23: 8000 | F23: 1600 | G23: 12800000 | H23: 15960000 | I23: 0.65 | J23: Direct - bills per procedure | K23: Reagent-heavy; bundled into longevity panels. Capacity-capped at 4,000 tests/yr (~1.3 per guest).
A24: Hematology analyzer (5-part diff) | B24: Lanserhof/CLP-tier | C24: 6200000 | D24: 3020000 | E24: 2500 | F24: 2000 | G24: 5000000 | H24: 5980000 | I24: 1.04 | J24: Direct - bills per procedure | K24: High volume, low ticket; mostly bundled into executive panel CBCs.
A25: IV therapy chair fleet (6 clinical recliners) | B25: Lanserhof/CLP-tier | C25: 2880000 | D25: 7715200 | E25: 22000 | F25: 2880 | G25: 63360000 | H25: 55644800 | I25: 0.05 | J25: Direct - bills per session | K25: 6 chairs, ~3 sessions/day each at 30% utilization = 2,880 sessions/yr. NAD+, Myers, glutathione protocols.
A26: Whole-body cryotherapy chamber | B26: Lanserhof/CLP-tier | C26: 28000000 | D26: 4080000 | E26: 4500 | F26: 2400 | G26: 10800000 | H26: 6720000 | I26: 4.17 | J26: Direct - bills per procedure | K26: 3-min sessions, 15-min slot. Spa staple; high-throughput, low ticket.
A27: Hydrotherapy pool / underwater treadmill | B27: Lanserhof/CLP-tier | C27: 44000000 | D27: 4800000 | E27: 0 | F27: 0 | G27: 0 | H27: 0 | I27: ADR-recovered | J27: ADR-recovered (signature spa amenity) | K27: Heavy capex; recovered via ADR uplift + bundled into rehab/longevity programs.
A28: Robotic gait rehabilitation (Lokomat-class) | B28: Lanserhof/CLP-tier | C28: 48000000 | D28: 5580000 | E28: 8500 | F28: 200 | G28: 1700000 | H28: -3880000 | I28: ADR-recovered (niche neurorehab; consider deferring) | J28: Niche / consider deferring | K28: Niche modality outside core longevity audience; financially marginal at 0.20 utilization. Recommend deferring or reducing scope (gait analysis only, no robotic exoskeleton).
A29: Pilates Reformer studio (8 reformers) | B29: SHA/Chenot-tier | C29: 5200000 | D29: 4058000 | E29: 0 | F29: 0 | G29: 0 | H29: 0 | I29: ADR-recovered | J29: ADR-recovered + bundled into program | K29: Modest capex; recovered through bundled programs and ADR uplift. Class fees can be billed separately if positioned that way.
A30: Technogym Artis + premium gym suite (full) | B30: Six Senses Place-tier | C30: 60930000 | D30: 5846500 | E30: 0 | F30: 0 | G30: 0 | H30: 0 | I30: ADR-recovered | J30: ADR-recovered | K30: Non-billable; recovered via ADR + optional day-pass for non-resident members.
A31: Russian banya complex (parnaya + smoke banya + second parnaya) | B31: SHA/Chenot-tier | C31: 17700000 | D31: 4185000 | E31: 15000 | F31: 600 | G31: 9000000 | H31: 4815000 | I31: 3.68 | J31: Hybrid - parenia ritual billed direct + ADR uplift | K31: Russia-specific signature; parenia ritual sells RUB 12-18k, taken as RUB 15k. Strong cultural premium. 1 FTE banya master + 1 part-time assistant blended. Capacity capped at 1,500 sessions/yr.
A32: Vichy + hammam + snow room thermal circuit | B32: SHA/Chenot-tier | C32: 35000000 | D32: 4250000 | E32: 11000 | F32: 800 | G32: 8800000 | H32: 4550000 | I32: 7.69 | J32: Hybrid - Vichy treatments billed; hammam/snow ADR-recovered | K32: Vichy treatments are direct-billed; hammam/snow are circuit amenities.
A33: Full kitchen & F&B build-out | B33: Six Senses Place-tier | C33: 130950000 | D33: 7857000 | E33: 0 | F33: 0 | G33: 0 | H33: 0 | I33: Enabling spend | J33: Enabling spend | K33: Therapeutic + restaurant kitchen. Recovered via F&B P&L (25-35% contribution margin).
A34: Mid-market EHR (Athenahealth-class) | B34: Lanserhof/CLP-tier | C34: 12000000 | D34: 6900000 | E34: 0 | F34: 0 | G34: 0 | H34: 0 | I34: Enabling spend | J34: Enabling spend | K34: Required infrastructure; payback via efficiency/compliance. Annual subscription RUB 6M is opex.
A35: Full PMS + spa booking + guest app stack | B35: Six Senses Place-tier | C35: 15500000 | D35: 5800000 | E35: 0 | F35: 0 | G35: 0 | H35: 0 | I35: Enabling spend | J35: Enabling spend | K35: Hospitality + wellness operations stack. Annual subscription RUB 5-7M is opex.
A37: PROCEDURE PRICING BENCHMARKS
A38: Procedure | B38: Lanserhof anchor (€) | C38: SHA (€) | D38: CLP (€) | E38: Russia target (₽) | F38: Russia equiv (€) | G38: Notes
A39: Whole-body MRI (executive screening, no contrast) | B39: 2200 | C39: 1800 | D39: 2500 | E39: 111000 | F39: 1207 | G39: Lanserhof/SHA/CLP do not publish standalone whole-body MRI prices; bundled into longevity packages. EU benchmark estimated EUR 1,800-2,500 standalone (no contrast) at premium clinic. Russia equivalent at premium private clinic estimated EUR 1,200-1,800.
A40: DEXA scan (body composition + bone density) | B40: 200 | C40: 180 | D40: 250 | E40: 10000 | F40: 109 | G40: Lanserhof/CLP/Chenot bundle DEXA into longevity packages, no standalone published price. Estimated from US/UK direct-pay benchmarks. Russia premium clinic equivalent estimated EUR 80-150.
A41: VO2max / CPET (cardiopulmonary exercise testing) | B41: 400 | C41: 350 | D41: 500 | E41: 20000 | F41: 217 | G41: Lanserhof Classic Plus 7-night package (from EUR 4,046 ex-accom) includes VO2max as a bundled item. Russia premium estimated EUR 200-350.
A42: Full polysomnography (in-lab overnight sleep study) | B42: 1500 | C42: 1300 | D42: 1800 | E42: 76000 | F42: 826 | G42: In-lab PSG; home sleep tests typically EUR 200-600. Russia premium estimated EUR 300-800.
A43: Executive diagnostic / longevity panel (medical basis therapy + diagnostics, ex-accommodation, 7 nights) | B43: 4046 | C43: 3825 | D43: 8500 | E43: 223000 | F43: 2424 | G43: Programmatic pricing — base medical therapy alone is the closest like-for-like to a standalone executive diagnostic block.
A44: Healthy ageing / advanced longevity program (7 nights, ex-accommodation) | B44: 8053 | C44: 7500 | D44: 21300 | E44: 407000 | F44: 4424 | G44: Most direct industry comparable for a longevity-resort program price. CLP Revitalisation Premium up to CHF 48,520 sets the upper bound.
A45: Longevity blood / biological-age test (epigenetic + biomarker panel) | B45: 600 | C45: 500 | D45: 800 | E45: 33000 | F45: 359 | G45: Direct-to-consumer benchmarks. Premium clinics (CLP, SHA) embed within program; standalone EUR 400-700 typical. Russia equivalents (Atlas, Genotek) at EUR 80-200 consumer price.
A46: Microbiome / gut health test (16S rRNA or metagenomic + report) | B46: 450 | C46: 400 | D46: 600 | E46: 23000 | F46: 250 | G46: DTC range EUR 100-450; premium clinic-administered (with consult) EUR 350-700. Russia equivalents (Atlas, Knomx) EUR 80-180.
A47: Brain health package (Lanserhof Tegernsee, ex-accommodation) | B47: 5000 | C47: 4000 | D47: 7000 | E47: 253000 | F47: 2750 | G47: Lanserhof does not openly publish exact add-on price; structure mirrors Longevity package add-on (EUR 5,113). Treated as estimated.
A49: PACKAGE PRICING BENCHMARKS
A50: Operator | B50: Package | C50: Price (€) | D50: Includes accommodation | E50: What's included | F50: Source
A51: Lanserhof Tegernsee | B51: Lanserhof Cure Classic + Longevity (7 nights, programme only, ex accommodation) | C51: 8053 | D51: 8175 | E51: Initial and final physician examinations, interim check-ups with manual abdominal treatments, body composition diagnostics, daily therapeutic group sessions, longevity diagnostics (epigenetic/biomarker assessments), Mayr-style nutrition (full board), spa/treatment access. Accommodation in addition. | F51: https://lanserhof.com/en/lanserhof-tegernsee/treatments/package-longevity-tegernsee/ ; https://www.serenityways.com/clinics/lanserhof-tegernsee
A52: SHA Wellness Clinic Spain (Alicante) | B52: Advanced Longevity (7 nights, programme + accommodation in Deluxe Suite sea view, 2 guests) | C52: 12520 | E52: Genetic testing, biomarker analysis, 88-determination biological profile, hypoxia training, neurocognitive assessment, photobiomodulation, NAD therapy, hyperbaric, tailored nutrition (full board), holistic therapies, accommodation Deluxe Suite sea view. | F52: https://shawellness.com/en/advanced-longevity/ ; https://www.serenityways.com/clinics/sha-spain
A53: Clinique La Prairie (Montreux) | B53: Master Detox (6 nights / 7 days) | E53: Accommodation, full board (CLP detox menu), comprehensive medical consultations and diagnostics (cardiology, internal medicine), advanced detox treatments, lymphatic drainage, IV therapy, spa access, follow-up plan. | F53: https://www.cliniquelaprairie.com/programs/master-detox/ ; https://swissmedexpert.com/clinique-la-prairie-detox
A54: Clinique La Prairie (Montreux) | B54: Revitalisation Premium / Legendary Premium (1 week, top tier) | E54: CLP signature revitalisation cellular therapy program, full medical work-up including imaging, comprehensive diagnostics, medical consultations across multiple specialties, accommodation in premium suite, full board, spa. | F54: https://serenityways.com/pages/clinique-la-prairie-prices ; https://swissmedexpert.com/clinic-la-prairie
A55: Chenot Palace Weggis | B55: Advanced Detox (7 nights, ex-accommodation) | E55: Chenot Method protocol, daily medical consultations, energetic and detox treatments (hydro-jet, bio-energetic, phyto-mud, massages), comprehensive diagnostics, all meals (Chenot Diet, fasting-mimicking), gym/pool/thermal access. Accommodation in addition. | F55: https://www.chenot.com/chenot-palace/weggis/programmes/ ; https://www.serenityways.com/clinics/chenot-palace-weggis ; https://www.chenot.com/wp-content/uploads/2024/05/Chenot-Palace-Weggis-Brochure-EN.pdf
A56: VIVAMAYR Maria Worth / Altaussee | B56: Modern Mayr Cure Classic (7 nights, programme only) | E56: Initial and final consultations with Mayr physician, daily abdominal treatment, full board on Mayr diet, Mayr-method digestion treatments, base diagnostics (laboratory, body composition), spa access. Accommodation in addition (rooms from EUR 378-3,750/night). | F56: https://www.vivamayr.com/en/downloads/ ; https://serenityways.com/pages/vivamayr-prices ; https://www.best-treatment.com/en/clinics/vivamayr-altaussee/packages/modern-mayr-cure-basic
A57: Buchinger Wilhelmi (Lake Constance, Uberlingen) | B57: Classic 10-day fasting programme | E57: 10 nights minimum: digestive rest day, ~6 days fasting, refeeding days. Two medical consultations per 7 nights, comprehensive lab diagnostics, daily nurse health check, daily liver pack during fasting, intestinal cleansing every second day, 24-h on-call doctor, EUR 45/night treatment voucher. Accommodation in addition (typically EUR 218+/night). | F57: https://www.buchinger-wilhelmi.com/en/buchinger-wilhelmi-lake-constance/arrangements-packages/ ; https://www.buchinger-wilhelmi.com/wp-content/uploads/2024/11/What-we-offer-2025_web_V1.3.pdf ; https://luxury-rehabs.com/buchinger-wilhelmi/
A58: Six Senses (multi-property longevity programme baseline) | B58: Six Senses Longevity (varies by property; e.g., Six Senses Ibiza, Douro Valley, Kaplankaya) | E58: Personalized longevity programme with biomarker baseline, integrative medical consultation, sleep analysis, fitness assessment, IV/peptide therapies (where licensed), bespoke nutrition, holistic therapies, accommodation, full board. | F58: https://www.sixsenses.com/en/wellness-spa/personalized-wellness/longevity/ ; https://www.sixsenses.com/en/wellness-spa/retreats/ ; https://www.hotel-online.com/news/six-senses-2025-wellness-forecast
A60: PACKAGE ECONOMICS — Premium 7-night longevity package at EUR 15,000 per guest
A61: Component | B61: Share | C61: Value (€) | D61: Notes
A62: Accommodation | B62: 0.3 | C62: 4500 | D62: Suite-class room rate, 7 nights
A63: Medical procedures (owned equipment) | B63: 0.25 | C63: 3750 | D63: MRI/CT/DEXA/PSG/CPET/labs allocated to package
A64: Spa & recovery (owned equipment) | B64: 0.15 | C64: 2250 | D64: Hydrotherapy, cryo, banya, hammam, Vichy, Pilates
A65: F&B (therapeutic + restaurant) | B65: 0.12 | C65: 1800 | D65: Therapeutic menu + a la carte allowance
A66: Specialist consultations (labor) | B66: 0.13 | C66: 1950 | D66: Physician, nutritionist, sleep specialist, physio time
A67: Margin contribution | B67: 0.05 | C67: 750 | D67: Property contribution after direct opex
A68: Total package | B68: =SUM(B62:B67) -> 1 | C68: =SUM(C62:C67) -> 15000
A70: NON-BILLABLE EQUIPMENT — ADR UPLIFT LOGIC
A71: Rationale | B71: High-end gym, hydrotherapy pool, premium banya complex, full Pilates studio, snow room, hammam dont bill per use but enable a meaningful ADR uplift versus a comparable luxury hotel.
A72: ADR uplift / night (€) | B72: 250
A73: ADR uplift / night (₽) | B73: 23000
A74: Annual room nights Yr5 | B74: 21352
A75: Annual uplift (₽) | B75: 491096000
A76: Annual uplift (€ equiv) | B76: 5338000
A77: Notes | B77: Uplift = 23,000 RUB x 21,352 room nights (90 keys x 365 x 65% occupancy). Industry rule: premium spa/wellness adds 15-30% to ADR; EUR 250/night is conservative on a EUR 1,000-1,500/night base.
A79: SUMMARY PAYBACK BANDS
A80: Fast payback (< 1.5 yr) | B80: IV chair fleet (~0.05 yr), CPET (~0.5 yr), DEXA, hormone analyzer (~1 yr) - small capex, high-margin direct billing
A81: Medium payback (1.5–6 yr) | B81: Hematology analyzer, full PSG suite (~1-1.5 yr); MRI 3T (~3 yr), MRI 1.5T (~3 yr), CT scanner (~5-6 yr after util adj), cardiac ultrasound (~3 yr)
A82: Slow payback (> 6 yr direct) | B82: Whole-body cryotherapy (~4 yr), banya complex (~6-8 yr blended), Vichy/hammam circuit (~10-15 yr direct)
A83: ADR uplift / enabling infra | B83: Hydrotherapy pool, full Technogym suite, Pilates studio, kitchen & F&B, EHR, full PMS+IT stack - recovered via ADR uplift, package pricing, F&B margin, or enabling infrastructure. Lokomat neurorehab flagged as niche/marginal - consider deferring.

Sheet Regional Cost Drivers
A1: REGIONAL COST DRIVERS
A2: Reference document — sourced from research Phase 6. Russia section is the deepest given sanctions complexity.
A4: 1. WESTERN EUROPE
A5: OEM list-price baseline | B5: Western Europe (Germany, Switzerland, Austria, Italy, France, Spain) functions as the de facto OEM list-price baseline for the major medical/spa equipment OEMs serving the longevity-resort segment: Siemens Healthineers, GE HealthCare (EU sales), Philips, Dragerwerk, Storz, Olympus, Hologic, Technogym, Klafs, Starpool, Iyashi Dome, Cosmed, Schiller, Mindray-Europe. EUR list pricing typically forms the reference for cross-border benchmarking.
A6: Distribution markup | B6: 15-25% typical local distributor markup over OEM list. Direct OEM contracts on large bundles (>EUR 1M) often achieve 8-15% list-discount; small single-unit purchases pay full list plus markup.
A7: Maintenance cost level | B7: Annual service contracts typically 6-10% of capex for imaging (MRI, CT, ultrasound) and 4-7% for spa/recovery equipment. Multi-year service bundles (5-7 yrs) often negotiated at 5-7% effective rate.
A8: Used / refurb market | B8: Strong secondary market: refurbished MRI/CT typically 40-60% of new list, refurbished ultrasound 35-50%, refurbished DEXA 50-65%. Block Imaging, Oxford Instruments, Soma Tech, Avante Health Solutions are primary EU-active brokers. Spa/recovery equipment (cryo, IHHT, hyperbaric, Technogym) has thinner refurb market, 60-80% of new and limited supply.
A9: Key notes | B9: VAT recovery typical for medical-license entities (DE 19%, AT 20%, CH 8.1%, ES 21%, IT 22%). CE marking under MDR (EU 2017/745) required for medical devices; transition deadlines drove 2022-2024 price inflation of 5-8% on Class II/III devices. Energy/labor inflation 2022-2024 added ~10-15% to spa-build costs.
A10: Currency notes | B10: EUR baseline; CHF premium typically 10-15% above EUR for Swiss-built spa equipment.
A12: 2. NORTH AMERICA
A13: Pricing vs Europe | B13: USD list prices typically 10-20% above EUR list at parity (before currency translation) for imaging and lab; spa and aesthetic equipment 5-15% above EUR. Driven by higher dealer margins, regulatory compliance overhead, and tort-litigation risk premium baked into pricing.
A14: FDA implications | B14: FDA 510(k) clearance or PMA required; longer time-to-market (typically +6-18 months vs CE) and OEM compliance costs flow into US list. Some EU-only models unavailable in US, forcing shift to alternative SKUs at higher cost. FDA-cleared whole-body MRI screening (Prenuvo, Ezra) operates as direct-pay specialty.
A15: Leasing market | B15: Highly developed equipment finance and operating-lease market; most luxury wellness operators lease imaging (typical 60-month term, 4-7% effective rate). DLL, Siemens Financial Services, GE HealthCare Financial Services dominate. Leasing penetration ~50-60% for imaging, ~25-35% for spa.
A16: Service network | B16: Dense OEM service footprint; 4-hour response SLA available in major metros at ~10-12% of capex annually.
A17: Key notes | B17: State-level sales tax 0-9.5%. Tariff exposure 2024-2026 elevated (Section 301 China tariffs hit Mindray/Edan ultrasound, some Technogym SKUs assembled in Asia). HIPAA compliance and EHR integration overhead 5-10% of IT capex.
A19: 3. ASIA
A20: Regional manufacturing | B20: Mindray (China, Shenzhen) — global #3 in patient monitors and ultrasound; Edan (China) — ECG, ultrasound, monitors; Samsung Medison (Korea) — ultrasound, X-ray; United Imaging (China) — MRI/CT competitive with Siemens/GE/Philips at 30-50% lower price; Esaote (Italian-owned, AP manufacturing) — ultrasound. Lower input cost on patient monitoring, ECG, ultrasound and basic lab; near-parity on advanced imaging.
A21: Duty variation | B21: Singapore 0% on most medical devices (HSA-listed); Thailand 0-10% (most exempt under FDA-TH); UAE 0-5% (DHA/MOHAP-registered); Japan 0%; Korea 0-8%; China 0-4% with 13% VAT (medical generally reduced 9% or exempt for some categories); Hong Kong 0%.
A22: Service network | B22: Strong in Singapore, Hong Kong, UAE, Japan, Seoul; thinner in Indonesia, Vietnam, secondary China cities. Mindray claims a service network in 190+ countries with regional service hubs.
A23: Key notes | B23: Asia-manufactured equipment (Mindray ultrasound, Samsung ultrasound, BMC sleep diagnostics) is increasingly used as a substitute in Russia post-2022. UAE has emerged as parallel-import transshipment hub. India offers Wipro GE-manufactured imaging at 10-25% discount to EU list.
A25: 4. RUSSIA — deepest detail: sanctions, parallel import, domestic alternatives
A26: Customs duties | B26: Medical equipment under HS Chapter 9018-9022 generally 0-5% (most diagnostic imaging, ECG, ultrasound, surgical instruments at 0-5%); some categories 5-10%. Decree 1042 (2008, with amendments) lists specific medical equipment exempt from import duty. Status to be re-verified per HS code at customs declaration.
A27: VAT | B27: 20% standard VAT; many medical devices on the government-approved list (Decree 1042 / list of essential and vitally important medical devices) are VAT-exempt or charged at reduced 10% rate. Operator should validate exemption status per device with Russian customs broker.
A28: Currency volatility (RUB) | B28: RUB depreciated from ~89/USD end-2023 to ~110/USD end-2024 (~23% depreciation). Capex models should incorporate a 15-25% RUB depreciation buffer over 5-year planning horizon, with FX hedging or USD/EUR-denominated procurement contracts where possible. Multi-tranche procurement spread across the build cycle reduces FX shock.
A29: Sanctions affected categories | B29: Restricted (EU 833/2014 + US BIS): high-end imaging where >USD 750k or dual-use components (advanced 3T+ MRI, PET-CT, certain CT, AI diagnostic platforms with cloud dependence on Western servers). De-listed/permitted under licenses: standard ultrasound, ECG, patient monitors, basic laboratory analyzers, sleep diagnostics, most spa/recovery equipment. US BIS License Exception MED (April 2024, 15 CFR 740.23) authorizes EAR99-classified medical devices for export to Russia without license. EU 833/2014 contains medical exemption for medicines and most medical devices.
A30: Parallel import mechanics | B30: Government Decree No. 506 (29 March 2022) and Ministry of Industry and Trade Order No. 1532 (April 2022, amended through 2024-2025) authorize parallel imports for many medical-equipment categories without trademark holder consent. Mechanism extended through 2025+. Side effects: OEM warranty void, no factory service contract, software updates and remote diagnostics often disabled, spare parts lead times 3-6 months via grey channels.
A31: OEM service post-2022 | B31: Siemens Healthineers, GE HealthCare, Philips suspended new equipment sales and most service contracts to Russia after Feb 2022. Ongoing service for installed base is partial (humanitarian/medical-essential carve-outs). Russian system integrators (e.g., Medtech-M, Medrobotics, MMC, Intelmed, R-Pharm) source spare parts and provide third-party service. Lead times for spares 8-24 weeks; software/firmware support unreliable.
A32: Used / refurb (Russia) | B32: Active domestic and parallel-import refurb market — typically 40-60% of new EU list for imaging, 50-70% for spa equipment. Supply tightening on Western brands; expanding supply of Chinese-brand new and refurbished. Quality verification challenging without OEM service.
A33: Domestic alternatives & substitutes | B33: ECG/Holter: Aktiv-Med, Medical Computer Systems (Neurosoft), Schiller-Reomed (JV). Ultrasound: limited domestic capacity, Mindray (China) and Samsung (Korea) dominate parallel-import substitution. Patient monitors: Triton ElectronicSystems, Kvazar. Sterilizers/autoclaves: Ozon-Med, KASIMOV-MEDIN, Tuttnauer (parallel). Laboratory analyzers: JSC EILITON, Reamed; Mindray and Roche-cobas (parallel) dominate premium. Hyperbaric/oxygen: Khrunichev-derivative manufacturers, Sechenov-affiliated. Cryotherapy: limited domestic; CryoBuilt, Mecotec parallel-import. Spa/recovery (saunas, IR, salt rooms): strong domestic capacity (TyloHelo licensed assembly, Helo-derivative, KLAFS parallel). Russian biomarker/longevity labs: Atlas, Genotek, MyGenetics offer epigenetic and microbiome panels at 30-50% of EU consumer prices.
A35: METHODOLOGY NOTE
A36: Cross-region adjustment | B36: Apply regional adjustments to base EUR OEM list price as follows: (1) Start with EUR list (Western Europe baseline). (2) Apply category-specific Russia uplift: imaging EUR list +25-40% (parallel import + logistics + FX buffer + grey-channel premium); spa/recovery EUR list +15-25%; lab/IT EUR list +10-20%; locally-sourced FF&E -10 to -25% vs EU. (3) Add 15-25% RUB FX buffer for capex spread over 24-36 month build. (4) Add 8-12% installation/commissioning premium for sanctioned equipment requiring third-party service setup. (5) For Tier-1 international comparables (Lanserhof, CLP, Chenot), use Western Europe baseline directly — these operators procure at OEM list with EU service contracts. (6) Annual opex maintenance: assume 8-12% of capex for installed base in Russia (vs 6-10% in EU) to reflect parallel-channel spare-parts cost. (7) For methodology audit trail, document each line item's source: OEM list, distributor quote, refurb broker quote, peer-comparable price, or estimation triangulated from (a) global list, (b) Russia uplift factor, (c) FX assumption.
A37: RUSSIA RISK SUMMARY
A38: Customs + VAT | B38: 0–5% duty under HS 9018-9022 with Decree 1042 carve-outs; 20% VAT standard, 10% reduced or exempt for many medical devices on the government essential-devices list. Operator must validate exemption per HS code with Russian customs broker.
A39: Sanctions affected | B39: RESTRICTED (EU 833/2014 + US BIS): 3T+ MRI premium class, PET-CT, advanced CT, AI cloud-dependent diagnostic platforms. PERMITTED under license/exemption: standard ultrasound, ECG, patient monitors, basic lab analyzers, sleep diagnostics, most spa/recovery. US BIS License Exception MED authorizes EAR99 medical devices since April 2024.
A40: Parallel import & service risk | B40: Decree 506 (2022) authorizes parallel imports without trademark consent through 2025+. Side effects: OEM warranty void, no factory service contract, software updates and remote diagnostics often disabled, spare parts lead times 3–6 months via grey channels (8–24 weeks for spares). Imaging carries 25–40% premium.
A41: Domestic alternatives | B41: Mindray / United Imaging / Samsung Medison (ultrasound, CT, MRI parallel-import substitution); Neurosoft / Aktiv-Med / Schiller-Reomed JV (ECG, Holter); TyloHelo / KLAFS-licensed assembly (sauna); Triton / Kvazar (monitors); Atlas / Genotek / MyGenetics (epigenetic / microbiome / biomarker labs at 30–50% of EU consumer prices).

Sheet Sources & Methodology
A1: SOURCES & METHODOLOGY
A2: Bibliography of 56 cited sources, plus confidence assessment & verification recommendations.
A4: Name | B4: Type | C4: Used for | D4: URL | E4: Date accessed
A5: Lanserhof Tegernsee — Package Longevity | B5: Operator price disclosure | C5: Longevity programme add-on price (EUR 5,113), base Classic therapy (EUR 2,940), Brain Health package | D5: https://lanserhof.com/en/lanserhof-tegernsee/treatments/package-longevity-tegernsee/ | E5: 2026-05-03
A6: Lanserhof Lans — Package Longevity | B6: Operator price disclosure | C6: Lanserhof Longevity standalone EUR 6,618 ex-accommodation | D6: https://lanserhof.com/en/lanserhof-lans/treatments/package-longevity-lans/ | E6: 2026-05-03
A7: SerenityWays — Lanserhof Tegernsee profile | B7: Industry aggregator | C7: Cross-validated programme pricing and totals (EUR 8,175 starting total 7-night) | D7: https://www.serenityways.com/clinics/lanserhof-tegernsee | E7: 2026-05-03
A8: SHA Wellness Clinic — Advanced Longevity programme page | B8: Operator price disclosure | C8: Advanced Longevity 7n EUR 7,500 / 10n EUR 9,500 / 14n EUR 12,000 | D8: https://shawellness.com/en/advanced-longevity/ | E8: 2026-05-03
A9: SerenityWays — SHA Spain prices | B9: Industry aggregator | C9: SHA total stay including accommodation (EUR 12,520 / 7n / 2 guests, Deluxe Suite) | D9: https://www.serenityways.com/clinics/sha-spain | E9: 2026-05-03
A10: Clinique La Prairie — Master Detox programme | B10: Operator price disclosure | C10: Master Detox CHF 20,950 / 7d / 6n | D10: https://www.cliniquelaprairie.com/programs/master-detox/ | E10: 2026-05-03
A11: SwissMedExpert — Clinique La Prairie pricing summary | B11: Industry aggregator | C11: CLP programme range CHF 5,000-48,520 (Detox to Legendary Premium Revitalisation) | D11: https://swissmedexpert.com/clinic-la-prairie | E11: 2026-05-03
A12: Chenot Palace Weggis — Programmes & brochure | B12: Operator price disclosure | C12: Advanced Detox CHF 5,500 / 7n programme-only; Nest Room CHF 410/night; total starting CHF 8,370 | D12: https://www.chenot.com/chenot-palace/weggis/programmes/ | E12: 2026-05-03
A13: Chenot Palace Weggis — 2024 Brochure (PDF) | B13: Operator publication | C13: Programme structure and inclusions | D13: https://www.chenot.com/wp-content/uploads/2024/05/Chenot-Palace-Weggis-Brochure-EN.pdf | E13: 2026-05-03
A14: VIVAMAYR — Downloads (price lists) | B14: Operator publication | C14: Modern Mayr Cure Classic Maria Worth EUR 3,825; Altaussee EUR 4,385; accommodation tiers | D14: https://www.vivamayr.com/en/downloads/ | E14: 2026-05-03
A15: VIVAMAYR Maria Worth pricelist (PDF, Jan 2024) | B15: Operator publication | C15: Programme and accommodation EUR pricing | D15: https://www.vivamayr.com/app/uploads/2025/01/VIVAMAYR_MW_Preisliste_E_inkl.-Programme_15.01.2024.pdf | E15: 2026-05-03
... A60: Globetrender — Six Senses to open three urban wellness resorts in 2026 | B60: Industry coverage | C60: Six Senses London (Whiteley) capacity (109 rooms + 14 residences); 2026 opening | D60: https://globetrender.com/2025/12/02/four-new-six-senses-resorts-2026/ | E60: 2026-05-03
A63: CONFIDENCE ASSESSMENT
A64: Most reliable | C64: Western Europe (€) and North America (USD) prices for kitchen, gym, spa, and IT/PMS — sourced from live dealer pages and OEM list pricing (Rational, Technogym, Pilates, Klafs, Mews, Salesforce). Variance to actual quote typically +/-10%.
A65: Moderately reliable | C65: Imaging (MRI/CT/DEXA), lab analyzers, and medical infrastructure in EU/NA — sourced from refurbisher pricelists (Block Imaging, Avante, Soma Tech) and published OEM quotes. New-equipment list prices carry +/-15% variance; refurb quotes are firmer.
A66: Weakest — Russia (₽) column | C66: Russia prices are TRIANGULATED, not quoted. Method: EU EUR list + 25–40% imaging uplift (parallel-import premium + FX buffer) + 15–25% spa/recovery uplift + 10–20% lab/IT uplift; minus 10–25% on locally-sourced FF&E. Confidence: Medium for spa/IT, Low for sanctioned imaging. Variance to actual quote +/-25–40%.
A67: Pass-through items | C67: Advanced biomarker panels, CGM kits, microbiome kits, epigenetic age testing — these are zero-capex (consumables billed per guest); priced as pass-through. Volumes affect margin not capex.
A69: VERIFICATION RECOMMENDATIONS BEFORE COMMITTING CAPEX
A70: Russia imaging — REQUIRED | C70: Commission a quote from a Russian medical equipment broker before locking capex. Recommended: M-Equipment (Москва), MedTechMarket, Medtech-M, or a Sechenov-University-affiliated procurement consultant. Specifically for: MRI 3T, CT 128-slice, DEXA, mammography. Expect 25–40% variance from this workbook's estimates.
A71: Russia spa & banya — RECOMMENDED | C71: Validate with a Russian spa-build GC (Termopark, Russky Banya, Banya Project) since banya complex pricing varies 2–3x with construction method and species (kedr/lipa/dub). The workbook's RUB estimates assume turnkey log-construction and may understate by 15–30% for premium kedr.
A72: Western Europe imaging — OPTIONAL | C72: Cross-check with Block Imaging, Avante, or Soma Tech for same-class refurb units; OEM list pricing tends to discount 10–15% for >€1M bundles.
A73: IT / Software — OPTIONAL | C73: Mews, Salesforce, Athenahealth pricing scales with key count and provider count. Validate with current vendor quote at signing. Subscription price drift +5–8% / yr is typical.
A74: Procedure & package pricing — OPTIONAL | C74: Procedure prices anchored to public Lanserhof/CLP/SHA disclosure plus EU self-pay clinics (Anova IRM, Radiologie Dr Jung, Prenuvo, Ezra). Russia targets are positioning estimates — validate vs Sechenov and Rassvet Clinic published self-pay menus.
