Workbook

Sheet Обзор
B2: Премиальный Longevity Resort , Бенчмарк CapEx
B3: Оборудование, ПО, SPA, кухня и медицинская инфраструктура в четырёх регионах
B5: Дата выпуска | C5: 2026-05-03
B6: Покрытие по уровням | C6: Lanserhof/CLP (полная медицинская глубина) | SHA/Chenot (медицина-лайт) | Six Senses Place (велнес-плюс)
B7: Профиль объекта | C7: 80–100 номеров (модель использует середину диапазона , 90 номеров); премиальное люкс-позиционирование
B8: Регионы ценообразования | C8: Западная Европа (EUR) | Северная Америка (USD) | Азия (USD, с указанием страны) | Россия (RUB, оценка)
B9: Количество позиций | C9: 134 позиции в 16 категориях
B11: СОДЕРЖИМОЕ КНИГИ
B12: Обзор | C12: Эта страница , методология, определения уровней, цветовая легенда
B13: Реестр оборудования | C13: Все 134 позиции с брендом, ценами в четырёх регионах, привязкой к уровню, источником и достоверностью
B14: Сводка CapEx по уровням | C14: Свод по уровням, группам и регионам. Живые формулы , изменения в реестре или keys_count пересчитают итоги.
B15: Окупаемость и выручка | C15: Блоки окупаемости оборудования, цены процедур и пакетов, логика прироста ADR, диапазоны окупаемости
B16: Региональные факторы стоимости | C16: Санкции, таможня и НДС, параллельный импорт, отечественные альтернативы , детально по России
B17: Источники и методология | C17: Все цитируемые источники, оценка достоверности и рекомендованный путь верификации
B20: ОПРЕДЕЛЕНИЯ УРОВНЕЙ
B21: Уровень Six Senses Place (велнес-плюс) | C21: Велнес-плюс. Премиальное SPA, полноценная термальная зона, пилатес и тренажёрный зал, полная кухня, PMS и ИТ. Без медицинского центра, визуализации, собственной лаборатории и МИС. Позиции этого уровня входят во ВСЕ уровни (операционная база).
B22: Уровень SHA/Chenot (медицина-лайт) | C22: Медицина-лайт. Добавляются УЗИ, DEXA, рентген, базовые лабораторные анализаторы, ЭКГ-комплекс, HSAT, кресла для капельниц, FibroScan, RMR, МИС среднего класса и базовая медицинская инфраструктура.
B23: Уровень Lanserhof/CLP (полный медицинский) | C23: Полная медицинская глубина. Добавляются МРТ 3 Тл и 1,5 Тл, КТ, ОКТ, маммография, полноценная PSG/ЭЭГ, озон/ИГГТ/HBOT, эстетические лазеры, полнофункциональный PACS, полная система медицинских газов, генератор и HEPA.
B24: Опциональный апселл | C24: Учитывается отдельно , Epic EHR, криолиполиз, парк ECG-патчей, корпоративные WHOOP/Garmin. НЕ входят в базовые итоги уровней.
B27: ЦВЕТОВАЯ ЛЕГЕНДА
B28: Жёсткий ввод | C28: Числа, которые пользователь меняет под сценарии (цены, keys_count, курсы)
B29: Формула / расчёт | C29: Ячейки, рассчитываемые книгой по введённым параметрам
B30: Кросс-листовая ссылка | C30: Ссылки на другие листы , поддерживают синхронность сводок с реестром
B31: Цвета достоверности | C31: Зелёный , высокая, жёлтый , средняя, оранжевый , низкая. Применяются к колонке достоверности в реестре.
B33: КАК ЧИТАТЬ ЭТУ КНИГУ
C34: 1. Реестр оборудования , единый источник истины. Изменение цены или количества там автоматически обновляет сводку CapEx через SUMPRODUCT.
C35: 2. Сводка CapEx использует логику включения уровней: позиции Six Senses учитываются во ВСЕХ трёх уровнях; позиции SHA , в CLP и SHA; позиции CLP , только в CLP.
C36: 3. Для ПО раздельно показаны единовременный CapEx и годовая подписка. Годовые суммы относятся к OpEx и в итоги CapEx не включаются.
C37: 4. Колонка России (₽) имеет НАИМЕНЬШУЮ достоверность , рекомендации по верификации см. в листе «Источники и методология».
C38: 5. «CapEx на номер» использует keys_count из ячейки B3 листа «Сводка CapEx по уровням» (по умолчанию 90 , редактируется).

Sheet Реестр оборудования
A1: ID | B1: Категория | C1: Подкатегория | D1: Оборудование | E1: Примеры брендов | F1: Назначение | G1: Уровень (скорректированный) | H1: Уровень (по исследованию) | I1: Цена , Западная Европа (€) | J1: Цена , Северная Америка (USD) | K1: Цена , Азия (USD) | L1: Страна Азии | M1: Цена , Россия, оценка (₽) | N1: Количество (80–100 номеров) | O1: Срок службы (лет) | P1: Годовое обслуживание (% CapEx) | Q1: FTE на эксплуатацию | R1: Источник | S1: Достоверность | T1: Дата проверки | U1: Примечания | V1: ЕС: годовая €, ПО | W1: СА: годовая $, ПО | X1: Азия: годовая $, ПО | Y1: Россия: годовая ₽, ПО | Z1: Путь(и) активации | AA1: Evidence (A/B/C) | AB1: Гормезис стек (Да/Нет)
A2: 1 | B2: Эстетика и регенеративные процедуры | C2: Аблятивно-неаблятивная платформа | D2: Модульная эстетическая лазерная платформа (BBL+Halo+ProFractional) | E2: Sciton JOULE X / Lumenis M22 | F2: Шлифовка кожи, удаление пигментации и сосудистых образований , рабочая лошадка эстетического направления. | G2: Уровень Lanserhof/CLP (полный медицинский) | H2: Уровень Lanserhof/CLP (полный медицинский) | I2: 180000 | J2: 215000 | K2: 175000 | L2: ОАЭ | M2: 25000000 | N2: 1 | O2: 8 | P2: 0.1 | Q2: 0.6 | R2: Дилерские предложения Sciton; платформа mJOULE с пробегом по цене $149 950 (mrp.io); прайсы Lumenis 2024. | S2: Средняя | T2: 2026-05 | U2: Регуляторное замечание: производитель , США. Импорт в Россию идёт по параллельным каналам с надбавкой 20–30%. Целесообразно рассмотреть европейские альтернативы (Asclepion, Quantel). | Z2: Диагностика | AA2: B | AB2: Нет
A3: 2 | B3: Эстетика и регенеративные процедуры | C3: Криолиполиз | D3: Система криолиполиза (редукция жировой ткани) | E3: Allergan CoolSculpting Elite / Cooltech Define | F3: Неинвазивная редукция жировой ткани , высокомаржинальная эстетическая услуга. | G3: Опциональный апселл | H3: Опциональный апселл | I3: 100000 | J3: 120000 | K3: 95000 | L3: ОАЭ | M3: 14000000 | N3: 1 | O3: 7 | P3: 0.1 | Q3: 0.4 | R3: Дилер Allergan, 2024; восстановленные системы CoolSculpting Elite на Offer Aesthetic. | S3: Средняя | T3: 2026-05 | U3: Регуляторное замечание: Allergan/AbbVie находятся под американским контролем. Для России предпочтительнее Cooltech (Испания, ныне Cocoon Medical). | Z3: Диагностика | AA3: B | AB3: Нет
A4: 3 | B4: Эстетика и регенеративные процедуры | C4: EMSculpt / электромагнитная стимуляция мышц | D4: Электромагнитная стимуляция мышц (HIFEM) | E4: BTL EMSculpt NEO | F4: Прирост мышечной массы и редукция жира , востребованная SPA-надстройка. | G4: Уровень Lanserhof/CLP (полный медицинский) | H4: Уровень SHA/Chenot (медицина-лайт) | I4: 130000 | J4: 150000 | K4: 125000 | L4: ОАЭ | M4: 18000000 | N4: 1 | O4: 7 | P4: 0.1 | Q4: 0.4 | R4: Дилерские предложения BTL Industries 2024–2025. | S4: Средняя | T4: 2026-05 | U4: Производитель BTL , чешская компания, поэтому канал поставки в Россию относительно чистый. | Z4: Диагностика | AA4: A | AB4: Нет
A5: 4 | B5: Эстетика и регенеративные процедуры | C5: HIFU-лифтинг кожи | D5: Микрофокусированный ультразвук для лифтинга кожи (HIFU) | E5: Merz Ultherapy Prime / Ulthera | F5: Безоперационное подтягивание кожи , востребованная процедура. | G5: Уровень SHA/Chenot (медицина-лайт) | H5: Уровень SHA/Chenot (медицина-лайт) | I5: 65000 | J5: 75000 | K5: 60000 | L5: ОАЭ | M5: 9000000 | N5: 1 | O5: 7 | P5: 0.12 | Q5: 0.4 | R5: Konmison: справочник цен на аппараты Ultherapy 2025; vsquareclinic об Ulthera Prime. | S5: Средняя | T5: 2026-05 | U5: Расходные картриджи , около $300 за процедуру. По России: производитель Merz базируется в ЕС, что снижает санкционные риски по сравнению с американскими аналогами. | Z5: Диагностика | AA5: A | AB5: Нет
A6: 5 | B6: Эстетика и регенеративные процедуры | C6: Светотерапия LED | D6: LED-кушетка/панель для медицинской светотерапии | E6: NovoTHOR / Celluma PRO panels | F6: Фотобиомодуляция для кожи, восстановления и программ долголетия. | G6: Уровень SHA/Chenot (медицина-лайт) | H6: Уровень SHA/Chenot (медицина-лайт) | I6: 65000 | J6: 78000 | K6: 60000 | L6: ОАЭ | M6: 9000000 | N6: 1 | O6: 10 | P6: 0.04 | Q6: 0.2 | R6: Розничные цены NovoTHOR 2024 (~$70–90 тыс.); панели Celluma Pro $3–5 тыс. как альтернатива. | S6: Средняя | T6: 2026-05 | U6: Полнотельная кушетка NovoTHOR , фирменное оборудование премиальных клиник. | Z6: Диагностика | AA6: A | AB6: Нет
A7: 6 | B7: Эстетика и регенеративные процедуры | C7: Радиочастотная терапия | D7: Аппарат радиочастотной терапии (Tecar 448 кГц) | E7: Indiba Activ Elite NS / Indiba CT9 | F7: Регенерация тканей, восстановление, контурирование тела , двойное применение в реабилитации и эстетике. | G7: Уровень SHA/Chenot (медицина-лайт) | H7: Уровень SHA/Chenot (медицина-лайт) | I7: 35000 | J7: 42000 | K7: 33000 | L7: ОАЭ | M7: 4800000 | N7: 2 | O7: 8 | P7: 0.07 | Q7: 0.6 | R7: Референтные предложения дилеров Indiba; клинические тарифы NYDNRehab; листинги б/у на eBay около $55 тыс. | S7: Средняя | T7: 2026-05 | U7: Производитель из Испании, что обеспечивает более чистый канал поставки в Россию по сравнению с американскими лазерами. | Z7: Диагностика | AA7: B | AB7: Нет
A8: 7 | B8: Эстетика и регенеративные процедуры | C8: Платформа сосудисто-пигментных лазеров | D8: Многоволновая эстетическая лазерная платформа (KTP+Nd:YAG) | E8: Cutera Excel V+ / Candela GentleMax Pro | F8: Сосудистые образования, пигментация, ревитализация кожи. | G8: Уровень Lanserhof/CLP (полный медицинский) | H8: Уровень Lanserhof/CLP (полный медицинский) | I8: 90000 | J8: 105000 | K8: 85000 | L8: ОАЭ | M8: 12500000 | N8: 1 | O8: 8 | P8: 0.1 | Q8: 0.5 | R8: Листинги новых Cutera Excel V+ от The Laser Agent 2025; Bimedis , диапазон б/у $18 613–49 950. | S8: Средняя | T8: 2026-05 | U8: Регуляторное замечание: эстетические лазеры из США и Израиля сталкиваются с ограничениями импорта в Россию. Поставка идёт через реэкспорт из Турции/ОАЭ с надбавкой 15–25% и риском отсутствия гарантии. | Z8: Диагностика | AA8: C | AB8: Нет
A9: 8 | B9: Состав тела и функциональная диагностика | C9: Состав тела , воздушная плетизмография | D9: Воздушный плетизмограф BodPod GS-X | E9: Cosmed BodPod GS-X | F9: Эталонный двухкомпонентный анализ состава тела , отличие премиального уровня от InBody. | G9: Уровень Six Senses Place (велнес-плюс) | H9: Уровень Lanserhof/CLP (полный медицинский) | I9: 50000 | J9: 58000 | K9: 48000 | L9: ОАЭ | M9: 6600000 | N9: 1 | O9: 12 | P9: 0.05 | Q9: 0.2 | R9: Дилерские предложения Cosmed; MedicalExpo 2024. | S9: Средняя | T9: 2026-05 | U9: Используется в Lanserhof и CLP. Тяжёлый аппарат, требует выделенного помещения со стабильной температурой. | Z9: Диагностика | AA9: A | AB9: Нет
A10: 9 | B10: Состав тела и функциональная диагностика | C10: Состав тела , биоимпеданс | D10: Анализатор состава тела медицинского класса (BIA, мультичастотный) | E10: InBody 970 / Seca mBCA 555 (medical-grade) | F10: Сегментарный состав тела, ECW/ICW, фазовый угол , базовое обследование в программах долголетия. | G10: Уровень Six Senses Place (велнес-плюс) | H10: Уровень Lanserhof/CLP (полный медицинский) | I10: 28000 | J10: 32600 | K10: 26000 | L10: ОАЭ | M10: 3700000 | N10: 2 | O10: 8 | P10: 0.05 | Q10: 0.3 | R10: Прайс InBody USA 2025 ($32 605); базовая Seca mBCA Pro $9 599; листинг HaB Direct mBCA 555. | S10: Высокая | T10: 2026-05 | U10: InBody 970 , рабочий стандарт; Seca mBCA 555 , медицинского класса CE. По России: дистрибьюторы доступны в Москве, санкционных проблем нет. | Z10: Диагностика | AA10: A | AB10: Нет
A11: 10 | B11: Состав тела и функциональная диагностика | C11: Кардиопульмонология | D11: Метаболическая платформа VO2max / CPET | E11: Cosmed K5 / Cosmed Quark CPET / MGC Diagnostics | F11: VO2max и базальный метаболизм , ключевые показатели здорового долголетия. | G11: Уровень SHA/Chenot (медицина-лайт) | H11: Уровень Lanserhof/CLP (полный медицинский) | I11: 45000 | J11: 52000 | K11: 42000 | L11: ОАЭ | M11: 6000000 | N11: 1 | O11: 10 | P11: 0.08 | Q11: 0.4 | R11: Дилеры Cosmed 2024; листинги MedicalExpo. | S11: Средняя | T11: 2026-05 | U11: CPET выполняют и в Lanserhof, и в SHA. В комплекте , беговая дорожка либо велоэргометр. | Z11: Диагностика | AA11: A | AB11: Нет
A12: 11 | B12: Состав тела и функциональная диагностика | C12: DEXA-сканер | D12: DEXA-сканер для анализа состава тела и плотности костной ткани | E12: Hologic Horizon / GE Lunar iDXA | F12: Эталон оценки минеральной плотности костей и состава тела. | G12: Уровень SHA/Chenot (медицина-лайт) | H12: Уровень Lanserhof/CLP (полный медицинский) | I12: 95000 | J12: 115000 | K12: 90000 | L12: ОАЭ | M12: 13100000 | N12: 1 | O12: 12 | P12: 0.07 | Q12: 0.4 | R12: Дилерские прайсы Hologic/GE 2024. | S12: Средняя | T12: 2026-05 | U12: Возможно пересечение с медицинской визуализацией , следует контролировать, чтобы позиция учитывалась только один раз. | Z12: Диагностика | AA12: A | AB12: Нет
A13: 12 | B13: Состав тела и функциональная диагностика | C13: Анализ опорной реакции и походки | D13: Система силовых платформ (двойная, встраиваемая) | E13: AMTI BMS400600 / Bertec FP4060 | F13: Опорная реакция, баланс, кинетика походки. | G13: Уровень SHA/Chenot (медицина-лайт) | H13: Уровень Lanserhof/CLP (полный медицинский) | I13: 45000 | J13: 52000 | K13: 42000 | L13: ОАЭ | M13: 6000000 | N13: 1 | O13: 15 | P13: 0.04 | Q13: 0.2 | R13: Предложения дилеров AMTI; партнёрские цены Noraxon 2024. | S13: Средняя | T13: 2026-05 | U13: Пара платформ; для монтажа требуется заглубление в полу. Часто используется в связке с системами Vicon. | Z13: Диагностика | AA13: C | AB13: Нет
... A66: 65 | B66: ИТ, МИС, ПО для пациентов | C66: Контроль доступа и RFID-замки | D66: Электронные замки номеров и контроль доступа в служебных зонах | E66: Salto, Assa Abloy VingCard, dormakaba | F66: RFID/мобильные ключи на дверь; раздельные зоны для персонала. | G66: Уровень Six Senses Place (велнес-плюс) | H66: Уровень Lanserhof/CLP (полный медицинский) | I66: 165000 | J66: 200000 | K66: 130000 | L66: Китай | M66: 20500000 | N66: 1 | O66: 12 | P66: 0.04 | Q66: 0 | R66: Kompareit hotel access $1500–2500/дверь; 100 дверей плюс 30 служебных. | S66: Высокая | T66: 2026-05 | U66: Премиальная спецификация (BLE и мобильный ключ). По России: VingCard поставляется параллельным импортом с надбавкой 20–25%. | Z66: Гостевой опыт | AA66: C | AB66: Нет
A67: 66 | B67: ИТ, МИС, ПО для пациентов | C67: МИС/EHR | D67: МИС среднего класса (уровень Athenahealth) | E67: Athenahealth athenaOne, Tebra, ModMed; Russian: МИС МедОфис, qMS | F67: Ведение клинической документации медицинского центра; интеграция с лабораторией и визуализацией. | G67: Уровень SHA/Chenot (медицина-лайт) | H67: Уровень Lanserhof/CLP (полный медицинский) | I67: 180000 | J67: 220000 | K67: 150000 | L67: Сингапур | M67: 12000000 | N67: 1 | O67: 7 | P67: 0 | Q67: 0.5 | R67: Athenahealth $140 за специалиста в месяц плюс 4–8% от собранной выручки; внедрение $2–5 тыс. на специалиста; emrguides.com 2025. | S67: Средняя | T67: 2026-05 | U67: По России: 152-ФЗ о локализации данных блокирует западные облачные МИС. Российские qMS/МедОфис обходятся примерно на 50% дешевле, но требуют кастомной интеграции. | V67: 90000 | W67: 110000 | X67: 75000 | Y67: 6000000 | Z67: Гостевой опыт, Снижение воспаления | AA67: C | AB67: Нет
A68: 67 | B68: ИТ, МИС, ПО для пациентов | C68: МИС (опционально, уровень Epic) | D68: МИС корпоративного уровня (Epic/Cerner) | E68: Epic Hyperspace, Oracle Health (Cerner Millennium) | F68: Полнофункциональная МИС больничного класса для медцентра курорта. | G68: Опциональный апселл | H68: Опциональный апселл | I68: 1800000 | J68: 2200000 | K68: 1500000 | L68: Сингапур | M68: 0 | N68: 0 | O68: 10 | P68: 0 | Q68: 1 | R68: Tactionsoft 2025 ($500 тыс. – 10 млн); arkenea.com Cerner; Veterans Memorial Hospital $3,88 млн. | S68: Средняя | T68: 2026-05 | U68: Избыточно для отеля 80–100 номеров; уместно только при стационарной мощности. В России развёртывание невозможно. | V68: 350000 | W68: 420000 | X68: 300000 | Y68: 0 | Z68: Гостевой опыт | AA68: C | AB68: Нет
A69: 68 | B69: ИТ, МИС, ПО для пациентов | C69: Гостевой опыт / мобильное приложение | D69: Гостевое мобильное приложение и in-room планшеты | E69: Crave Interactive, SuitePad, Hudini, INTELITY | F69: Мобильный check-in, заказ в номер, бронирование процедур, контент. | G69: Уровень Six Senses Place (велнес-плюс) | H69: Уровень Lanserhof/CLP (полный медицинский) | I69: 90000 | J69: 110000 | K69: 75000 | L69: Сингапур | M69: 9500000 | N69: 1 | O69: 5 | P69: 0 | Q69: 0 | R69: Бенчмарки hospitality tech; планшет $600–1200 на номер плюс лицензия $25–40 на номер в месяц. | S69: Средняя | T69: 2026-05 | U69: Включает планшеты в номера, лицензии и интеграцию с PMS/SPA. | V69: 35000 | W69: 42000 | X69: 28000 | Y69: 2800000 | Z69: Гостевой опыт | AA69: C | AB69: Нет
A70: 69 | B70: ИТ, МИС, ПО для пациентов | C70: Платформа долголетия для пациентов | D70: Специализированная платформа долголетия для пациентов | E70: Function Health (B2B), Hone Health, Healthspan; alt: custom | F70: Отслеживание биомаркеров, личный кабинет, продольные результаты, ИИ-аналитика. | G70: Уровень Six Senses Place (велнес-плюс) | H70: Уровень Lanserhof/CLP (полный медицинский) | I70: 75000 | J70: 90000 | K70: 65000 | L70: Сингапур | M70: 8500000 | N70: 1 | O70: 5 | P70: 0 | Q70: 0.5 | R70: Function Health B2B (Equinox $249, Higginbotham $334 в год за участника); sacra.com. | S70: Низкая | T70: 2026-05 | U70: Годовой ARR , около 200–300 активных участников по $250–350 в год. По России: потребуется кастомная разработка либо изолированный инстанс. | V70: 60000 | W70: 72000 | X70: 55000 | Y70: 4000000 | Z70: Гормезис, Активация AMPK, Снижение воспаления | AA70: B | AB70: Да
A71: 70 | B71: ИТ, МИС, ПО для пациентов | C71: Сетевая инфраструктура | D71: Проводная и Wi-Fi 6/7 магистраль (корпоративный класс) | E71: Cisco Meraki, RUCKUS Networks, Aruba; Russian: Eltex, QTECH | F71: Гостевая и служебная сети с сегментированными VLAN, включая медицинский сегмент. | G71: Уровень Six Senses Place (велнес-плюс) | H71: Уровень Lanserhof/CLP (полный медицинский) | I71: 220000 | J71: 260000 | K71: 170000 | L71: Сингапур | M71: 28000000 | N71: 1 | O71: 8 | P71: 0.1 | Q71: 0 | R71: RUCKUS/Cisco hospitality vertical; ~€2–3 тыс. за установленную точку доступа, 80 точек плюс коммутация. | S71: Средняя | T71: 2026-05 | U71: По России: Cisco/Aruba под санкциями с 2022 года. Замена , Eltex/QTECH либо серый рынок. | Z71: Снижение воспаления | AA71: C | AB71: Нет
A72: 71 | B72: ИТ, МИС, ПО для пациентов | C72: PMS , отельная часть | D72: Облачная PMS (отель 80–100 номеров класса люкс) | E72: Mews Enterprise, Oracle Opera Cloud, Protel; Russian: Bnovo, Shelter, TravelLine | F72: Бронирование, гостевые счета, хаускипинг, channel manager, интеграция POS. | G72: Уровень Six Senses Place (велнес-плюс) | H72: Уровень Lanserhof/CLP (полный медицинский) | I72: 45000 | J72: 55000 | K72: 38000 | L72: Сингапур | M72: 2500000 | N72: 1 | O72: 7 | P72: 0 | Q72: 0 | R72: Mews Enterprise (hoteltechreport, roommaster); цена Mews EUR 300/мес. | S72: Средняя | T72: 2026-05 | U72: По России на 2026 год: Mews и Opera ушли после санкций 2022 года. Российские альтернативы (Shelter, Bnovo) обходятся на 40–50% дешевле, но уступают премиальным сценариям. | V72: 36000 | W72: 45000 | X72: 32000 | Y72: 1500000 | Z72: Гормезис, Активация AMPK, Митохондриальная функция, Снижение воспаления | AA72: B | AB72: Да
A73: 72 | B73: ИТ, МИС, ПО для пациентов | C73: Безопасность , видеонаблюдение | D73: IP-видеонаблюдение (40–60 камер плюс NVR) | E73: Avigilon, Axis, Hanwha; Russian: TRASSIR, Macroscop | F73: Периметр и служебные зоны. | G73: Уровень Six Senses Place (велнес-плюс) | H73: Уровень Lanserhof/CLP (полный медицинский) | I73: 75000 | J73: 90000 | K73: 55000 | L73: Китай | M73: 7800000 | N73: 1 | O73: 10 | P73: 0.05 | Q73: 0 | R73: Avigilon/Axis у дилеров; ~€1–1,5 тыс. за установленную камеру. | S73: Высокая | T73: 2026-05 | U73: По России: доминирует TRASSIR; цена выгоднее западных решений. | Z73: Гормезис, Активация AMPK, Митохондриальная функция, Снижение воспаления | AA73: A | AB73: Да
A74: 73 | B74: ИТ, МИС, ПО для пациентов | C74: Система записи в SPA и медицинском блоке | D74: Интегрированная система записи на SPA и процедуры | E74: Book4Time, Agilysys Spa, ResortSuite | F74: Расписание терапевтов, загрузка кабинетов, управление пакетами, ритейл. | G74: Уровень Six Senses Place (велнес-плюс) | H74: Уровень Lanserhof/CLP (полный медицинский) | I74: 55000 | J74: 68000 | K74: 45000 | L74: Сингапур | M74: 3500000 | N74: 1 | O74: 7 | P74: 0 | Q74: 0 | R74: Book4Time, Agilysys, ResortSuite , ориентировочные цены 2025. | S74: Средняя | T74: 2026-05 | U74: Критично для премиальных велнес-резортов; интегрируется с PMS и МИС. | V74: 28000 | W74: 35000 | X74: 22000 | Y74: 1500000 | Z74: Гормезис, Активация AMPK, Митохондриальная функция, Снижение воспаления | AA74: B | AB74: Да
A75: 74 | B75: ИТ, МИС, ПО для пациентов | C75: Телефония и IPTV | D75: VoIP-телефония и IPTV | E75: Mitel, Cisco; LG/Samsung Pro:Idiom IPTV | F75: Телефония в номерах, IPTV, телефония в служебных зонах. | G75: Уровень Six Senses Place (велнес-плюс) | H75: Уровень Lanserhof/CLP (полный медицинский) | I75: 95000 | J75: 115000 | K75: 75000 | L75: Китай | M75: 12500000 | N75: 1 | O75: 10 | P75: 0.06 | Q75: 0 | R75: Бенчмарк интеграторов hospitality AV/IT. | S75: Средняя | T75: 2026-05 | U75: Резорты среднего сегмента иногда отказываются от стационарной телефонии в пользу стриминга. | Z75: Гормезис, Активация AMPK, Митохондриальная функция, Снижение воспаления, Гостевой опыт | AA75: C | AB75: Да
A76: 75 | B76: Инфузионная терапия | C76: Гипербарическая оксигенация | D76: Гипербарическая кислородная камера , мягкая HBOT (1,3–1,5 ATA) | E76: OxyHealth Vitaeris 320, Hyperbaric Centrales OxyVita, Summit to Sea Dive | F76: Мягкокорпусная гипербарическая оксигенация для протоколов восстановления и долголетия. | G76: Уровень Lanserhof/CLP (полный медицинский) | H76: Уровень Lanserhof/CLP (полный медицинский) | I76: 35000 | J76: 40000 | K76: 28000 | L76: Китай | M76: 4800000 | N76: 2 | O76: 10 | P76: 0.05 | Q76: 0.5 | R76: Прайс OxyHealth Vitaeris 320 $20–35 тыс.; типовая мягкокорпусная HBOT €25–45 тыс. Жёсткие медицинские камеры (2,0+ ATA) дороже в 5–10 раз. | S76: Средняя | T76: 2026-05 | U76: Объём ограничен мягкокорпусной HBOT (упрощённая регуляторика, без сжатого кислорода). Жёсткие камеры , отдельная категория, не учтены. По России: отечественные камеры BLKS и OxyHealth , параллельным импортом. | Z76: Гормезис, Активация AMPK, Митохондриальная функция, Снижение воспаления | AA76: A | AB76: Да
A77: 76 | B77: Инфузионная терапия | C77: ИГГТ | D77: Аппарат интервальной гипоксической-гипероксической тренировки | E77: Cellgym Pro / Lounge, Hypoxico Everest Summit II, GO2Altitude Biomedtech | F77: Интервальная гипоксия-гипероксия , митохондриальный тренинг, протокол долголетия. | G77: Уровень Lanserhof/CLP (полный медицинский) | H77: Уровень Lanserhof/CLP (полный медицинский) | I77: 35000 | J77: 40000 | K77: 28000 | L77: Китай | M77: 4800000 | N77: 3 | O77: 8 | P77: 0.05 | Q77: 0.3 | R77: Cellgym у дилеров €30–45 тыс. за Pro/Lounge; цены дистрибьюторов Hypoxico; референсы установок Cellgym в Cocoon Medical Spa. | S77: Низкая | T77: 2026-05 | U77: Оценочно: публичная цена Cellgym отсутствует. Розничная сессия €50–80. Три аппарата покрывают 25–30 сеансов в день. По России: отечественная Bio-Nova MTI/IHT , альтернатива за €12–18 тыс. | Z77: Гормезис, Активация AMPK, Снижение воспаления | AA77: B | AB77: Да
A78: 77 | B78: Инфузионная терапия | C78: IV-зона | D78: Кресло-реклайнер для IV-капельниц | E78: Champion Manufacturing 56 series, Stance Healthcare Bari, Winco CareCliner | F78: Удобное кресло-реклайнер для капельниц, NAD+ и витаминотерапии. | G78: Уровень SHA/Chenot (медицина-лайт) | H78: Уровень Lanserhof/CLP (полный медицинский) | I78: 3500 | J78: 4000 | K78: 2500 | L78: Китай | M78: 480000 | N78: 6 | O78: 10 | P78: 0.04 | Q78: 0 | R78: Champion / Stance / Winco , клинические реклайнеры $2 500–5 000; типовые предложения дилеров €3 000–4 500. | S78: Высокая | T78: 2026-05 | U78: 6–8 кресел на резорт 80–100 номеров. По России: отечественный Med-Mos и поставки через Турцию одинаково жизнеспособны. | Z78: Гормезис, Снижение воспаления | AA78: C | AB78: Да
A79: 78 | B79: Инфузионная терапия | C79: Инфузионные насосы | D79: Умный инфузионный насос | E79: B.Braun Infusomat Space, Baxter Sigma Spectrum IQ, BD Alaris | F79: Умный инфузионный насос с DERS для витаминов, NAD+, хелатной терапии и пептидов. | G79: Уровень SHA/Chenot (медицина-лайт) | H79: Уровень Lanserhof/CLP (полный медицинский) | I79: 3500 | J79: 4000 | K79: 2500 | L79: Китай | M79: 480000 | N79: 8 | O79: 7 | P79: 0.06 | Q79: 0 | R79: Outfront Medical / Coast Biomed Baxter Sigma Spectrum , восстановленные $1,5–2,5 тыс.; B.Braun , новый ~€3–4 тыс. | S79: Высокая | T79: 2026-05 | U79: 8 насосов на 6 кресел плюс 2 резервных. По России: B.Braun (Германия) поставляется, но сроки увеличены; используются и российские насосы Yelatma. | Z79: Митохондриальная функция, Очищение от стареющих клеток, Гормезис | AA79: B | AB79: Нет
A80: 79 | B80: Инфузионная терапия | C80: Озонотерапия | D80: Медицинский озонотерапевтический генератор | E80: Herrmann Apparatebau Hyper Medozon comfort, Zotzmann + Stahl OzonoSan, Humares Medozon | F80: Большая и малая аутогемотерапия, инсуффляция, озонированный физраствор. | G80: Уровень Lanserhof/CLP (полный медицинский) | H80: Уровень Lanserhof/CLP (полный медицинский) | I80: 18000 | J80: 0 | K80: 14000 | L80: Китай | M80: 2500000 | N80: 2 | O80: 10 | P80: 0.05 | Q80: 0.3 | R80: MedicalExpo Herrmann Hyper Medozon comfort; листинг HealthManagement.org; восстановленные на Medbidding €6–9 тыс.; новые €15–22 тыс. от немецких дилеров. | S80: Средняя | T80: 2026-05 | U80: Жёстко регулируется: запрещено/ограничено в США (FDA), разрешено в Германии, Австрии, Швейцарии, Испании, России под медицинским контролем. По России: озонотерапия имеет зарегистрированные показания Минздрава; отечественная альтернатива , Медозонс-БМ. | Z80: Гостевой опыт | AA80: B | AB80: Нет
A81: 80 | B81: Кухня и F&B | C81: Хлебопекарная печь | D81: Подовая/конвекционная хлебопекарная печь | E81: MIWE Condo 3.0608, MIWE econo, Wachtel | F81: Собственный хлеб, выпечка, безглютеновая продукция. | G81: Уровень Six Senses Place (велнес-плюс) | H81: Уровень Lanserhof/CLP (полный медицинский) | I81: 42000 | J81: 52000 | K81: 38000 | L81: Китай | M81: 5300000 | N81: 1 | O81: 15 | P81: 0.04 | Q81: 0 | R81: Ориентировочные цены MIWE/Wachtel (archiexpo, bakeryequipment.com) для трёхподовой модели. | S81: Средняя | T81: 2026-05 | U81: Органическая безглютеновая пекарня в стиле Lanserhof требует подовую печь с расстойкой. | Z81: Гостевой опыт | AA81: B | AB81: Нет
A82: 81 | B82: Кухня и F&B | C82: Холодный цех | D82: Станция холодной кухни (охлаждаемая зона подготовки и подачи) | E82: Inomak, True, Hoshizaki | F82: Салаты, raw-блюда, сашими, подача чистой кухни. | G82: Уровень Six Senses Place (велнес-плюс) | H82: Уровень SHA/Chenot (медицина-лайт) | I82: 35000 | J82: 42000 | K82: 28000 | L82: Китай | M82: 4400000 | N82: 1 | O82: 12 | P82: 0.04 | Q82: 0 | R82: Inomak/True (дилеры ЕС); линейная зона 6–8 м. | S82: Средняя | T82: 2026-05 | U82: Критично для raw- и clean-программ (стиль Chenot). | Z82: Гостевой опыт | AA82: C | AB82: Нет
A83: 82 | B83: Кухня и F&B | C83: Пароконвектомат | D83: Премиальный пароконвектомат (10×1/1 GN) | E83: Rational iCombi Pro 10-1/1, Convotherm 4 easyTouch | F83: Терапевтическая и ресторанная кухня; пар, конвекция, низкие температуры. | G83: Уровень Six Senses Place (велнес-плюс) | H83: Уровень Lanserhof/CLP (полный медицинский) | I83: 22000 | J83: 27000 | K83: 19000 | L83: Китай | M83: 2750000 | N83: 3 | O83: 12 | P83: 0.05 | Q83: 0 | R83: Дилеры Rational (WebstaurantStore, Buzz Catering, Nella) 2025; российский дилер ~+25% к ЕС. | S83: Высокая | T83: 2026-05 | U83: Три аппарата покрывают терапевтическую, горячую и банкетную кухни. | Z83: Гормезис, Гостевой опыт | AA83: C | AB83: Нет
A84: 83 | B84: Кухня и F&B | C84: Пароконвектомат (компакт) | D84: Компактный пароконвектомат (6×1/1 GN) | E84: Rational iCombi Pro 6-1/1, UNOX ChefTop | F84: Кондитерский цех, рыба, диетическая зона, room-service. | G84: Уровень Six Senses Place (велнес-плюс) | H84: Уровень SHA/Chenot (медицина-лайт) | I84: 14500 | J84: 18000 | K84: 12000 | L84: Китай | M84: 1800000 | N84: 2 | O84: 12 | P84: 0.05 | Q84: 0 | R84: Прайс Rational; дилеры UNOX (ЕС) 2025. | S84: Высокая | T84: 2026-05 | U84: Используется в кондитерской и дополнительной диетической линии. | Z84: Гостевой опыт | AA84: B | AB84: Нет
A85: 84 | B85: Кухня и F&B | C85: Посудомоечная машина (конвейерная) | D85: Конвейерная/тоннельная посудомоечная машина | E85: Hobart FT1000e, Winterhalter MTF, Meiko M-iQ | F85: Основная линия моечной для банкетов и ресторана. | G85: Уровень Six Senses Place (велнес-плюс) | H85: Уровень Lanserhof/CLP (полный медицинский) | I85: 75000 | J85: 90000 | K85: 60000 | L85: Китай | M85: 9500000 | N85: 1 | O85: 12 | P85: 0.05 | Q85: 0 | R85: Hobart, Winterhalter , дилеры ЕС 2025; hobartcorp.com. | S85: Высокая | T85: 2026-05 | U85: Обязательна для отеля 80–100 номеров с банкетной нагрузкой. | Z85: Гостевой опыт | AA85: B | AB85: Нет
A86: 85 | B86: Кухня и F&B | C86: Посудомоечные машины (фронтальные и подстольные) | D86: Подстольные и фронтальные стаканомойки и посудомойки (комплект) | E86: Hobart, Winterhalter UC-M, Meiko | F86: Бар, сокобар, станции подготовки. | G86: Уровень Six Senses Place (велнес-плюс) | H86: Уровень Lanserhof/CLP (полный медицинский) | I86: 28000 | J86: 34000 | K86: 22000 | L86: Китай | M86: 3500000 | N86: 4 | O86: 10 | P86: 0.05 | Q86: 0 | R86: Hobart/Winterhalter , дилеры ЕС 2025. | S86: Высокая | T86: 2026-05 | U86: Комплект из 4 машин закрывает бар, сокобар, банкеты и сателлит. | Z86: Гостевой опыт | AA86: B | AB86: Нет
... A130: 129 | B130: Сон и неврология | C130: Носимые устройства | D130: Премиальные носимые устройства (Oura/WHOOP/Apple Watch) | E130: Oura Ring Gen 4, WHOOP 5.0, Apple Watch Ultra 2 | F130: Стадии сна, ВСР, восстановление, тренировочная нагрузка , гостевой носимый гаджет в составе программы. | G130: Уровень SHA/Chenot (медицина-лайт) | H130: Уровень Lanserhof/CLP (полный медицинский) | I130: 8000 | J130: 9000 | K130: 6500 | L130: Китай | M130: 1100000 | N130: 25 | O130: 3 | P130: 0.1 | Q130: 0 | R130: Oura Ring $349–499; WHOOP $239 + $30 в месяц; Apple Watch Ultra 2 $799. Парк 25 единиц по средней цене €320. | S130: Высокая | T130: 2026-05 | U130: Парк выдаётся гостям на проживание. Подписки относятся к OPEX. По России: Apple Watch и Oura , параллельный импорт (надбавка 30%); WHOOP официально недоступен. | Z130: Инфраструктура | AA130: A | AB130: Нет
A131: 130 | B131: Телемедицина и цифровое здоровье | C131: Интеграция данных CGM | D131: Интеграция платформы CGM (тип Levels) | E131: Levels Health API, Nutrisense, Veri | F131: Передача данных непрерывных глюкометров в платформу долголетия. | G131: Уровень Six Senses Place (велнес-плюс) | H131: Уровень SHA/Chenot (медицина-лайт) | I131: 18000 | J131: 22000 | K131: 15000 | L131: Сингапур | M131: 2200000 | N131: 1 | O131: 5 | P131: 0 | Q131: 0 | R131: Levels API B2B / Nutrisense; ориентировочная стоимость интеграции. | S131: Низкая | T131: 2026-05 | U131: Сенсоры тарифицируются отдельно по гостю. По России: Abbott Libre , параллельным импортом; портал , российская разработка. | V131: 14000 | W131: 17000 | X131: 11000 | Y131: 1400000 | Z131: Инфраструктура, Диагностика | AA131: B | AB131: Нет
A132: 131 | B132: Телемедицина и цифровое здоровье | C132: Платформа постгостевого коучинга | D132: Приложение для коучинга и консьерж-сервиса (после выезда) | E132: MindBody Plus, Healthie, custom on Twilio | F132: Индивидуальный коучинг, контент и удержание клиента в течение 6–12 месяцев после визита. | G132: Уровень Six Senses Place (велнес-плюс) | H132: Уровень Lanserhof/CLP (полный медицинский) | I132: 65000 | J132: 80000 | K132: 55000 | L132: Сингапур | M132: 7500000 | N132: 1 | O132: 5 | P132: 0 | Q132: 1 | R132: Healthie / индивидуальная разработка; референс модели Lanserhof@home. | S132: Низкая | T132: 2026-05 | U132: Критичный драйвер выручки и возврата гостей , формирует ARR через подписку. Штатный показатель , численность коучей. | V132: 30000 | W132: 38000 | X132: 24000 | Y132: 2400000 | Z132: Диагностика | AA132: B | AB132: Нет
A133: 132 | B133: Телемедицина и цифровое здоровье | C133: Платформа видеоконсультаций | D133: HIPAA/GDPR-совместимая телемедицинская платформа | E133: Doxy.me Enterprise, Teladoc B2B, Amwell | F133: Видеоконсультации с врачами долголетия после визита. | G133: Уровень Six Senses Place (велнес-плюс) | H133: Уровень Lanserhof/CLP (полный медицинский) | I133: 25000 | J133: 32000 | K133: 22000 | L133: Сингапур | M133: 2500000 | N133: 1 | O133: 5 | P133: 0 | Q133: 0 | R133: Doxy.me Clinic $50 за пользователя в месяц; Enterprise , индивидуально; ~30–40 пользователей. | S133: Высокая | T133: 2026-05 | U133: По России: используются российские альтернативы (Mednote, Doctis) из-за GDPR/152-ФЗ и санкций. | V133: 22000 | W133: 28000 | X133: 18000 | Y133: 1800000 | Z133: Диагностика | AA133: B | AB133: Нет
A134: 133 | B134: Телемедицина и цифровое здоровье | C134: Носимые устройства , WHOOP/Garmin | D134: WHOOP Unite + Garmin Health (корпоративный пакет) | E134: WHOOP Unite, Garmin Health enterprise | F134: Учёт нагрузки и восстановления, коучинг по перформансу и долголетию. | G134: Опциональный апселл | H134: Опциональный апселл | I134: 35000 | J134: 42000 | K134: 28000 | L134: Сингапур | M134: 4200000 | N134: 1 | O134: 4 | P134: 0 | Q134: 0 | R134: WHOOP Unite (200+ корпоративных клиентов, prnewswire 2022); Garmin Health B2B. | S134: Низкая | T134: 2026-05 | U134: Опционально как дополнение к Oura. По России: оборудование , параллельным импортом. | V134: 25000 | W134: 30000 | X134: 20000 | Y134: 2400000 | Z134: Диагностика | AA134: A | AB134: Нет
A135: 134 | B135: Телемедицина и цифровое здоровье | C135: Носимые устройства , кольца | D135: Корпоративное развёртывание Oura Ring | E135: Oura for Business, Ultrahuman Ring, RingConn | F135: Отслеживание сна, ВСР и восстановления; долгосрочный крючок вовлечения. | G135: Уровень Six Senses Place (велнес-плюс) | H135: Уровень Lanserhof/CLP (полный медицинский) | I135: 65000 | J135: 80000 | K135: 55000 | L135: Сингапур | M135: 7500000 | N135: 1 | O135: 4 | P135: 0 | Q135: 0 | R135: Oura for Business B2B (sacra.com , 23% выручки); ~200 колец по $300 плюс дашборд. | S135: Средняя | T135: 2026-05 | U135: Стартовый парк 150–250 колец и B2B-дашборд; ежегодное пополнение ~25%. | V135: 18000 | W135: 22000 | X135: 14000 | Y135: 1800000 | Z135: Инфраструктура, Гостевой опыт | AA135: C | AB135: Нет

Sheet Сводка CapEx по уровням
A1: СВОДКА CapEx ПО УРОВНЯМ
A2: Живой свод из реестра через SUMPRODUCT. Меняйте цены в реестре , итоги обновятся.
A3: keys_count | B3: 90 | C3: ← редактируемый параметр (середина диапазона 80–100 номеров)
A4: Курс RUB/EUR | B4: 92
A5: Курс RUB/USD | B5: 85
A7: РЕГИОН , Европа (€)
A8: Группа | B8: Уровень Lanserhof/CLP (полный медицинский) | C8: Уровень SHA/Chenot (медицина-лайт) | D8: Уровень Six Senses Place (велнес-плюс)
A9: Итого медицинский CapEx | B9: =SUMPRODUCT((((1*('Реестр оборудования'!$G$2:$G$135="Уровень Six Senses Place (велнес-плюс)")+2*('Реестр оборудования'!$G$2:$G$135="Уровень SHA/Chenot (медицина-лайт)")+3*('Реестр оборудования'!$G$2:$G$135="Уровень Lanserhof/CLP (полный медицинский)"))>0)*((1*('Реестр оборудования'!$G$2:$G$135="Уровень Six Senses Place (велнес-плюс)")+2*('Реестр оборудования'!$G$2:$G$135="Уровень SHA/Chenot (медицина-лайт)")+3*('Реестр оборудования'!$G$2:$G$135="Уровень Lanserhof/CLP (полный медицинский)"))<=3))*(('Реестр оборудования'!$B$2:$B$135="Лучевая диагностика")+('Реестр оборудования'!$B$2:$B$135="Лаборатория и биомаркеры")+('Реестр оборудования'!$B$2:$B$135="Кардиология и пульмонология")+('Реестр оборудования'!$B$2:$B$135="Сон и неврология")+('Реестр оборудования'!$B$2:$B$135="Инфузионная терапия")+('Реестр оборудования'!$B$2:$B$135="Эстетика и регенеративные процедуры")+('Реестр оборудования'!$B$2:$B$135="Нутрициология и ЖКТ-диагностика")+('Реестр оборудования'!$B$2:$B$135="Состав тела и функциональная диагностика")+('Реестр оборудования'!$B$2:$B$135="Телемедицина и цифровое здоровье"))*IFERROR('Реестр оборудования'!$N$2:$N$135+0,0)*IFERROR('Реестр оборудования'!$I$2:$I$135+0,0)) -> 3250000 | C9: =SUMPRODUCT((((1*('Реестр оборудования'!$G$2:$G$135="Уровень Six Senses Place (велнес-плюс)")+2*('Реестр оборудования'!$G$2:$G$135="Уровень SHA/Chenot (медицина-лайт)")+3*('Реестр оборудования'!$G$2:$G$135="Уровень Lanserhof/CLP (полный медицинский)"))>0)*((1*('Реестр оборудования'!$G$2:$G$135="Уровень Six Senses Place (велнес-плюс)")+2*('Реестр оборудования'!$G$2:$G$135="Уровень SHA/Chenot (медицина-лайт)")+3*('Реестр оборудования'!$G$2:$G$135="Уровень Lanserhof/CLP (полный медицинский)"))<=2))*(('Реестр оборудования'!$B$2:$B$135="Лучевая диагностика")+('Реестр оборудования'!$B$2:$B$135="Лаборатория и биомаркеры")+('Реестр оборудования'!$B$2:$B$135="Кардиология и пульмонология")+('Реестр оборудования'!$B$2:$B$135="Сон и неврология")+('Реестр оборудования'!$B$2:$B$135="Инфузионная терапия")+('Реестр оборудования'!$B$2:$B$135="Эстетика и регенеративные процедуры")+('Реестр оборудования'!$B$2:$B$135="Нутрициология и ЖКТ-диагностика")+('Реестр оборудования'!$B$2:$B$135="Состав тела и функциональная диагностика")+('Реестр оборудования'!$B$2:$B$135="Телемедицина и цифровое здоровье"))*IFERROR('Реестр оборудования'!$N$2:$N$135+0,0)*IFERROR('Реестр оборудования'!$I$2:$I$135+0,0)) -> 2200000 | D9: =SUMPRODUCT((((1*('Реестр оборудования'!$G$2:$G$135="Уровень Six Senses Place (велнес-плюс)")+2*('Реестр оборудования'!$G$2:$G$135="Уровень SHA/Chenot (медицина-лайт)")+3*('Реестр оборудования'!$G$2:$G$135="Уровень Lanserhof/CLP (полный медицинский)"))>0)*((1*('Реестр оборудования'!$G$2:$G$135="Уровень Six Senses Place (велнес-плюс)")+2*('Реестр оборудования'!$G$2:$G$135="Уровень SHA/Chenot (медицина-лайт)")+3*('Реестр оборудования'!$G$2:$G$135="Уровень Lanserhof/CLP (полный медицинский)"))<=1))*(('Реестр оборудования'!$B$2:$B$135="Лучевая диагностика")+('Реестр оборудования'!$B$2:$B$135="Лаборатория и биомаркеры")+('Реестр оборудования'!$B$2:$B$135="Кардиология и пульмонология")+('Реестр оборудования'!$B$2:$B$135="Сон и неврология")+('Реестр оборудования'!$B$2:$B$135="Инфузионная терапия")+('Реестр оборудования'!$B$2:$B$135="Эстетика и регенеративные процедуры")+('Реестр оборудования'!$B$2:$B$135="Нутрициология и ЖКТ-диагностика")+('Реестр оборудования'!$B$2:$B$135="Состав тела и функциональная диагностика")+('Реестр оборудования'!$B$2:$B$135="Телемедицина и цифровое здоровье"))*IFERROR('Реестр оборудования'!$N$2:$N$135+0,0)*IFERROR('Реестр оборудования'!$I$2:$I$135+0,0)) -> 300000
A10: Итого SPA и восстановление | B10: =SUMPRODUCT((((1*('Реестр оборудования'!$G$2:$G$135="Уровень Six Senses Place (велнес-плюс)")+2*('Реестр оборудования'!$G$2:$G$135="Уровень SHA/Chenot (медицина-лайт)")+3*('Реестр оборудования'!$G$2:$G$135="Уровень Lanserhof/CLP (полный медицинский)"))>0)*((1*('Реестр оборудования'!$G$2:$G$135="Уровень Six Senses Place (велнес-плюс)")+2*('Реестр оборудования'!$G$2:$G$135="Уровень SHA/Chenot (медицина-лайт)")+3*('Реестр оборудования'!$G$2:$G$135="Уровень Lanserhof/CLP (полный медицинский)"))<=3))*(('Реестр оборудования'!$B$2:$B$135="Гидротерапия и SPA")+('Реестр оборудования'!$B$2:$B$135="Криотерапия и термальные зоны"))*IFERROR('Реестр оборудования'!$N$2:$N$135+0,0)*IFERROR('Реестр оборудования'!$I$2:$I$135+0,0)) -> 1064000 | C10: =SUMPRODUCT((((1*('Реестр оборудования'!$G$2:$G$135="Уровень Six Senses Place (велнес-плюс)")+2*('Реестр оборудования'!$G$2:$G$135="Уровень SHA/Chenot (медицина-лайт)")+3*('Реестр оборудования'!$G$2:$G$135="Уровень Lanserhof/CLP (полный медицинский)"))>0)*((1*('Реестр оборудования'!$G$2:$G$135="Уровень Six Senses Place (велнес-плюс)")+2*('Реестр оборудования'!$G$2:$G$135="Уровень SHA/Chenot (медицина-лайт)")+3*('Реестр оборудования'!$G$2:$G$135="Уровень Lanserhof/CLP (полный медицинский)"))<=2))*(('Реестр оборудования'!$B$2:$B$135="Гидротерапия и SPA")+('Реестр оборудования'!$B$2:$B$135="Криотерапия и термальные зоны"))*IFERROR('Реестр оборудования'!$N$2:$N$135+0,0)*IFERROR('Реестр оборудования'!$I$2:$I$135+0,0)) -> 1064000 | D10: =SUMPRODUCT((((1*('Реестр оборудования'!$G$2:$G$135="Уровень Six Senses Place (велнес-плюс)")+2*('Реестр оборудования'!$G$2:$G$135="Уровень SHA/Chenot (медицина-лайт)")+3*('Реестр оборудования'!$G$2:$G$135="Уровень Lanserhof/CLP (полный медицинский)"))>0)*((1*('Реестр оборудования'!$G$2:$G$135="Уровень Six Senses Place (велнес-плюс)")+2*('Реестр оборудования'!$G$2:$G$135="Уровень SHA/Chenot (медицина-лайт)")+3*('Реестр оборудования'!$G$2:$G$135="Уровень Lanserhof/CLP (полный медицинский)"))<=1))*(('Реестр оборудования'!$B$2:$B$135="Гидротерапия и SPA")+('Реестр оборудования'!$B$2:$B$135="Криотерапия и термальные зоны"))*IFERROR('Реестр оборудования'!$N$2:$N$135+0,0)*IFERROR('Реестр оборудования'!$I$2:$I$135+0,0)) -> 1064000
A11: Итого фитнес и движение | B11: =SUMPRODUCT((((1*('Реестр оборудования'!$G$2:$G$135="Уровень Six Senses Place (велнес-плюс)")+2*('Реестр оборудования'!$G$2:$G$135="Уровень SHA/Chenot (медицина-лайт)")+3*('Реестр оборудования'!$G$2:$G$135="Уровень Lanserhof/CLP (полный медицинский)"))>0)*((1*('Реестр оборудования'!$G$2:$G$135="Уровень Six Senses Place (велнес-плюс)")+2*('Реестр оборудования'!$G$2:$G$135="Уровень SHA/Chenot (медицина-лайт)")+3*('Реестр оборудования'!$G$2:$G$135="Уровень Lanserhof/CLP (полный медицинский)"))<=3))*(('Реестр оборудования'!$B$2:$B$135="Движение и реабилитация")+('Реестр оборудования'!$B$2:$B$135="Тренажёрный зал и силовая зона"))*IFERROR('Реестр оборудования'!$N$2:$N$135+0,0)*IFERROR('Реестр оборудования'!$I$2:$I$135+0,0)) -> 720000 | C11: =SUMPRODUCT((((1*('Реестр оборудования'!$G$2:$G$135="Уровень Six Senses Place (велнес-плюс)")+2*('Реестр оборудования'!$G$2:$G$135="Уровень SHA/Chenot (медицина-лайт)")+3*('Реестр оборудования'!$G$2:$G$135="Уровень Lanserhof/CLP (полный медицинский)"))>0)*((1*('Реестр оборудования'!$G$2:$G$135="Уровень Six Senses Place (велнес-плюс)")+2*('Реестр оборудования'!$G$2:$G$135="Уровень SHA/Chenot (медицина-лайт)")+3*('Реестр оборудования'!$G$2:$G$135="Уровень Lanserhof/CLP (полный медицинский)"))<=2))*(('Реестр оборудования'!$B$2:$B$135="Движение и реабилитация")+('Реестр оборудования'!$B$2:$B$135="Тренажёрный зал и силовая зона"))*IFERROR('Реестр оборудования'!$N$2:$N$135+0,0)*IFERROR('Реестр оборудования'!$I$2:$I$135+0,0)) -> 540000 | D11: =SUMPRODUCT((((1*('Реестр оборудования'!$G$2:$G$135="Уровень Six Senses Place (велнес-плюс)")+2*('Реестр оборудования'!$G$2:$G$135="Уровень SHA/Chenot (медицина-лайт)")+3*('Реестр оборудования'!$G$2:$G$135="Уровень Lanserhof/CLP (полный медицинский)"))>0)*((1*('Реестр оборудования'!$G$2:$G$135="Уровень Six Senses Place (велнес-плюс)")+2*('Реестр оборудования'!$G$2:$G$135="Уровень SHA/Chenot (медицина-лайт)")+3*('Реестр оборудования'!$G$2:$G$135="Уровень Lanserhof/CLP (полный медицинский)"))<=1))*(('Реестр оборудования'!$B$2:$B$135="Движение и реабилитация")+('Реестр оборудования'!$B$2:$B$135="Тренажёрный зал и силовая зона"))*IFERROR('Реестр оборудования'!$N$2:$N$135+0,0)*IFERROR('Реестр оборудования'!$I$2:$I$135+0,0)) -> 540000
A12: Итого ИТ и ПО (единовременный CapEx) | B12: =SUMPRODUCT((((1*('Реестр оборудования'!$G$2:$G$135="Уровень Six Senses Place (велнес-плюс)")+2*('Реестр оборудования'!$G$2:$G$135="Уровень SHA/Chenot (медицина-лайт)")+3*('Реестр оборудования'!$G$2:$G$135="Уровень Lanserhof/CLP (полный медицинский)"))>0)*((1*('Реестр оборудования'!$G$2:$G$135="Уровень Six Senses Place (велнес-плюс)")+2*('Реестр оборудования'!$G$2:$G$135="Уровень SHA/Chenot (медицина-лайт)")+3*('Реестр оборудования'!$G$2:$G$135="Уровень Lanserhof/CLP (полный медицинский)"))<=3))*(('Реестр оборудования'!$B$2:$B$135="ИТ, МИС, ПО для пациентов"))*IFERROR('Реестр оборудования'!$N$2:$N$135+0,0)*IFERROR('Реестр оборудования'!$I$2:$I$135+0,0)) -> 855000 | C12: =SUMPRODUCT((((1*('Реестр оборудования'!$G$2:$G$135="Уровень Six Senses Place (велнес-плюс)")+2*('Реестр оборудования'!$G$2:$G$135="Уровень SHA/Chenot (медицина-лайт)")+3*('Реестр оборудования'!$G$2:$G$135="Уровень Lanserhof/CLP (полный медицинский)"))>0)*((1*('Реестр оборудования'!$G$2:$G$135="Уровень Six Senses Place (велнес-плюс)")+2*('Реестр оборудования'!$G$2:$G$135="Уровень SHA/Chenot (медицина-лайт)")+3*('Реестр оборудования'!$G$2:$G$135="Уровень Lanserhof/CLP (полный медицинский)"))<=2))*(('Реестр оборудования'!$B$2:$B$135="ИТ, МИС, ПО для пациентов"))*IFERROR('Реестр оборудования'!$N$2:$N$135+0,0)*IFERROR('Реестр оборудования'!$I$2:$I$135+0,0)) -> 855000 | D12: =SUMPRODUCT((((1*('Реестр оборудования'!$G$2:$G$135="Уровень Six Senses Place (велнес-плюс)")+2*('Реестр оборудования'!$G$2:$G$135="Уровень SHA/Chenot (медицина-лайт)")+3*('Реестр оборудования'!$G$2:$G$135="Уровень Lanserhof/CLP (полный медицинский)"))>0)*((1*('Реестр оборудования'!$G$2:$G$135="Уровень Six Senses Place (велнес-плюс)")+2*('Реестр оборудования'!$G$2:$G$135="Уровень SHA/Chenot (медицина-лайт)")+3*('Реестр оборудования'!$G$2:$G$135="Уровень Lanserhof/CLP (полный медицинский)"))<=1))*(('Реестр оборудования'!$B$2:$B$135="ИТ, МИС, ПО для пациентов"))*IFERROR('Реестр оборудования'!$N$2:$N$135+0,0)*IFERROR('Реестр оборудования'!$I$2:$I$135+0,0)) -> 760000
A13: Итого кухня и F&B | B13: =SUMPRODUCT((((1*('Реестр оборудования'!$G$2:$G$135="Уровень Six Senses Place (велнес-плюс)")+2*('Реестр оборудования'!$G$2:$G$135="Уровень SHA/Chenot (медицина-лайт)")+3*('Реестр оборудования'!$G$2:$G$135="Уровень Lanserhof/CLP (полный медицинский)"))>0)*((1*('Реестр оборудования'!$G$2:$G$135="Уровень Six Senses Place (велнес-плюс)")+2*('Реестр оборудования'!$G$2:$G$135="Уровень SHA/Chenot (медицина-лайт)")+3*('Реестр оборудования'!$G$2:$G$135="Уровень Lanserhof/CLP (полный медицинский)"))<=3))*(('Реестр оборудования'!$B$2:$B$135="Кухня и F&B"))*IFERROR('Реестр оборудования'!$N$2:$N$135+0,0)*IFERROR('Реестр оборудования'!$I$2:$I$135+0,0)) -> 630000 | C13: =SUMPRODUCT((((1*('Реестр оборудования'!$G$2:$G$135="Уровень Six Senses Place (велнес-плюс)")+2*('Реестр оборудования'!$G$2:$G$135="Уровень SHA/Chenot (медицина-лайт)")+3*('Реестр оборудования'!$G$2:$G$135="Уровень Lanserhof/CLP (полный медицинский)"))>0)*((1*('Реестр оборудования'!$G$2:$G$135="Уровень Six Senses Place (велнес-плюс)")+2*('Реестр оборудования'!$G$2:$G$135="Уровень SHA/Chenot (медицина-лайт)")+3*('Реестр оборудования'!$G$2:$G$135="Уровень Lanserhof/CLP (полный медицинский)"))<=2))*(('Реестр оборудования'!$B$2:$B$135="Кухня и F&B"))*IFERROR('Реестр оборудования'!$N$2:$N$135+0,0)*IFERROR('Реестр оборудования'!$I$2:$I$135+0,0)) -> 630000 | D13: =SUMPRODUCT((((1*('Реестр оборудования'!$G$2:$G$135="Уровень Six Senses Place (велнес-плюс)")+2*('Реестр оборудования'!$G$2:$G$135="Уровень SHA/Chenot (медицина-лайт)")+3*('Реестр оборудования'!$G$2:$G$135="Уровень Lanserhof/CLP (полный медицинский)"))>0)*((1*('Реестр оборудования'!$G$2:$G$135="Уровень Six Senses Place (велнес-плюс)")+2*('Реестр оборудования'!$G$2:$G$135="Уровень SHA/Chenot (медицина-лайт)")+3*('Реестр оборудования'!$G$2:$G$135="Уровень Lanserhof/CLP (полный медицинский)"))<=1))*(('Реестр оборудования'!$B$2:$B$135="Кухня и F&B"))*IFERROR('Реестр оборудования'!$N$2:$N$135+0,0)*IFERROR('Реестр оборудования'!$I$2:$I$135+0,0)) -> 630000
A14: Итого медицинская инфраструктура | B14: =SUMPRODUCT((((1*('Реестр оборудования'!$G$2:$G$135="Уровень Six Senses Place (велнес-плюс)")+2*('Реестр оборудования'!$G$2:$G$135="Уровень SHA/Chenot (медицина-лайт)")+3*('Реестр оборудования'!$G$2:$G$135="Уровень Lanserhof/CLP (полный медицинский)"))>0)*((1*('Реестр оборудования'!$G$2:$G$135="Уровень Six Senses Place (велнес-плюс)")+2*('Реестр оборудования'!$G$2:$G$135="Уровень SHA/Chenot (медицина-лайт)")+3*('Реестр оборудования'!$G$2:$G$135="Уровень Lanserhof/CLP (полный медицинский)"))<=3))*(('Реестр оборудования'!$B$2:$B$135="Медицинская инфраструктура"))*IFERROR('Реестр оборудования'!$N$2:$N$135+0,0)*IFERROR('Реестр оборудования'!$I$2:$I$135+0,0)) -> 910000 | C14: =SUMPRODUCT((((1*('Реестр оборудования'!$G$2:$G$135="Уровень Six Senses Place (велнес-плюс)")+2*('Реестр оборудования'!$G$2:$G$135="Уровень SHA/Chenot (медицина-лайт)")+3*('Реестр оборудования'!$G$2:$G$135="Уровень Lanserhof/CLP (полный медицинский)"))>0)*((1*('Реестр оборудования'!$G$2:$G$135="Уровень Six Senses Place (велнес-плюс)")+2*('Реестр оборудования'!$G$2:$G$135="Уровень SHA/Chenot (медицина-лайт)")+3*('Реестр оборудования'!$G$2:$G$135="Уровень Lanserhof/CLP (полный медицинский)"))<=2))*(('Реестр оборудования'!$B$2:$B$135="Медицинская инфраструктура"))*IFERROR('Реестр оборудования'!$N$2:$N$135+0,0)*IFERROR('Реестр оборудования'!$I$2:$I$135+0,0)) -> 260000 | D14: =SUMPRODUCT((((1*('Реестр оборудования'!$G$2:$G$135="Уровень Six Senses Place (велнес-плюс)")+2*('Реестр оборудования'!$G$2:$G$135="Уровень SHA/Chenot (медицина-лайт)")+3*('Реестр оборудования'!$G$2:$G$135="Уровень Lanserhof/CLP (полный медицинский)"))>0)*((1*('Реестр оборудования'!$G$2:$G$135="Уровень Six Senses Place (велнес-плюс)")+2*('Реестр оборудования'!$G$2:$G$135="Уровень SHA/Chenot (медицина-лайт)")+3*('Реестр оборудования'!$G$2:$G$135="Уровень Lanserhof/CLP (полный медицинский)"))<=1))*(('Реестр оборудования'!$B$2:$B$135="Медицинская инфраструктура"))*IFERROR('Реестр оборудования'!$N$2:$N$135+0,0)*IFERROR('Реестр оборудования'!$I$2:$I$135+0,0)) -> 0
A15: ИТОГО CapEx | B15: =SUM(B9:B14) -> 7429000 | C15: =SUM(C9:C14) -> 5549000 | D15: =SUM(D9:D14) -> 3294000
A16: CapEx на номер | B16: =B15/$B$3 -> 82544.444 | C16: =C15/$B$3 -> 61655.556 | D16: =D15/$B$3 -> 36600
A18: РЕГИОН , Северная Америка ($)
A19: Группа | B19: Уровень Lanserhof/CLP (полный медицинский) | C19: Уровень SHA/Chenot (медицина-лайт) | D19: Уровень Six Senses Place (велнес-плюс)
A20: Итого медицинский CapEx | B20: =SUMPRODUCT((((1*('Реестр оборудования'!$G$2:$G$135="Уровень Six Senses Place (велнес-плюс)")+2*('Реестр оборудования'!$G$2:$G$135="Уровень SHA/Chenot (медицина-лайт)")+3*('Реестр оборудования'!$G$2:$G$135="Уровень Lanserhof/CLP (полный медицинский)"))>0)*((1*('Реестр оборудования'!$G$2:$G$135="Уровень Six Senses Place (велнес-плюс)")+2*('Реестр оборудования'!$G$2:$G$135="Уровень SHA/Chenot (медицина-лайт)")+3*('Реестр оборудования'!$G$2:$G$135="Уровень Lanserhof/CLP (полный медицинский)"))<=3))*(('Реестр оборудования'!$B$2:$B$135="Лучевая диагностика")+('Реестр оборудования'!$B$2:$B$135="Лаборатория и биомаркеры")+('Реестр оборудования'!$B$2:$B$135="Кардиология и пульмонология")+('Реестр оборудования'!$B$2:$B$135="Сон и неврология")+('Реестр оборудования'!$B$2:$B$135="Инфузионная терапия")+('Реестр оборудования'!$B$2:$B$135="Эстетика и регенеративные процедуры")+('Реестр оборудования'!$B$2:$B$135="Нутрициология и ЖКТ-диагностика")+('Реестр оборудования'!$B$2:$B$135="Состав тела и функциональная диагностика")+('Реестр оборудования'!$B$2:$B$135="Телемедицина и цифровое здоровье"))*IFERROR('Реестр оборудования'!$N$2:$N$135+0,0)*IFERROR('Реестр оборудования'!$J$2:$J$135+0,0)) -> 0 | C20: =SUMPRODUCT((((1*('Реестр оборудования'!$G$2:$G$135="Уровень Six Senses Place (велнес-плюс)")+2*('Реестр оборудования'!$G$2:$G$135="Уровень SHA/Chenot (медицина-лайт)")+3*('Реестр оборудования'!$G$2:$G$135="Уровень Lanserhof/CLP (полный медицинский)"))>0)*((1*('Реестр оборудования'!$G$2:$G$135="Уровень Six Senses Place (велнес-плюс)")+2*('Реестр оборудования'!$G$2:$G$135="Уровень SHA/Chenot (медицина-лайт)")+3*('Реестр оборудования'!$G$2:$G$135="Уровень Lanserhof/CLP (полный медицинский)"))<=2))*(('Реестр оборудования'!$B$2:$B$135="Лучевая диагностика")+('Реестр оборудования'!$B$2:$B$135="Лаборатория и биомаркеры")+('Реестр оборудования'!$B$2:$B$135="Кардиология и пульмонология")+('Реестр оборудования'!$B$2:$B$135="Сон и неврология")+('Реестр оборудования'!$B$2:$B$135="Инфузионная терапия")+('Реестр оборудования'!$B$2:$B$135="Эстетика и регенеративные процедуры")+('Реестр оборудования'!$B$2:$B$135="Нутрициология и ЖКТ-диагностика")+('Реестр оборудования'!$B$2:$B$135="Состав тела и функциональная диагностика")+('Реестр оборудования'!$B$2:$B$135="Телемедицина и цифровое здоровье"))*IFERROR('Реестр оборудования'!$N$2:$N$135+0,0)*IFERROR('Реестр оборудования'!$J$2:$J$135+0,0)) -> 0 | D20: =SUMPRODUCT((((1*('Реестр оборудования'!$G$2:$G$135="Уровень Six Senses Place (велнес-плюс)")+2*('Реестр оборудования'!$G$2:$G$135="Уровень SHA/Chenot (медицина-лайт)")+3*('Реестр оборудования'!$G$2:$G$135="Уровень Lanserhof/CLP (полный медицинский)"))>0)*((1*('Реестр оборудования'!$G$2:$G$135="Уровень Six Senses Place (велнес-плюс)")+2*('Реестр оборудования'!$G$2:$G$135="Уровень SHA/Chenot (медицина-лайт)")+3*('Реестр оборудования'!$G$2:$G$135="Уровень Lanserhof/CLP (полный медицинский)"))<=1))*(('Реестр оборудования'!$B$2:$B$135="Лучевая диагностика")+('Реестр оборудования'!$B$2:$B$135="Лаборатория и биомаркеры")+('Реестр оборудования'!$B$2:$B$135="Кардиология и пульмонология")+('Реестр оборудования'!$B$2:$B$135="Сон и неврология")+('Реестр оборудования'!$B$2:$B$135="Инфузионная терапия")+('Реестр оборудования'!$B$2:$B$135="Эстетика и регенеративные процедуры")+('Реестр оборудования'!$B$2:$B$135="Нутрициология и ЖКТ-диагностика")+('Реестр оборудования'!$B$2:$B$135="Состав тела и функциональная диагностика")+('Реестр оборудования'!$B$2:$B$135="Телемедицина и цифровое здоровье"))*IFERROR('Реестр оборудования'!$N$2:$N$135+0,0)*IFERROR('Реестр оборудования'!$J$2:$J$135+0,0)) -> 0
A21: Итого SPA и восстановление | B21: =SUMPRODUCT((((1*('Реестр оборудования'!$G$2:$G$135="Уровень Six Senses Place (велнес-плюс)")+2*('Реестр оборудования'!$G$2:$G$135="Уровень SHA/Chenot (медицина-лайт)")+3*('Реестр оборудования'!$G$2:$G$135="Уровень Lanserhof/CLP (полный медицинский)"))>0)*((1*('Реестр оборудования'!$G$2:$G$135="Уровень Six Senses Place (велнес-плюс)")+2*('Реестр оборудования'!$G$2:$G$135="Уровень SHA/Chenot (медицина-лайт)")+3*('Реестр оборудования'!$G$2:$G$135="Уровень Lanserhof/CLP (полный медицинский)"))<=3))*(('Реестр оборудования'!$B$2:$B$135="Гидротерапия и SPA")+('Реестр оборудования'!$B$2:$B$135="Криотерапия и термальные зоны"))*IFERROR('Реестр оборудования'!$N$2:$N$135+0,0)*IFERROR('Реестр оборудования'!$J$2:$J$135+0,0)) -> 798000 | C21: =SUMPRODUCT((((1*('Реестр оборудования'!$G$2:$G$135="Уровень Six Senses Place (велнес-плюс)")+2*('Реестр оборудования'!$G$2:$G$135="Уровень SHA/Chenot (медицина-лайт)")+3*('Реестр оборудования'!$G$2:$G$135="Уровень Lanserhof/CLP (полный медицинский)"))>0)*((1*('Реестр оборудования'!$G$2:$G$135="Уровень Six Senses Place (велнес-плюс)")+2*('Реестр оборудования'!$G$2:$G$135="Уровень SHA/Chenot (медицина-лайт)")+3*('Реестр оборудования'!$G$2:$G$135="Уровень Lanserhof/CLP (полный медицинский)"))<=2))*(('Реестр оборудования'!$B$2:$B$135="Гидротерапия и SPA")+('Реестр оборудования'!$B$2:$B$135="Криотерапия и термальные зоны"))*IFERROR('Реестр оборудования'!$N$2:$N$135+0,0)*IFERROR('Реестр оборудования'!$J$2:$J$135+0,0)) -> 798000 | D21: =SUMPRODUCT((((1*('Реестр оборудования'!$G$2:$G$135="Уровень Six Senses Place (велнес-плюс)")+2*('Реестр оборудования'!$G$2:$G$135="Уровень SHA/Chenot (медицина-лайт)")+3*('Реестр оборудования'!$G$2:$G$135="Уровень Lanserhof/CLP (полный медицинский)"))>0)*((1*('Реестр оборудования'!$G$2:$G$135="Уровень Six Senses Place (велнес-плюс)")+2*('Реестр оборудования'!$G$2:$G$135="Уровень SHA/Chenot (медицина-лайт)")+3*('Реестр оборудования'!$G$2:$G$135="Уровень Lanserhof/CLP (полный медицинский)"))<=1))*(('Реестр оборудования'!$B$2:$B$135="Гидротерапия и SPA")+('Реестр оборудования'!$B$2:$B$135="Криотерапия и термальные зоны"))*IFERROR('Реестр оборудования'!$N$2:$N$135+0,0)*IFERROR('Реестр оборудования'!$J$2:$J$135+0,0)) -> 798000
A22: Итого фитнес и движение | B22: =SUMPRODUCT((((1*('Реестр оборудования'!$G$2:$G$135="Уровень Six Senses Place (велнес-плюс)")+2*('Реестр оборудования'!$G$2:$G$135="Уровень SHA/Chenot (медицина-лайт)")+3*('Реестр оборудования'!$G$2:$G$135="Уровень Lanserhof/CLP (полный медицинский)"))>0)*((1*('Реестр оборудования'!$G$2:$G$135="Уровень Six Senses Place (велнес-плюс)")+2*('Реестр оборудования'!$G$2:$G$135="Уровень SHA/Chenot (медицина-лайт)")+3*('Реестр оборудования'!$G$2:$G$135="Уровень Lanserhof/CLP (полный медицинский)"))<=3))*(('Реестр оборудования'!$B$2:$B$135="Движение и реабилитация")+('Реестр оборудования'!$B$2:$B$135="Тренажёрный зал и силовая зона"))*IFERROR('Реестр оборудования'!$N$2:$N$135+0,0)*IFERROR('Реестр оборудования'!$J$2:$J$135+0,0)) -> 896000 | C22: =SUMPRODUCT((((1*('Реестр оборудования'!$G$2:$G$135="Уровень Six Senses Place (велнес-плюс)")+2*('Реестр оборудования'!$G$2:$G$135="Уровень SHA/Chenot (медицина-лайт)")+3*('Реестр оборудования'!$G$2:$G$135="Уровень Lanserhof/CLP (полный медицинский)"))>0)*((1*('Реестр оборудования'!$G$2:$G$135="Уровень Six Senses Place (велнес-плюс)")+2*('Реестр оборудования'!$G$2:$G$135="Уровень SHA/Chenot (медицина-лайт)")+3*('Реестр оборудования'!$G$2:$G$135="Уровень Lanserhof/CLP (полный медицинский)"))<=2))*(('Реестр оборудования'!$B$2:$B$135="Движение и реабилитация")+('Реестр оборудования'!$B$2:$B$135="Тренажёрный зал и силовая зона"))*IFERROR('Реестр оборудования'!$N$2:$N$135+0,0)*IFERROR('Реестр оборудования'!$J$2:$J$135+0,0)) -> 672000 | D22: =SUMPRODUCT((((1*('Реестр оборудования'!$G$2:$G$135="Уровень Six Senses Place (велнес-плюс)")+2*('Реестр оборудования'!$G$2:$G$135="Уровень SHA/Chenot (медицина-лайт)")+3*('Реестр оборудования'!$G$2:$G$135="Уровень Lanserhof/CLP (полный медицинский)"))>0)*((1*('Реестр оборудования'!$G$2:$G$135="Уровень Six Senses Place (велнес-плюс)")+2*('Реестр оборудования'!$G$2:$G$135="Уровень SHA/Chenot (медицина-лайт)")+3*('Реестр оборудования'!$G$2:$G$135="Уровень Lanserhof/CLP (полный медицинский)"))<=1))*(('Реестр оборудования'!$B$2:$B$135="Движение и реабилитация")+('Реестр оборудования'!$B$2:$B$135="Тренажёрный зал и силовая зона"))*IFERROR('Реестр оборудования'!$N$2:$N$135+0,0)*IFERROR('Реестр оборудования'!$J$2:$J$135+0,0)) -> 672000
A23: Итого ИТ и ПО (единовременный CapEx) | B23: =SUMPRODUCT((((1*('Реестр оборудования'!$G$2:$G$135="Уровень Six Senses Place (велнес-плюс)")+2*('Реестр оборудования'!$G$2:$G$135="Уровень SHA/Chenot (медицина-лайт)")+3*('Реестр оборудования'!$G$2:$G$135="Уровень Lanserhof/CLP (полный медицинский)"))>0)*((1*('Реестр оборудования'!$G$2:$G$135="Уровень Six Senses Place (велнес-плюс)")+2*('Реестр оборудования'!$G$2:$G$135="Уровень SHA/Chenot (медицина-лайт)")+3*('Реестр оборудования'!$G$2:$G$135="Уровень Lanserhof/CLP (полный медицинский)"))<=3))*(('Реестр оборудования'!$B$2:$B$135="ИТ, МИС, ПО для пациентов"))*IFERROR('Реестр оборудования'!$N$2:$N$135+0,0)*IFERROR('Реестр оборудования'!$J$2:$J$135+0,0)) -> 90000 | C23: =SUMPRODUCT((((1*('Реестр оборудования'!$G$2:$G$135="Уровень Six Senses Place (велнес-плюс)")+2*('Реестр оборудования'!$G$2:$G$135="Уровень SHA/Chenot (медицина-лайт)")+3*('Реестр оборудования'!$G$2:$G$135="Уровень Lanserhof/CLP (полный медицинский)"))>0)*((1*('Реестр оборудования'!$G$2:$G$135="Уровень Six Senses Place (велнес-плюс)")+2*('Реестр оборудования'!$G$2:$G$135="Уровень SHA/Chenot (медицина-лайт)")+3*('Реестр оборудования'!$G$2:$G$135="Уровень Lanserhof/CLP (полный медицинский)"))<=2))*(('Реестр оборудования'!$B$2:$B$135="ИТ, МИС, ПО для пациентов"))*IFERROR('Реестр оборудования'!$N$2:$N$135+0,0)*IFERROR('Реестр оборудования'!$J$2:$J$135+0,0)) -> 90000 | D23: =SUMPRODUCT((((1*('Реестр оборудования'!$G$2:$G$135="Уровень Six Senses Place (велнес-плюс)")+2*('Реестр оборудования'!$G$2:$G$135="Уровень SHA/Chenot (медицина-лайт)")+3*('Реестр оборудования'!$G$2:$G$135="Уровень Lanserhof/CLP (полный медицинский)"))>0)*((1*('Реестр оборудования'!$G$2:$G$135="Уровень Six Senses Place (велнес-плюс)")+2*('Реестр оборудования'!$G$2:$G$135="Уровень SHA/Chenot (медицина-лайт)")+3*('Реестр оборудования'!$G$2:$G$135="Уровень Lanserhof/CLP (полный медицинский)"))<=1))*(('Реестр оборудования'!$B$2:$B$135="ИТ, МИС, ПО для пациентов"))*IFERROR('Реестр оборудования'!$N$2:$N$135+0,0)*IFERROR('Реестр оборудования'!$J$2:$J$135+0,0)) -> 80000
A24: Итого кухня и F&B | B24: =SUMPRODUCT((((1*('Реестр оборудования'!$G$2:$G$135="Уровень Six Senses Place (велнес-плюс)")+2*('Реестр оборудования'!$G$2:$G$135="Уровень SHA/Chenot (медицина-лайт)")+3*('Реестр оборудования'!$G$2:$G$135="Уровень Lanserhof/CLP (полный медицинский)"))>0)*((1*('Реестр оборудования'!$G$2:$G$135="Уровень Six Senses Place (велнес-плюс)")+2*('Реестр оборудования'!$G$2:$G$135="Уровень SHA/Chenot (медицина-лайт)")+3*('Реестр оборудования'!$G$2:$G$135="Уровень Lanserhof/CLP (полный медицинский)"))<=3))*(('Реестр оборудования'!$B$2:$B$135="Кухня и F&B"))*IFERROR('Реестр оборудования'!$N$2:$N$135+0,0)*IFERROR('Реестр оборудования'!$J$2:$J$135+0,0)) -> 448000 | C24: =SUMPRODUCT((((1*('Реестр оборудования'!$G$2:$G$135="Уровень Six Senses Place (велнес-плюс)")+2*('Реестр оборудования'!$G$2:$G$135="Уровень SHA/Chenot (медицина-лайт)")+3*('Реестр оборудования'!$G$2:$G$135="Уровень Lanserhof/CLP (полный медицинский)"))>0)*((1*('Реестр оборудования'!$G$2:$G$135="Уровень Six Senses Place (велнес-плюс)")+2*('Реестр оборудования'!$G$2:$G$135="Уровень SHA/Chenot (медицина-лайт)")+3*('Реестр оборудования'!$G$2:$G$135="Уровень Lanserhof/CLP (полный медицинский)"))<=2))*(('Реестр оборудования'!$B$2:$B$135="Кухня и F&B"))*IFERROR('Реестр оборудования'!$N$2:$N$135+0,0)*IFERROR('Реестр оборудования'!$J$2:$J$135+0,0)) -> 448000 | D24: =SUMPRODUCT((((1*('Реестр оборудования'!$G$2:$G$135="Уровень Six Senses Place (велнес-плюс)")+2*('Реестр оборудования'!$G$2:$G$135="Уровень SHA/Chenot (медицина-лайт)")+3*('Реестр оборудования'!$G$2:$G$135="Уровень Lanserhof/CLP (полный медицинский)"))>0)*((1*('Реестр оборудования'!$G$2:$G$135="Уровень Six Senses Place (велнес-плюс)")+2*('Реестр оборудования'!$G$2:$G$135="Уровень SHA/Chenot (медицина-лайт)")+3*('Реестр оборудования'!$G$2:$G$135="Уровень Lanserhof/CLP (полный медицинский)"))<=1))*(('Реестр оборудования'!$B$2:$B$135="Кухня и F&B"))*IFERROR('Реестр оборудования'!$N$2:$N$135+0,0)*IFERROR('Реестр оборудования'!$J$2:$J$135+0,0)) -> 448000
A25: Итого медицинская инфраструктура | B25: =SUMPRODUCT((((1*('Реестр оборудования'!$G$2:$G$135="Уровень Six Senses Place (велнес-плюс)")+2*('Реестр оборудования'!$G$2:$G$135="Уровень SHA/Chenot (медицина-лайт)")+3*('Реестр оборудования'!$G$2:$G$135="Уровень Lanserhof/CLP (полный медицинский)"))>0)*((1*('Реестр оборудования'!$G$2:$G$135="Уровень Six Senses Place (велнес-плюс)")+2*('Реестр оборудования'!$G$2:$G$135="Уровень SHA/Chenot (медицина-лайт)")+3*('Реестр оборудования'!$G$2:$G$135="Уровень Lanserhof/CLP (полный медицинский)"))<=3))*(('Реестр оборудования'!$B$2:$B$135="Медицинская инфраструктура"))*IFERROR('Реестр оборудования'!$N$2:$N$135+0,0)*IFERROR('Реестр оборудования'!$J$2:$J$135+0,0)) -> 175000 | C25: =SUMPRODUCT((((1*('Реестр оборудования'!$G$2:$G$135="Уровень Six Senses Place (велнес-плюс)")+2*('Реестр оборудования'!$G$2:$G$135="Уровень SHA/Chenot (медицина-лайт)")+3*('Реестр оборудования'!$G$2:$G$135="Уровень Lanserhof/CLP (полный медицинский)"))>0)*((1*('Реестр оборудования'!$G$2:$G$135="Уровень Six Senses Place (велнес-плюс)")+2*('Реестр оборудования'!$G$2:$G$135="Уровень SHA/Chenot (медицина-лайт)")+3*('Реестр оборудования'!$G$2:$G$135="Уровень Lanserhof/CLP (полный медицинский)"))<=2))*(('Реестр оборудования'!$B$2:$B$135="Медицинская инфраструктура"))*IFERROR('Реестр оборудования'!$N$2:$N$135+0,0)*IFERROR('Реестр оборудования'!$J$2:$J$135+0,0)) -> 50000 | D25: =SUMPRODUCT((((1*('Реестр оборудования'!$G$2:$G$135="Уровень Six Senses Place (велнес-плюс)")+2*('Реестр оборудования'!$G$2:$G$135="Уровень SHA/Chenot (медицина-лайт)")+3*('Реестр оборудования'!$G$2:$G$135="Уровень Lanserhof/CLP (полный медицинский)"))>0)*((1*('Реестр оборудования'!$G$2:$G$135="Уровень Six Senses Place (велнес-плюс)")+2*('Реестр оборудования'!$G$2:$G$135="Уровень SHA/Chenot (медицина-лайт)")+3*('Реестр оборудования'!$G$2:$G$135="Уровень Lanserhof/CLP (полный медицинский)"))<=1))*(('Реестр оборудования'!$B$2:$B$135="Медицинская инфраструктура"))*IFERROR('Реестр оборудования'!$N$2:$N$135+0,0)*IFERROR('Реестр оборудования'!$J$2:$J$135+0,0)) -> 0
A26: ИТОГО CapEx | B26: =SUM(B20:B25) -> 2407000 | C26: =SUM(C20:C25) -> 2058000 | D26: =SUM(D20:D25) -> 1998000
A27: CapEx на номер | B27: =B26/$B$3 -> 26744.444 | C27: =C26/$B$3 -> 22866.667 | D27: =D26/$B$3 -> 22200
A29: РЕГИОН , Азия ($)
A30: Группа | B30: Уровень Lanserhof/CLP (полный медицинский) | C30: Уровень SHA/Chenot (медицина-лайт) | D30: Уровень Six Senses Place (велнес-плюс)
A31: Итого медицинский CapEx | B31: =SUMPRODUCT((((1*('Реестр оборудования'!$G$2:$G$135="Уровень Six Senses Place (велнес-плюс)")+2*('Реестр оборудования'!$G$2:$G$135="Уровень SHA/Chenot (медицина-лайт)")+3*('Реестр оборудования'!$G$2:$G$135="Уровень Lanserhof/CLP (полный медицинский)"))>0)*((1*('Реестр оборудования'!$G$2:$G$135="Уровень Six Senses Place (велнес-плюс)")+2*('Реестр оборудования'!$G$2:$G$135="Уровень SHA/Chenot (медицина-лайт)")+3*('Реестр оборудования'!$G$2:$G$135="Уровень Lanserhof/CLP (полный медицинский)"))<=3))*(('Реестр оборудования'!$B$2:$B$135="Лучевая диагностика")+('Реестр оборудования'!$B$2:$B$135="Лаборатория и биомаркеры")+('Реестр оборудования'!$B$2:$B$135="Кардиология и пульмонология")+('Реестр оборудования'!$B$2:$B$135="Сон и неврология")+('Реестр оборудования'!$B$2:$B$135="Инфузионная терапия")+('Реестр оборудования'!$B$2:$B$135="Эстетика и регенеративные процедуры")+('Реестр оборудования'!$B$2:$B$135="Нутрициология и ЖКТ-диагностика")+('Реестр оборудования'!$B$2:$B$135="Состав тела и функциональная диагностика")+('Реестр оборудования'!$B$2:$B$135="Телемедицина и цифровое здоровье"))*IFERROR('Реестр оборудования'!$N$2:$N$135+0,0)*IFERROR('Реестр оборудования'!$K$2:$K$135+0,0)) -> 1690000 | C31: =SUMPRODUCT((((1*('Реестр оборудования'!$G$2:$G$135="Уровень Six Senses Place (велнес-плюс)")+2*('Реестр оборудования'!$G$2:$G$135="Уровень SHA/Chenot (медицина-лайт)")+3*('Реестр оборудования'!$G$2:$G$135="Уровень Lanserhof/CLP (полный медицинский)"))>0)*((1*('Реестр оборудования'!$G$2:$G$135="Уровень Six Senses Place (велнес-плюс)")+2*('Реестр оборудования'!$G$2:$G$135="Уровень SHA/Chenot (медицина-лайт)")+3*('Реестр оборудования'!$G$2:$G$135="Уровень Lanserhof/CLP (полный медицинский)"))<=2))*(('Реестр оборудования'!$B$2:$B$135="Лучевая диагностика")+('Реестр оборудования'!$B$2:$B$135="Лаборатория и биомаркеры")+('Реестр оборудования'!$B$2:$B$135="Кардиология и пульмонология")+('Реестр оборудования'!$B$2:$B$135="Сон и неврология")+('Реестр оборудования'!$B$2:$B$135="Инфузионная терапия")+('Реестр оборудования'!$B$2:$B$135="Эстетика и регенеративные процедуры")+('Реестр оборудования'!$B$2:$B$135="Нутрициология и ЖКТ-диагностика")+('Реестр оборудования'!$B$2:$B$135="Состав тела и функциональная диагностика")+('Реестр оборудования'!$B$2:$B$135="Телемедицина и цифровое здоровье"))*IFERROR('Реестр оборудования'!$N$2:$N$135+0,0)*IFERROR('Реестр оборудования'!$K$2:$K$135+0,0)) -> 1144000 | D31: =SUMPRODUCT((((1*('Реестр оборудования'!$G$2:$G$135="Уровень Six Senses Place (велнес-плюс)")+2*('Реестр оборудования'!$G$2:$G$135="Уровень SHA/Chenot (медицина-лайт)")+3*('Реестр оборудования'!$G$2:$G$135="Уровень Lanserhof/CLP (полный медицинский)"))>0)*((1*('Реестр оборудования'!$G$2:$G$135="Уровень Six Senses Place (велнес-плюс)")+2*('Реестр оборудования'!$G$2:$G$135="Уровень SHA/Chenot (медицина-лайт)")+3*('Реестр оборудования'!$G$2:$G$135="Уровень Lanserhof/CLP (полный медицинский)"))<=1))*(('Реестр оборудования'!$B$2:$B$135="Лучевая диагностика")+('Реестр оборудования'!$B$2:$B$135="Лаборатория и биомаркеры")+('Реестр оборудования'!$B$2:$B$135="Кардиология и пульмонология")+('Реестр оборудования'!$B$2:$B$135="Сон и неврология")+('Реестр оборудования'!$B$2:$B$135="Инфузионная терапия")+('Реестр оборудования'!$B$2:$B$135="Эстетика и регенеративные процедуры")+('Реестр оборудования'!$B$2:$B$135="Нутрициология и ЖКТ-диагностика")+('Реестр оборудования'!$B$2:$B$135="Состав тела и функциональная диагностика")+('Реестр оборудования'!$B$2:$B$135="Телемедицина и цифровое здоровье"))*IFERROR('Реестр оборудования'!$N$2:$N$135+0,0)*IFERROR('Реестр оборудования'!$K$2:$K$135+0,0)) -> 156000
A32: Итого SPA и восстановление | B32: =SUMPRODUCT((((1*('Реестр оборудования'!$G$2:$G$135="Уровень Six Senses Place (велнес-плюс)")+2*('Реестр оборудования'!$G$2:$G$135="Уровень SHA/Chenot (медицина-лайт)")+3*('Реестр оборудования'!$G$2:$G$135="Уровень Lanserhof/CLP (полный медицинский)"))>0)*((1*('Реестр оборудования'!$G$2:$G$135="Уровень Six Senses Place (велнес-плюс)")+2*('Реестр оборудования'!$G$2:$G$135="Уровень SHA/Chenot (медицина-лайт)")+3*('Реестр оборудования'!$G$2:$G$135="Уровень Lanserhof/CLP (полный медицинский)"))<=3))*(('Реестр оборудования'!$B$2:$B$135="Гидротерапия и SPA")+('Реестр оборудования'!$B$2:$B$135="Криотерапия и термальные зоны"))*IFERROR('Реестр оборудования'!$N$2:$N$135+0,0)*IFERROR('Реестр оборудования'!$K$2:$K$135+0,0)) -> 570000 | C32: =SUMPRODUCT((((1*('Реестр оборудования'!$G$2:$G$135="Уровень Six Senses Place (велнес-плюс)")+2*('Реестр оборудования'!$G$2:$G$135="Уровень SHA/Chenot (медицина-лайт)")+3*('Реестр оборудования'!$G$2:$G$135="Уровень Lanserhof/CLP (полный медицинский)"))>0)*((1*('Реестр оборудования'!$G$2:$G$135="Уровень Six Senses Place (велнес-плюс)")+2*('Реестр оборудования'!$G$2:$G$135="Уровень SHA/Chenot (медицина-лайт)")+3*('Реестр оборудования'!$G$2:$G$135="Уровень Lanserhof/CLP (полный медицинский)"))<=2))*(('Реестр оборудования'!$B$2:$B$135="Гидротерапия и SPA")+('Реестр оборудования'!$B$2:$B$135="Криотерапия и термальные зоны"))*IFERROR('Реестр оборудования'!$N$2:$N$135+0,0)*IFERROR('Реестр оборудования'!$K$2:$K$135+0,0)) -> 570000 | D32: =SUMPRODUCT((((1*('Реестр оборудования'!$G$2:$G$135="Уровень Six Senses Place (велнес-плюс)")+2*('Реестр оборудования'!$G$2:$G$135="Уровень SHA/Chenot (медицина-лайт)")+3*('Реестр оборудования'!$G$2:$G$135="Уровень Lanserhof/CLP (полный медицинский)"))>0)*((1*('Реестр оборудования'!$G$2:$G$135="Уровень Six Senses Place (велнес-плюс)")+2*('Реестр оборудования'!$G$2:$G$135="Уровень SHA/Chenot (медицина-лайт)")+3*('Реестр оборудования'!$G$2:$G$135="Уровень Lanserhof/CLP (полный медицинский)"))<=1))*(('Реестр оборудования'!$B$2:$B$135="Гидротерапия и SPA")+('Реестр оборудования'!$B$2:$B$135="Криотерапия и термальные зоны"))*IFERROR('Реестр оборудования'!$N$2:$N$135+0,0)*IFERROR('Реестр оборудования'!$K$2:$K$135+0,0)) -> 570000
A33: Итого фитнес и движение | B33: =SUMPRODUCT((((1*('Реестр оборудования'!$G$2:$G$135="Уровень Six Senses Place (велнес-плюс)")+2*('Реестр оборудования'!$G$2:$G$135="Уровень SHA/Chenot (медицина-лайт)")+3*('Реестр оборудования'!$G$2:$G$135="Уровень Lanserhof/CLP (полный медицинский)"))>0)*((1*('Реестр оборудования'!$G$2:$G$135="Уровень Six Senses Place (велнес-плюс)")+2*('Реестр оборудования'!$G$2:$G$135="Уровень SHA/Chenot (медицина-лайт)")+3*('Реестр оборудования'!$G$2:$G$135="Уровень Lanserhof/CLP (полный медицинский)"))<=3))*(('Реестр оборудования'!$B$2:$B$135="Движение и реабилитация")+('Реестр оборудования'!$B$2:$B$135="Тренажёрный зал и силовая зона"))*IFERROR('Реестр оборудования'!$N$2:$N$135+0,0)*IFERROR('Реестр оборудования'!$K$2:$K$135+0,0)) -> 1120000 | C33: =SUMPRODUCT((((1*('Реестр оборудования'!$G$2:$G$135="Уровень Six Senses Place (велнес-плюс)")+2*('Реестр оборудования'!$G$2:$G$135="Уровень SHA/Chenot (медицина-лайт)")+3*('Реестр оборудования'!$G$2:$G$135="Уровень Lanserhof/CLP (полный медицинский)"))>0)*((1*('Реестр оборудования'!$G$2:$G$135="Уровень Six Senses Place (велнес-плюс)")+2*('Реестр оборудования'!$G$2:$G$135="Уровень SHA/Chenot (медицина-лайт)")+3*('Реестр оборудования'!$G$2:$G$135="Уровень Lanserhof/CLP (полный медицинский)"))<=2))*(('Реестр оборудования'!$B$2:$B$135="Движение и реабилитация")+('Реестр оборудования'!$B$2:$B$135="Тренажёрный зал и силовая зона"))*IFERROR('Реестр оборудования'!$N$2:$N$135+0,0)*IFERROR('Реестр оборудования'!$K$2:$K$135+0,0)) -> 840000 | D33: =SUMPRODUCT((((1*('Реестр оборудования'!$G$2:$G$135="Уровень Six Senses Place (велнес-плюс)")+2*('Реестр оборудования'!$G$2:$G$135="Уровень SHA/Chenot (медицина-лайт)")+3*('Реестр оборудования'!$G$2:$G$135="Уровень Lanserhof/CLP (полный медицинский)"))>0)*((1*('Реестр оборудования'!$G$2:$G$135="Уровень Six Senses Place (велнес-плюс)")+2*('Реестр оборудования'!$G$2:$G$135="Уровень SHA/Chenot (медицина-лайт)")+3*('Реестр оборудования'!$G$2:$G$135="Уровень Lanserhof/CLP (полный медицинский)"))<=1))*(('Реестр оборудования'!$B$2:$B$135="Движение и реабилитация")+('Реестр оборудования'!$B$2:$B$135="Тренажёрный зал и силовая зона"))*IFERROR('Реестр оборудования'!$N$2:$N$135+0,0)*IFERROR('Реестр оборудования'!$K$2:$K$135+0,0)) -> 840000
A34: Итого ИТ и ПО (единовременный CapEx) | B34: =SUMPRODUCT((((1*('Реестр оборудования'!$G$2:$G$135="Уровень Six Senses Place (велнес-плюс)")+2*('Реестр оборудования'!$G$2:$G$135="Уровень SHA/Chenot (медицина-лайт)")+3*('Реестр оборудования'!$G$2:$G$135="Уровень Lanserhof/CLP (полный медицинский)"))>0)*((1*('Реестр оборудования'!$G$2:$G$135="Уровень Six Senses Place (велнес-плюс)")+2*('Реестр оборудования'!$G$2:$G$135="Уровень SHA/Chenot (медицина-лайт)")+3*('Реестр оборудования'!$G$2:$G$135="Уровень Lanserhof/CLP (полный медицинский)"))<=3))*(('Реестр оборудования'!$B$2:$B$135="ИТ, МИС, ПО для пациентов"))*IFERROR('Реестр оборудования'!$N$2:$N$135+0,0)*IFERROR('Реестр оборудования'!$K$2:$K$135+0,0)) -> 423000 | C34: =SUMPRODUCT((((1*('Реестр оборудования'!$G$2:$G$135="Уровень Six Senses Place (велнес-плюс)")+2*('Реестр оборудования'!$G$2:$G$135="Уровень SHA/Chenot (медицина-лайт)")+3*('Реестр оборудования'!$G$2:$G$135="Уровень Lanserhof/CLP (полный медицинский)"))>0)*((1*('Реестр оборудования'!$G$2:$G$135="Уровень Six Senses Place (велнес-плюс)")+2*('Реестр оборудования'!$G$2:$G$135="Уровень SHA/Chenot (медицина-лайт)")+3*('Реестр оборудования'!$G$2:$G$135="Уровень Lanserhof/CLP (полный медицинский)"))<=2))*(('Реестр оборудования'!$B$2:$B$135="ИТ, МИС, ПО для пациентов"))*IFERROR('Реестр оборудования'!$N$2:$N$135+0,0)*IFERROR('Реестр оборудования'!$K$2:$K$135+0,0)) -> 423000 | D34: =SUMPRODUCT((((1*('Реестр оборудования'!$G$2:$G$135="Уровень Six Senses Place (велнес-плюс)")+2*('Реестр оборудования'!$G$2:$G$135="Уровень SHA/Chenot (медицина-лайт)")+3*('Реестр оборудования'!$G$2:$G$135="Уровень Lanserhof/CLP (полный медицинский)"))>0)*((1*('Реестр оборудования'!$G$2:$G$135="Уровень Six Senses Place (велнес-плюс)")+2*('Реестр оборудования'!$G$2:$G$135="Уровень SHA/Chenot (медицина-лайт)")+3*('Реестр оборудования'!$G$2:$G$135="Уровень Lanserhof/CLP (полный медицинский)"))<=1))*(('Реестр оборудования'!$B$2:$B$135="ИТ, МИС, ПО для пациентов"))*IFERROR('Реестр оборудования'!$N$2:$N$135+0,0)*IFERROR('Реестр оборудования'!$K$2:$K$135+0,0)) -> 376000
A35: Итого кухня и F&B | B35: =SUMPRODUCT((((1*('Реестр оборудования'!$G$2:$G$135="Уровень Six Senses Place (велнес-плюс)")+2*('Реестр оборудования'!$G$2:$G$135="Уровень SHA/Chenot (медицина-лайт)")+3*('Реестр оборудования'!$G$2:$G$135="Уровень Lanserhof/CLP (полный медицинский)"))>0)*((1*('Реестр оборудования'!$G$2:$G$135="Уровень Six Senses Place (велнес-плюс)")+2*('Реестр оборудования'!$G$2:$G$135="Уровень SHA/Chenot (медицина-лайт)")+3*('Реестр оборудования'!$G$2:$G$135="Уровень Lanserhof/CLP (полный медицинский)"))<=3))*(('Реестр оборудования'!$B$2:$B$135="Кухня и F&B"))*IFERROR('Реестр оборудования'!$N$2:$N$135+0,0)*IFERROR('Реестр оборудования'!$K$2:$K$135+0,0)) -> 588000 | C35: =SUMPRODUCT((((1*('Реестр оборудования'!$G$2:$G$135="Уровень Six Senses Place (велнес-плюс)")+2*('Реестр оборудования'!$G$2:$G$135="Уровень SHA/Chenot (медицина-лайт)")+3*('Реестр оборудования'!$G$2:$G$135="Уровень Lanserhof/CLP (полный медицинский)"))>0)*((1*('Реестр оборудования'!$G$2:$G$135="Уровень Six Senses Place (велнес-плюс)")+2*('Реестр оборудования'!$G$2:$G$135="Уровень SHA/Chenot (медицина-лайт)")+3*('Реестр оборудования'!$G$2:$G$135="Уровень Lanserhof/CLP (полный медицинский)"))<=2))*(('Реестр оборудования'!$B$2:$B$135="Кухня и F&B"))*IFERROR('Реестр оборудования'!$N$2:$N$135+0,0)*IFERROR('Реестр оборудования'!$K$2:$K$135+0,0)) -> 588000 | D35: =SUMPRODUCT((((1*('Реестр оборудования'!$G$2:$G$135="Уровень Six Senses Place (велнес-плюс)")+2*('Реестр оборудования'!$G$2:$G$135="Уровень SHA/Chenot (медицина-лайт)")+3*('Реестр оборудования'!$G$2:$G$135="Уровень Lanserhof/CLP (полный медицинский)"))>0)*((1*('Реестр оборудования'!$G$2:$G$135="Уровень Six Senses Place (велнес-плюс)")+2*('Реестр оборудования'!$G$2:$G$135="Уровень SHA/Chenot (медицина-лайт)")+3*('Реестр оборудования'!$G$2:$G$135="Уровень Lanserhof/CLP (полный медицинский)"))<=1))*(('Реестр оборудования'!$B$2:$B$135="Кухня и F&B"))*IFERROR('Реестр оборудования'!$N$2:$N$135+0,0)*IFERROR('Реестр оборудования'!$K$2:$K$135+0,0)) -> 588000
A36: Итого медицинская инфраструктура | B36: =SUMPRODUCT((((1*('Реестр оборудования'!$G$2:$G$135="Уровень Six Senses Place (велнес-плюс)")+2*('Реестр оборудования'!$G$2:$G$135="Уровень SHA/Chenot (медицина-лайт)")+3*('Реестр оборудования'!$G$2:$G$135="Уровень Lanserhof/CLP (полный медицинский)"))>0)*((1*('Реестр оборудования'!$G$2:$G$135="Уровень Six Senses Place (велнес-плюс)")+2*('Реестр оборудования'!$G$2:$G$135="Уровень SHA/Chenot (медицина-лайт)")+3*('Реестр оборудования'!$G$2:$G$135="Уровень Lanserhof/CLP (полный медицинский)"))<=3))*(('Реестр оборудования'!$B$2:$B$135="Медицинская инфраструктура"))*IFERROR('Реестр оборудования'!$N$2:$N$135+0,0)*IFERROR('Реестр оборудования'!$K$2:$K$135+0,0)) -> 805000 | C36: =SUMPRODUCT((((1*('Реестр оборудования'!$G$2:$G$135="Уровень Six Senses Place (велнес-плюс)")+2*('Реестр оборудования'!$G$2:$G$135="Уровень SHA/Chenot (медицина-лайт)")+3*('Реестр оборудования'!$G$2:$G$135="Уровень Lanserhof/CLP (полный медицинский)"))>0)*((1*('Реестр оборудования'!$G$2:$G$135="Уровень Six Senses Place (велнес-плюс)")+2*('Реестр оборудования'!$G$2:$G$135="Уровень SHA/Chenot (медицина-лайт)")+3*('Реестр оборудования'!$G$2:$G$135="Уровень Lanserhof/CLP (полный медицинский)"))<=2))*(('Реестр оборудования'!$B$2:$B$135="Медицинская инфраструктура"))*IFERROR('Реестр оборудования'!$N$2:$N$135+0,0)*IFERROR('Реестр оборудования'!$K$2:$K$135+0,0)) -> 230000 | D36: =SUMPRODUCT((((1*('Реестр оборудования'!$G$2:$G$135="Уровень Six Senses Place (велнес-плюс)")+2*('Реестр оборудования'!$G$2:$G$135="Уровень SHA/Chenot (медицина-лайт)")+3*('Реестр оборудования'!$G$2:$G$135="Уровень Lanserhof/CLP (полный медицинский)"))>0)*((1*('Реестр оборудования'!$G$2:$G$135="Уровень Six Senses Place (велнес-плюс)")+2*('Реестр оборудования'!$G$2:$G$135="Уровень SHA/Chenot (медицина-лайт)")+3*('Реестр оборудования'!$G$2:$G$135="Уровень Lanserhof/CLP (полный медицинский)"))<=1))*(('Реестр оборудования'!$B$2:$B$135="Медицинская инфраструктура"))*IFERROR('Реестр оборудования'!$N$2:$N$135+0,0)*IFERROR('Реестр оборудования'!$K$2:$K$135+0,0)) -> 0
A37: ИТОГО CapEx | B37: =SUM(B31:B36) -> 5196000 | C37: =SUM(C31:C36) -> 3795000 | D37: =SUM(D31:D36) -> 2530000
A38: CapEx на номер | B38: =B37/$B$3 -> 57733.333 | C38: =C37/$B$3 -> 42166.667 | D38: =D37/$B$3 -> 28111.111
A40: РЕГИОН , Россия (₽)
A41: Группа | B41: Уровень Lanserhof/CLP (полный медицинский) | C41: Уровень SHA/Chenot (медицина-лайт) | D41: Уровень Six Senses Place (велнес-плюс)
A42: Итого медицинский CapEx | B42: =SUMPRODUCT((((1*('Реестр оборудования'!$G$2:$G$135="Уровень Six Senses Place (велнес-плюс)")+2*('Реестр оборудования'!$G$2:$G$135="Уровень SHA/Chenot (медицина-лайт)")+3*('Реестр оборудования'!$G$2:$G$135="Уровень Lanserhof/CLP (полный медицинский)"))>0)*((1*('Реестр оборудования'!$G$2:$G$135="Уровень Six Senses Place (велнес-плюс)")+2*('Реестр оборудования'!$G$2:$G$135="Уровень SHA/Chenot (медицина-лайт)")+3*('Реестр оборудования'!$G$2:$G$135="Уровень Lanserhof/CLP (полный медицинский)"))<=3))*(('Реестр оборудования'!$B$2:$B$135="Лучевая диагностика")+('Реестр оборудования'!$B$2:$B$135="Лаборатория и биомаркеры")+('Реестр оборудования'!$B$2:$B$135="Кардиология и пульмонология")+('Реестр оборудования'!$B$2:$B$135="Сон и неврология")+('Реестр оборудования'!$B$2:$B$135="Инфузионная терапия")+('Реестр оборудования'!$B$2:$B$135="Эстетика и регенеративные процедуры")+('Реестр оборудования'!$B$2:$B$135="Нутрициология и ЖКТ-диагностика")+('Реестр оборудования'!$B$2:$B$135="Состав тела и функциональная диагностика")+('Реестр оборудования'!$B$2:$B$135="Телемедицина и цифровое здоровье"))*IFERROR('Реестр оборудования'!$N$2:$N$135+0,0)*IFERROR('Реестр оборудования'!$M$2:$M$135+0,0)) -> 845000000 | C42: =SUMPRODUCT((((1*('Реестр оборудования'!$G$2:$G$135="Уровень Six Senses Place (велнес-плюс)")+2*('Реестр оборудования'!$G$2:$G$135="Уровень SHA/Chenot (медицина-лайт)")+3*('Реестр оборудования'!$G$2:$G$135="Уровень Lanserhof/CLP (полный медицинский)"))>0)*((1*('Реестр оборудования'!$G$2:$G$135="Уровень Six Senses Place (велнес-плюс)")+2*('Реестр оборудования'!$G$2:$G$135="Уровень SHA/Chenot (медицина-лайт)")+3*('Реестр оборудования'!$G$2:$G$135="Уровень Lanserhof/CLP (полный медицинский)"))<=2))*(('Реестр оборудования'!$B$2:$B$135="Лучевая диагностика")+('Реестр оборудования'!$B$2:$B$135="Лаборатория и биомаркеры")+('Реестр оборудования'!$B$2:$B$135="Кардиология и пульмонология")+('Реестр оборудования'!$B$2:$B$135="Сон и неврология")+('Реестр оборудования'!$B$2:$B$135="Инфузионная терапия")+('Реестр оборудования'!$B$2:$B$135="Эстетика и регенеративные процедуры")+('Реестр оборудования'!$B$2:$B$135="Нутрициология и ЖКТ-диагностика")+('Реестр оборудования'!$B$2:$B$135="Состав тела и функциональная диагностика")+('Реестр оборудования'!$B$2:$B$135="Телемедицина и цифровое здоровье"))*IFERROR('Реестр оборудования'!$N$2:$N$135+0,0)*IFERROR('Реестр оборудования'!$M$2:$M$135+0,0)) -> 572000000 | D42: =SUMPRODUCT((((1*('Реестр оборудования'!$G$2:$G$135="Уровень Six Senses Place (велнес-плюс)")+2*('Реестр оборудования'!$G$2:$G$135="Уровень SHA/Chenot (медицина-лайт)")+3*('Реестр оборудования'!$G$2:$G$135="Уровень Lanserhof/CLP (полный медицинский)"))>0)*((1*('Реестр оборудования'!$G$2:$G$135="Уровень Six Senses Place (велнес-плюс)")+2*('Реестр оборудования'!$G$2:$G$135="Уровень SHA/Chenot (медицина-лайт)")+3*('Реестр оборудования'!$G$2:$G$135="Уровень Lanserhof/CLP (полный медицинский)"))<=1))*(('Реестр оборудования'!$B$2:$B$135="Лучевая диагностика")+('Реестр оборудования'!$B$2:$B$135="Лаборатория и биомаркеры")+('Реестр оборудования'!$B$2:$B$135="Кардиология и пульмонология")+('Реестр оборудования'!$B$2:$B$135="Сон и неврология")+('Реестр оборудования'!$B$2:$B$135="Инфузионная терапия")+('Реестр оборудования'!$B$2:$B$135="Эстетика и регенеративные процедуры")+('Реестр оборудования'!$B$2:$B$135="Нутрициология и ЖКТ-диагностика")+('Реестр оборудования'!$B$2:$B$135="Состав тела и функциональная диагностика")+('Реестр оборудования'!$B$2:$B$135="Телемедицина и цифровое здоровье"))*IFERROR('Реестр оборудования'!$N$2:$N$135+0,0)*IFERROR('Реестр оборудования'!$M$2:$M$135+0,0)) -> 78000000
A43: Итого SPA и восстановление | B43: =SUMPRODUCT((((1*('Реестр оборудования'!$G$2:$G$135="Уровень Six Senses Place (велнес-плюс)")+2*('Реестр оборудования'!$G$2:$G$135="Уровень SHA/Chenot (медицина-лайт)")+3*('Реестр оборудования'!$G$2:$G$135="Уровень Lanserhof/CLP (полный медицинский)"))>0)*((1*('Реестр оборудования'!$G$2:$G$135="Уровень Six Senses Place (велнес-плюс)")+2*('Реестр оборудования'!$G$2:$G$135="Уровень SHA/Chenot (медицина-лайт)")+3*('Реестр оборудования'!$G$2:$G$135="Уровень Lanserhof/CLP (полный медицинский)"))<=3))*(('Реестр оборудования'!$B$2:$B$135="Гидротерапия и SPA")+('Реестр оборудования'!$B$2:$B$135="Криотерапия и термальные зоны"))*IFERROR('Реестр оборудования'!$N$2:$N$135+0,0)*IFERROR('Реестр оборудования'!$M$2:$M$135+0,0)) -> 209000000 | C43: =SUMPRODUCT((((1*('Реестр оборудования'!$G$2:$G$135="Уровень Six Senses Place (велнес-плюс)")+2*('Реестр оборудования'!$G$2:$G$135="Уровень SHA/Chenot (медицина-лайт)")+3*('Реестр оборудования'!$G$2:$G$135="Уровень Lanserhof/CLP (полный медицинский)"))>0)*((1*('Реестр оборудования'!$G$2:$G$135="Уровень Six Senses Place (велнес-плюс)")+2*('Реестр оборудования'!$G$2:$G$135="Уровень SHA/Chenot (медицина-лайт)")+3*('Реестр оборудования'!$G$2:$G$135="Уровень Lanserhof/CLP (полный медицинский)"))<=2))*(('Реестр оборудования'!$B$2:$B$135="Гидротерапия и SPA")+('Реестр оборудования'!$B$2:$B$135="Криотерапия и термальные зоны"))*IFERROR('Реестр оборудования'!$N$2:$N$135+0,0)*IFERROR('Реестр оборудования'!$M$2:$M$135+0,0)) -> 209000000 | D43: =SUMPRODUCT((((1*('Реестр оборудования'!$G$2:$G$135="Уровень Six Senses Place (велнес-плюс)")+2*('Реестр оборудования'!$G$2:$G$135="Уровень SHA/Chenot (медицина-лайт)")+3*('Реестр оборудования'!$G$2:$G$135="Уровень Lanserhof/CLP (полный медицинский)"))>0)*((1*('Реестр оборудования'!$G$2:$G$135="Уровень Six Senses Place (велнес-плюс)")+2*('Реестр оборудования'!$G$2:$G$135="Уровень SHA/Chenot (медицина-лайт)")+3*('Реестр оборудования'!$G$2:$G$135="Уровень Lanserhof/CLP (полный медицинский)"))<=1))*(('Реестр оборудования'!$B$2:$B$135="Гидротерапия и SPA")+('Реестр оборудования'!$B$2:$B$135="Криотерапия и термальные зоны"))*IFERROR('Реестр оборудования'!$N$2:$N$135+0,0)*IFERROR('Реестр оборудования'!$M$2:$M$135+0,0)) -> 209000000
A44: Итого фитнес и движение | B44: =SUMPRODUCT((((1*('Реестр оборудования'!$G$2:$G$135="Уровень Six Senses Place (велнес-плюс)")+2*('Реестр оборудования'!$G$2:$G$135="Уровень SHA/Chenot (медицина-лайт)")+3*('Реестр оборудования'!$G$2:$G$135="Уровень Lanserhof/CLP (полный медицинский)"))>0)*((1*('Реестр оборудования'!$G$2:$G$135="Уровень Six Senses Place (велнес-плюс)")+2*('Реестр оборудования'!$G$2:$G$135="Уровень SHA/Chenot (медицина-лайт)")+3*('Реестр оборудования'!$G$2:$G$135="Уровень Lanserhof/CLP (полный медицинский)"))<=3))*(('Реестр оборудования'!$B$2:$B$135="Движение и реабилитация")+('Реестр оборудования'!$B$2:$B$135="Тренажёрный зал и силовая зона"))*IFERROR('Реестр оборудования'!$N$2:$N$135+0,0)*IFERROR('Реестр оборудования'!$M$2:$M$135+0,0)) -> 2080000000 | C44: =SUMPRODUCT((((1*('Реестр оборудования'!$G$2:$G$135="Уровень Six Senses Place (велнес-плюс)")+2*('Реестр оборудования'!$G$2:$G$135="Уровень SHA/Chenot (медицина-лайт)")+3*('Реестр оборудования'!$G$2:$G$135="Уровень Lanserhof/CLP (полный медицинский)"))>0)*((1*('Реестр оборудования'!$G$2:$G$135="Уровень Six Senses Place (велнес-плюс)")+2*('Реестр оборудования'!$G$2:$G$135="Уровень SHA/Chenot (медицина-лайт)")+3*('Реестр оборудования'!$G$2:$G$135="Уровень Lanserhof/CLP (полный медицинский)"))<=2))*(('Реестр оборудования'!$B$2:$B$135="Движение и реабилитация")+('Реестр оборудования'!$B$2:$B$135="Тренажёрный зал и силовая зона"))*IFERROR('Реестр оборудования'!$N$2:$N$135+0,0)*IFERROR('Реестр оборудования'!$M$2:$M$135+0,0)) -> 1560000000 | D44: =SUMPRODUCT((((1*('Реестр оборудования'!$G$2:$G$135="Уровень Six Senses Place (велнес-плюс)")+2*('Реестр оборудования'!$G$2:$G$135="Уровень SHA/Chenot (медицина-лайт)")+3*('Реестр оборудования'!$G$2:$G$135="Уровень Lanserhof/CLP (полный медицинский)"))>0)*((1*('Реестр оборудования'!$G$2:$G$135="Уровень Six Senses Place (велнес-плюс)")+2*('Реестр оборудования'!$G$2:$G$135="Уровень SHA/Chenot (медицина-лайт)")+3*('Реестр оборудования'!$G$2:$G$135="Уровень Lanserhof/CLP (полный медицинский)"))<=1))*(('Реестр оборудования'!$B$2:$B$135="Движение и реабилитация")+('Реестр оборудования'!$B$2:$B$135="Тренажёрный зал и силовая зона"))*IFERROR('Реестр оборудования'!$N$2:$N$135+0,0)*IFERROR('Реестр оборудования'!$M$2:$M$135+0,0)) -> 1560000000
A45: Итого ИТ и ПО (единовременный CapEx) | B45: =SUMPRODUCT((((1*('Реестр оборудования'!$G$2:$G$135="Уровень Six Senses Place (велнес-плюс)")+2*('Реестр оборудования'!$G$2:$G$135="Уровень SHA/Chenot (медицина-лайт)")+3*('Реестр оборудования'!$G$2:$G$135="Уровень Lanserhof/CLP (полный медицинский)"))>0)*((1*('Реестр оборудования'!$G$2:$G$135="Уровень Six Senses Place (велнес-плюс)")+2*('Реестр оборудования'!$G$2:$G$135="Уровень SHA/Chenot (медицина-лайт)")+3*('Реестр оборудования'!$G$2:$G$135="Уровень Lanserhof/CLP (полный медицинский)"))<=3))*(('Реестр оборудования'!$B$2:$B$135="ИТ, МИС, ПО для пациентов"))*IFERROR('Реестр оборудования'!$N$2:$N$135+0,0)*IFERROR('Реестр оборудования'!$M$2:$M$135+0,0)) -> 2610000000 | C45: =SUMPRODUCT((((1*('Реестр оборудования'!$G$2:$G$135="Уровень Six Senses Place (велнес-плюс)")+2*('Реестр оборудования'!$G$2:$G$135="Уровень SHA/Chenot (медицина-лайт)")+3*('Реестр оборудования'!$G$2:$G$135="Уровень Lanserhof/CLP (полный медицинский)"))>0)*((1*('Реестр оборудования'!$G$2:$G$135="Уровень Six Senses Place (велнес-плюс)")+2*('Реестр оборудования'!$G$2:$G$135="Уровень SHA/Chenot (медицина-лайт)")+3*('Реестр оборудования'!$G$2:$G$135="Уровень Lanserhof/CLP (полный медицинский)"))<=2))*(('Реестр оборудования'!$B$2:$B$135="ИТ, МИС, ПО для пациентов"))*IFERROR('Реестр оборудования'!$N$2:$N$135+0,0)*IFERROR('Реестр оборудования'!$M$2:$M$135+0,0)) -> 2610000000 | D45: =SUMPRODUCT((((1*('Реестр оборудования'!$G$2:$G$135="Уровень Six Senses Place (велнес-плюс)")+2*('Реестр оборудования'!$G$2:$G$135="Уровень SHA/Chenot (медицина-лайт)")+3*('Реестр оборудования'!$G$2:$G$135="Уровень Lanserhof/CLP (полный медицинский)"))>0)*((1*('Реестр оборудования'!$G$2:$G$135="Уровень Six Senses Place (велнес-плюс)")+2*('Реестр оборудования'!$G$2:$G$135="Уровень SHA/Chenot (медицина-лайт)")+3*('Реестр оборудования'!$G$2:$G$135="Уровень Lanserhof/CLP (полный медицинский)"))<=1))*(('Реестр оборудования'!$B$2:$B$135="ИТ, МИС, ПО для пациентов"))*IFERROR('Реестр оборудования'!$N$2:$N$135+0,0)*IFERROR('Реестр оборудования'!$M$2:$M$135+0,0)) -> 2320000000
A46: Итого кухня и F&B | B46: =SUMPRODUCT((((1*('Реестр оборудования'!$G$2:$G$135="Уровень Six Senses Place (велнес-плюс)")+2*('Реестр оборудования'!$G$2:$G$135="Уровень SHA/Chenot (медицина-лайт)")+3*('Реестр оборудования'!$G$2:$G$135="Уровень Lanserhof/CLP (полный медицинский)"))>0)*((1*('Реестр оборудования'!$G$2:$G$135="Уровень Six Senses Place (велнес-плюс)")+2*('Реестр оборудования'!$G$2:$G$135="Уровень SHA/Chenot (медицина-лайт)")+3*('Реестр оборудования'!$G$2:$G$135="Уровень Lanserhof/CLP (полный медицинский)"))<=3))*(('Реестр оборудования'!$B$2:$B$135="Кухня и F&B"))*IFERROR('Реестр оборудования'!$N$2:$N$135+0,0)*IFERROR('Реестр оборудования'!$M$2:$M$135+0,0)) -> 539000000 | C46: =SUMPRODUCT((((1*('Реестр оборудования'!$G$2:$G$135="Уровень Six Senses Place (велнес-плюс)")+2*('Реестр оборудования'!$G$2:$G$135="Уровень SHA/Chenot (медицина-лайт)")+3*('Реестр оборудования'!$G$2:$G$135="Уровень Lanserhof/CLP (полный медицинский)"))>0)*((1*('Реестр оборудования'!$G$2:$G$135="Уровень Six Senses Place (велнес-плюс)")+2*('Реестр оборудования'!$G$2:$G$135="Уровень SHA/Chenot (медицина-лайт)")+3*('Реестр оборудования'!$G$2:$G$135="Уровень Lanserhof/CLP (полный медицинский)"))<=2))*(('Реестр оборудования'!$B$2:$B$135="Кухня и F&B"))*IFERROR('Реестр оборудования'!$N$2:$N$135+0,0)*IFERROR('Реестр оборудования'!$M$2:$M$135+0,0)) -> 539000000 | D46: =SUMPRODUCT((((1*('Реестр оборудования'!$G$2:$G$135="Уровень Six Senses Place (велнес-плюс)")+2*('Реестр оборудования'!$G$2:$G$135="Уровень SHA/Chenot (медицина-лайт)")+3*('Реестр оборудования'!$G$2:$G$135="Уровень Lanserhof/CLP (полный медицинский)"))>0)*((1*('Реестр оборудования'!$G$2:$G$135="Уровень Six Senses Place (велнес-плюс)")+2*('Реестр оборудования'!$G$2:$G$135="Уровень SHA/Chenot (медицина-лайт)")+3*('Реестр оборудования'!$G$2:$G$135="Уровень Lanserhof/CLP (полный медицинский)"))<=1))*(('Реестр оборудования'!$B$2:$B$135="Кухня и F&B"))*IFERROR('Реестр оборудования'!$N$2:$N$135+0,0)*IFERROR('Реестр оборудования'!$M$2:$M$135+0,0)) -> 539000000
A47: Итого медицинская инфраструктура | B47: =SUMPRODUCT((((1*('Реестр оборудования'!$G$2:$G$135="Уровень Six Senses Place (велнес-плюс)")+2*('Реестр оборудования'!$G$2:$G$135="Уровень SHA/Chenot (медицина-лайт)")+3*('Реестр оборудования'!$G$2:$G$135="Уровень Lanserhof/CLP (полный медицинский)"))>0)*((1*('Реестр оборудования'!$G$2:$G$135="Уровень Six Senses Place (велнес-плюс)")+2*('Реестр оборудования'!$G$2:$G$135="Уровень SHA/Chenot (медицина-лайт)")+3*('Реестр оборудования'!$G$2:$G$135="Уровень Lanserhof/CLP (полный медицинский)"))<=3))*(('Реестр оборудования'!$B$2:$B$135="Медицинская инфраструктура"))*IFERROR('Реестр оборудования'!$N$2:$N$135+0,0)*IFERROR('Реестр оборудования'!$M$2:$M$135+0,0)) -> 91000000 | C47: =SUMPRODUCT((((1*('Реестр оборудования'!$G$2:$G$135="Уровень Six Senses Place (велнес-плюс)")+2*('Реестр оборудования'!$G$2:$G$135="Уровень SHA/Chenot (медицина-лайт)")+3*('Реестр оборудования'!$G$2:$G$135="Уровень Lanserhof/CLP (полный медицинский)"))>0)*((1*('Реестр оборудования'!$G$2:$G$135="Уровень Six Senses Place (велнес-плюс)")+2*('Реестр оборудования'!$G$2:$G$135="Уровень SHA/Chenot (медицина-лайт)")+3*('Реестр оборудования'!$G$2:$G$135="Уровень Lanserhof/CLP (полный медицинский)"))<=2))*(('Реестр оборудования'!$B$2:$B$135="Медицинская инфраструктура"))*IFERROR('Реестр оборудования'!$N$2:$N$135+0,0)*IFERROR('Реестр оборудования'!$M$2:$M$135+0,0)) -> 26000000 | D47: =SUMPRODUCT((((1*('Реестр оборудования'!$G$2:$G$135="Уровень Six Senses Place (велнес-плюс)")+2*('Реестр оборудования'!$G$2:$G$135="Уровень SHA/Chenot (медицина-лайт)")+3*('Реестр оборудования'!$G$2:$G$135="Уровень Lanserhof/CLP (полный медицинский)"))>0)*((1*('Реестр оборудования'!$G$2:$G$135="Уровень Six Senses Place (велнес-плюс)")+2*('Реестр оборудования'!$G$2:$G$135="Уровень SHA/Chenot (медицина-лайт)")+3*('Реестр оборудования'!$G$2:$G$135="Уровень Lanserhof/CLP (полный медицинский)"))<=1))*(('Реестр оборудования'!$B$2:$B$135="Медицинская инфраструктура"))*IFERROR('Реестр оборудования'!$N$2:$N$135+0,0)*IFERROR('Реестр оборудования'!$M$2:$M$135+0,0)) -> 0
A48: ИТОГО CapEx | B48: =SUM(B42:B47) -> 6374000000 | C48: =SUM(C42:C47) -> 5516000000 | D48: =SUM(D42:D47) -> 4706000000
A49: CapEx на номер | B49: =B48/$B$3 -> 70822222 | C49: =C48/$B$3 -> 61288889 | D49: =D48/$B$3 -> 52288889
A51: БЕНЧМАРКИ
A52: Люкс-отель: CapEx на номер (HVS, глобально) | B52: $400 000 – $1 100 000 | D52: HVS Hotel Development Cost Survey, люкс-сегмент
A53: Премиальный longevity-резорт: общий CapEx на номер (оценка) | B53: $700 000 – $1 500 000 | D53: Оборудование в этой книге показано как НАДБАВКА к базовой постройке отеля.
A54: CapEx на номер только по оборудованию по уровням (это исследование) | B54: Считается живой формулой из реестра по каждому региону выше. | D54: Меняйте цены в реестре , все своды обновятся.
A55: Примечание о цитировании | B55: Все ценовые ориентиры операторов (Lanserhof, SHA, CLP, Chenot) перекрёстно проверены за 2025–2026 годы. | D55: Полную библиографию см. на листе «Источники и методология».
A58: ОПЕРАЦИОННАЯ ЭКОНОМИКА
A60: Метрика | B60: Six Senses Place | C60: SHA / Chenot | D60: Lanserhof / CLP
A61: Годовой ФОТ клиники, EUR | B61: 1061000 | C61: 2953000 | D61: 3883000
A62: Годовой ФОТ клиники, RUB | B62: 97569000 | C62: 271648000 | D62: 357271000
A63: Выручка программ, год 5, EUR | B63: 27029100 | C63: 27029100 | D63: 27029100
A64: Выручка программ, год 5, RUB | B64: 2486677200 | C64: 2486677200 | D64: 2486677200
A65: Контрибуционная маржа программ, EUR | B65: 14866005 | C65: 14866005 | D65: 14866005

Sheet Окупаемость и выручка
A1: МОДЕЛЬ ОКУПАЕМОСТИ И ВЫРУЧКИ
A2: Окупаемость на уровне оборудования при российской рублёвой базе затрат; цены в EUR/USD приведены в реестре.
A4: ДОПУЩЕНИЯ
A5: Номера | B5: 90
A6: Загрузка на 5-й год | B6: 0.65
A7: Годовых ночей продаж на 5-й год | B7: 21352
A8: Среднее число заездов в год (при 7 ночах) | B8: 3050
A9: Курс RUB/EUR | B9: 92
A10: Рабочих дней в году | B10: 320
A11: Рабочих часов в день | B11: 10
A12: Рабочих часов в году | B12: 3200
A14: БЛОКИ ОКУПАЕМОСТИ ОБОРУДОВАНИЯ (база Россия / RUB)
A15: Блок | B15: Уровень | C15: CapEx (₽) | D15: Годовые расходы (₽) | E15: Цена процедуры (₽) | F15: Годовое количество процедур | G15: Прямая выручка (₽) | H15: Годовой вклад (₽) | I15: Окупаемость (лет) | J15: Характер | K15: Примечания
A16: МРТ 3 Тл (премиальный скрининг) | B16: Уровень Lanserhof/CLP (полный медицинский) | C16: 290000000 | D16: 32200000 | E16: 110000 | F16: 1210 | G16: 133100000 | H16: 100900000 | I16: 2.87 | J16: Прямая , оплата за процедуру | K16: Пропускная способность ограничена 2 200 сканов в год (~50% гостей плюс 30% внешних). Высокомаржинальный executive-скрининг при санкционно обусловленном CapEx. Бенчмарк ЕС €1 800–2 500; целевая цена в России 110 тыс. ₽ ≈ €1 200.
A17: МРТ 1,5 Тл (рабочая лошадка) | B17: Уровень Lanserhof/CLP (полный медицинский) | C17: 130000000 | D17: 16300000 | E17: 70000 | F17: 810 | G17: 56700000 | H17: 40400000 | I17: 3.22 | J17: Прямая , оплата за процедуру | K17: Целевая нагрузка по опорно-двигательному аппарату, неврологии и кардиологии; премия ниже, чем у 3 Тл. Пропускная способность ограничена 1 800 сканами в год.
A18: КТ-сканер 128–256 срезов | B18: Уровень Lanserhof/CLP (полный медицинский) | C18: 117000000 | D18: 16660000 | E18: 45000 | F18: 800 | G18: 36000000 | H18: 19340000 | I18: 6.05 | J18: Прямая , оплата за процедуру | K18: Кардио-CA scoring и низкодозный скрининг лёгких; ~30% гостей. Загрузка ниже МРТ при более высокой пропускной способности.
A19: DEXA-сканер (состав тела + плотность кости) | B19: Уровень Lanserhof/CLP (полный медицинский) | C19: 13000000 | D19: 2010000 | E19: 12000 | F19: 1375 | G19: 16500000 | H19: 14490000 | I19: 0.9 | J19: Прямая , оплата за процедуру | K19: Базовая позиция программ долголетия , назначается практически всем гостям. Цена в России 12 тыс. ₽ ≈ €130.
A20: Полный полисомнографический комплекс (PSG) | B20: Уровень Lanserhof/CLP (полный медицинский) | C20: 12500000 | D20: 4950000 | E20: 80000 | F20: 192 | G20: 15360000 | H20: 10410000 | I20: 1.2 | J20: Прямая , оплата за процедуру | K20: Однокоечная PSG; пропускная способность , 1 исследование за ночь × 320 ночей. Расширение до многокоечной возможно. Целевая цена 80 тыс. ₽ против €800–2500 в ЕС.
A21: CPET / VO2max , метаболическая платформа | B21: Уровень Lanserhof/CLP (полный медицинский) | C21: 9000000 | D21: 4450000 | E21: 25000 | F21: 990 | G21: 24750000 | H21: 20300000 | I21: 0.44 | J21: Прямая , оплата за процедуру | K21: Lanserhof Classic Plus включает CPET в пакет; в России оценочно ~50% от европейских €350–500.
A22: Премиальный кардиологический УЗИ (эхо) | B22: Уровень Lanserhof/CLP (полный медицинский) | C22: 18000000 | D22: 6040000 | E22: 15000 | F22: 800 | G22: 12000000 | H22: 5960000 | I22: 3.02 | J22: Прямая , оплата за процедуру | K22: Кардиологическая опорная позиция; включается в executive-панель плюс оплачивается отдельно за исследование.
A23: Гормональный/иммуноанализатор | B23: Уровень Lanserhof/CLP (полный медицинский) | C23: 10400000 | D23: 4840000 | E23: 8000 | F23: 1600 | G23: 12800000 | H23: 15960000 | I23: 0.65 | J23: Прямая , оплата за процедуру | K23: Высокая доля реагентов; включается в долголетческие панели. Пропускная способность ограничена 4 000 тестами в год (~1,3 на гостя).
A24: Гематологический анализатор (5-diff) | B24: Уровень Lanserhof/CLP (полный медицинский) | C24: 6200000 | D24: 3020000 | E24: 2500 | F24: 2000 | G24: 5000000 | H24: 5980000 | I24: 1.04 | J24: Прямая , оплата за процедуру | K24: Стандартная составляющая executive-панели; ежедневное использование.
A25: Блок IV-кресел (NAD+/витаминно-инфузионная зона) | B25: Уровень Lanserhof/CLP (полный медицинский) | C25: 2880000 | D25: 7715200 | E25: 22000 | F25: 2880 | G25: 63360000 | H25: 55644800 | I25: 0.05 | J25: Прямая , оплата за процедуру | K25: Высокомаржинальный сервис (NAD+ €600–1200; «коктейль Майерса» €120–300). Шесть кресел дают 6 × 320 × 4 сеанса = 7 680 сеансов в год; реалистичная нагрузка ~30%.
A26: FibroScan | B26: Уровень Lanserhof/CLP (полный медицинский) | C26: 28000000 | D26: 4080000 | E26: 4500 | F26: 2400 | G26: 10800000 | H26: 6720000 | I26: 4.17 | J26: Прямая , оплата за процедуру | K26: Часть протоколов longevity и метаболического скрининга. Французский OEM , чистый канал в Россию.
A27: Криосауна (whole-body) | B27: Уровень Lanserhof/CLP (полный медицинский) | C27: 44000000 | D27: 4800000 | E27: 0 | F27: 0 | G27: 0 | H27: 0 | I27: ADR-recovered | J27: Прямая , оплата за процедуру | K27: Цена за сеанс 3 тыс. ₽ ≈ €33 , ниже европейской, что соответствует позиционированию России как «доступной премиальной» аудитории.
A28: Премиальный комплекс банных и термальных зон | B28: Уровень Lanserhof/CLP (полный медицинский) | C28: 48000000 | D28: 5580000 | E28: 8500 | F28: 200 | G28: 1700000 | H28: -3880000 | I28: ADR-recovered (niche neurorehab; consider deferring) | J28: ADR-надбавка / пакеты | K28: Выручка идёт через ADR и комплексные пакеты, а не через прямой биллинг. Якорь культурной идентичности резорта.
A29: Гидротерапевтический контур (Виши, душ-впечатления, Кнайпп, хаммам) | B29: Уровень SHA/Chenot (медицина-лайт) | C29: 5200000 | D29: 4058000 | E29: 0 | F29: 0 | G29: 0 | H29: 0 | I29: ADR-recovered | J29: ADR-надбавка / пакеты | K29: Окупается через ADR-надбавку и SPA-пакеты. Прямой биллинг лишь для отдельных Виши-сеансов.
A30: Полный комплекс Pilates (8 реформеров + кадиллак) | B30: Уровень Six Senses Place (велнес-плюс) | C30: 60930000 | D30: 5846500 | E30: 0 | F30: 0 | G30: 0 | H30: 0 | I30: ADR-recovered | J30: ADR-надбавка / пакеты | K30: Источник выручки , групповые занятия и пакеты. Прямые сеансы , €40–80 за индивидуальный.
A31: Тренажёрный зал Technogym Artis (премиум-линейка) | B31: Уровень SHA/Chenot (медицина-лайт) | C31: 17700000 | D31: 4185000 | E31: 15000 | F31: 600 | G31: 9000000 | H31: 4815000 | I31: 3.68 | J31: ADR-надбавка | K31: Не выставляется отдельным счётом; обеспечивает позиционирование курорта и ADR.
A32: PMS, гостевая инфраструктура и AV | B32: Уровень SHA/Chenot (медицина-лайт) | C32: 35000000 | D32: 4250000 | E32: 11000 | F32: 800 | G32: 8800000 | H32: 4550000 | I32: 7.69 | J32: Обеспечивающая инфраструктура | K32: Окупается через ADR и операционную эффективность. ~5–7 млн ₽ в год , это OPEX по подпискам.
A33: Премиальный кухонный комплекс | B33: Уровень Six Senses Place (велнес-плюс) | C33: 130950000 | D33: 7857000 | E33: 0 | F33: 0 | G33: 0 | H33: 0 | I33: Enabling spend | J33: Обеспечивающая инфраструктура | K33: Терапевтическая и ресторанная кухня. Окупается через P&L F&B (контрибьюшн 25–35%).
A34: МИС среднего класса (тип Athenahealth) | B34: Уровень Lanserhof/CLP (полный медицинский) | C34: 12000000 | D34: 6900000 | E34: 0 | F34: 0 | G34: 0 | H34: 0 | I34: Enabling spend | J34: Обеспечивающая инфраструктура | K34: Обязательная инфраструктура; окупается через эффективность и комплаенс. Подписка 6 млн ₽ в год относится к OPEX.
A35: Полный стек PMS, бронирования SPA и гостевого приложения | B35: Уровень Six Senses Place (велнес-плюс) | C35: 15500000 | D35: 5800000 | E35: 0 | F35: 0 | G35: 0 | H35: 0 | I35: Enabling spend | J35: Обеспечивающая инфраструктура | K35: Стек hospitality и велнес-операций. Подписка 5–7 млн ₽ в год относится к OPEX.
A37: БЕНЧМАРКИ ЦЕН НА ПРОЦЕДУРЫ
A38: Процедура | B38: Lanserhof, якорь (€) | C38: SHA (€) | D38: CLP (€) | E38: Россия, цель (₽) | F38: Россия, эквивалент (€) | G38: Примечания
A39: МРТ всего тела (executive-скрининг, без контраста) | B39: 2200 | C39: 1800 | D39: 2500 | E39: 111000 | F39: 1207 | G39: Lanserhof, SHA и CLP не публикуют отдельных цен на МРТ всего тела , она входит в пакеты долголетия. Бенчмарк ЕС оценочно €1 800–2 500 за самостоятельное исследование (без контраста) в премиальной клинике. Российский эквивалент в премиальной частной клинике , €1 200–1 800.
A40: DEXA (состав тела и плотность кости) | B40: 200 | C40: 180 | D40: 250 | E40: 10000 | F40: 109 | G40: Lanserhof, CLP и Chenot включают DEXA в пакеты долголетия и не публикуют отдельной цены. Оценено по бенчмаркам прямой оплаты в США и Великобритании. Эквивалент в российской премиальной клинике , €80–150.
A41: VO2max / CPET (кардиопульмональный тест) | B41: 400 | C41: 350 | D41: 500 | E41: 20000 | F41: 217 | G41: Пакет Lanserhof Classic Plus на 7 ночей (от €4 046 без проживания) включает VO2max. Российский премиум-сегмент , €200–350.
A42: Полная полисомнография (стационарная ночная) | B42: 1500 | C42: 1300 | D42: 1800 | E42: 76000 | F42: 826 | G42: Стационарная PSG; домашние тесты обычно €200–600. Российский премиум-сегмент , €300–800.
A43: Executive-диагностическая / longevity-панель (medical basis therapy + диагностика, без проживания, 7 ночей) | B43: 4046 | C43: 3825 | D43: 8500 | E43: 223000 | F43: 2424 | G43: Программное ценообразование , базовая медицинская терапия наиболее близка к самостоятельному executive-блоку.
A44: Программа здорового старения / расширенного долголетия (7 ночей, без проживания) | B44: 8053 | C44: 7500 | D44: 21300 | E44: 407000 | F44: 4424 | G44: Самый прямой отраслевой бенчмарк цены программы. CLP Revitalisation Premium до 48 520 CHF задаёт верхнюю границу.
A45: Тест биологического возраста / эпигенетика (биомаркерная панель) | B45: 600 | C45: 500 | D45: 800 | E45: 33000 | F45: 359 | G45: Бенчмарки розничного DTC. Премиальные клиники (CLP, SHA) включают тест в программу; самостоятельный , обычно €400–700. Российские аналоги (Atlas, Genotek) , €80–200 розницей.
A46: Тест микробиома (16S rRNA или метагеномика, отчёт) | B46: 450 | C46: 400 | D46: 600 | E46: 23000 | F46: 250 | G46: Розница DTC €100–450; администрирование в премиальной клинике (с консультацией) , €350–700. Российские аналоги (Atlas, Knomx) , €80–180.
A47: Пакет «Здоровый мозг» (Lanserhof Tegernsee, без проживания) | B47: 5000 | C47: 4000 | D47: 7000 | E47: 253000 | F47: 2750 | G47: Lanserhof не раскрывает точную цену надстройки; структура повторяет надстройку Longevity (€5 113). Учитывается как оценка.
A49: БЕНЧМАРКИ ЦЕН НА ПАКЕТЫ
A50: Оператор | B50: Пакет | C50: Цена (€) | D50: Включает проживание | E50: Что входит | F50: Источник
A51: Lanserhof Tegernsee | B51: Lanserhof Cure Classic + Longevity (7 ночей, только программа, без проживания) | C51: 8053 | D51: 8175 | E51: Первичный и заключительный осмотры врача, промежуточные приёмы с мануальными абдоминальными процедурами, диагностика состава тела, ежедневные терапевтические групповые сессии, longevity-диагностика (эпигенетика и биомаркеры), питание по принципам Майра (полный пансион), доступ к SPA. Проживание , отдельно. | F51: https://lanserhof.com/en/lanserhof-tegernsee/treatments/package-longevity-tegernsee/ ; https://www.serenityways.com/clinics/lanserhof-tegernsee
A52: SHA Wellness Clinic Spain (Аликанте) | B52: Advanced Longevity (7 ночей, программа + Deluxe Suite с видом на море, на 2 гостей) | C52: 12520 | E52: Генетическое тестирование, биомаркерный анализ, биологический профиль из 88 показателей, гипоксическая тренировка, нейрокогнитивная оценка, фотобиомодуляция, NAD-терапия, гипербарическая оксигенация, индивидуальная нутрициология (полный пансион), холистические процедуры, проживание в Deluxe Suite с видом на море. | F52: https://shawellness.com/en/advanced-longevity/ ; https://www.serenityways.com/clinics/sha-spain
A53: Clinique La Prairie (Монтрё) | B53: Master Detox (6 ночей / 7 дней) | E53: Проживание, полный пансион (детокс-меню CLP), комплексные медицинские консультации и диагностика (кардиология, терапия), углублённые детокс-процедуры, лимфодренаж, IV-терапия, доступ к SPA, план дальнейшего наблюдения. | F53: https://www.cliniquelaprairie.com/programs/master-detox/ ; https://swissmedexpert.com/clinique-la-prairie-detox
A54: Clinique La Prairie (Монтрё) | B54: Revitalisation Premium / Legendary Premium (1 неделя, верхний уровень) | E54: Фирменная клеточная программа CLP, полный медицинский осмотр с визуализацией, расширенная диагностика, мультиспециализированные консультации, проживание в премиальном сьюте, полный пансион, SPA. | F54: https://serenityways.com/pages/clinique-la-prairie-prices ; https://swissmedexpert.com/clinic-la-prairie
A55: Chenot Palace Weggis | B55: Advanced Detox (7 ночей, без проживания) | E55: Метод Chenot, ежедневные медицинские консультации, энергетические и детокс-процедуры (hydro-jet, биоэнергетические, фитогрязи, массаж), комплексная диагностика, питание (диета Chenot, fasting-mimicking), доступ к фитнесу, бассейну и термальной зоне. Проживание , отдельно. | F55: https://www.chenot.com/chenot-palace/weggis/programmes/ ; https://www.serenityways.com/clinics/chenot-palace-weggis ; https://www.chenot.com/wp-content/uploads/2024/05/Chenot-Palace-Weggis-Brochure-EN.pdf
A56: VIVAMAYR Maria Wörth / Altaussee | B56: Modern Mayr Cure Classic (7 ночей, только программа) | E56: Первичная и заключительная консультации с врачом по Майру, ежедневные абдоминальные процедуры, полный пансион по диете Майра, процедуры пищеварения, базовая диагностика (лаборатория, состав тела), доступ к SPA. Проживание , отдельно (номера от €378 до €3 750 за ночь). | F56: https://www.vivamayr.com/en/downloads/ ; https://serenityways.com/pages/vivamayr-prices ; https://www.best-treatment.com/en/clinics/vivamayr-altaussee/packages/modern-mayr-cure-basic
A57: Buchinger Wilhelmi (Боденское озеро, Юберлинген) | B57: Классическая 10-дневная программа лечебного голодания | E57: Минимум 10 ночей: разгрузочный день, ~6 дней голодания, дни выхода. Две медицинские консультации на 7 ночей, расширенная лабораторная диагностика, ежедневный осмотр, печёночные обёртывания, кишечные процедуры через день, круглосуточный дежурный врач, ваучер €45 за ночь на процедуры. Проживание , отдельно (обычно от €218 за ночь). | F57: https://www.buchinger-wilhelmi.com/en/buchinger-wilhelmi-lake-constance/arrangements-packages/ ; https://www.buchinger-wilhelmi.com/wp-content/uploads/2024/11/What-we-offer-2025_web_V1.3.pdf ; https://luxury-rehabs.com/buchinger-wilhelmi/
A58: Six Senses (базовая программа долголетия в нескольких отелях) | B58: Six Senses Longevity (зависит от объекта; например Six Senses Ibiza, Douro Valley, Kaplankaya) | E58: Персонализированная программа с биомаркерной базой, интегративной медицинской консультацией, анализом сна, фитнес-оценкой, IV/пептидной терапией (там, где разрешено), индивидуальным питанием, холистическими процедурами, проживанием и полным пансионом. | F58: https://www.sixsenses.com/en/wellness-spa/personalized-wellness/longevity/ ; https://www.sixsenses.com/en/wellness-spa/retreats/ ; https://www.hotel-online.com/news/six-senses-2025-wellness-forecast
A60: ЭКОНОМИКА ПАКЕТА , премиум-программа долголетия 7 ночей по €15 000 на гостя
A61: Компонент | B61: Доля | C61: Стоимость (€) | D61: Примечания
A62: Проживание | B62: 0.3 | C62: 4500 | D62: Сьют, тариф за номер на 7 ночей
A63: Медицинские процедуры (собственное оборудование) | B63: 0.25 | C63: 3750 | D63: Аллокация МРТ/КТ/DEXA/PSG/CPET/лаборатории на пакет
A64: SPA и восстановление (собственное оборудование) | B64: 0.15 | C64: 2250 | D64: Гидротерапия, криосауна, банный комплекс, хаммам, Виши, пилатес
A65: F&B (терапевтическая и ресторанная) | B65: 0.12 | C65: 1800 | D65: Терапевтическое меню и a la carte allowance
A66: Профильные консультации (труд) | B66: 0.13 | C66: 1950 | D66: Время врача, нутрициолога, специалиста по сну, физиотерапевта
A67: Маржинальный вклад | B67: 0.05 | C67: 750 | D67: Контрибьюшн объекта после прямого OPEX
A68: Итого пакет | B68: =SUM(B62:B67) -> 1 | C68: =SUM(C62:C67) -> 15000
A70: ОБОРУДОВАНИЕ БЕЗ ПРЯМОГО БИЛЛИНГА , ЛОГИКА НАДБАВКИ К ADR
A71: Обоснование | B71: Высококлассный тренажёрный зал, гидротерапевтический бассейн, премиальный банный комплекс, полная пилатес-студия, снежная комната и хаммам не выставляются за процедуру, но обеспечивают значимую надбавку к ADR относительно сопоставимого люкс-отеля.
A72: Надбавка к ADR за ночь (€) | B72: 250
A73: Надбавка к ADR за ночь (₽) | B73: 23000
A74: Годовых ночей продаж на 5-й год | B74: 21352
A75: Годовая надбавка (₽) | B75: 491096000
A76: Годовая надбавка (€-эквивалент) | B76: 5338000
A77: Примечания | B77: Надбавка = 23 000 ₽ × 21 352 ночи (90 номеров × 365 × 65% загрузки). Отраслевое правило: премиальное SPA/велнес добавляет 15–30% к ADR; €250 за ночь , консервативная оценка при базе €1 000–1 500 за ночь.
A79: СВОДНЫЕ ДИАПАЗОНЫ ОКУПАЕМОСТИ
A80: Быстрая окупаемость (< 1,5 года) | B80: Парк IV-кресел (~0,05 года), CPET (~0,5 года), DEXA, гормональный анализатор (~1 год) , небольшой CapEx и высокая маржинальность.
A81: Средняя окупаемость (1,5–6 лет) | B81: Гематологический анализатор, полная PSG (~1–1,5 года); МРТ 3 Тл (~3 года), МРТ 1,5 Тл (~3 года), КТ (~5–6 лет с поправкой на загрузку), кардио-УЗИ (~3 года).
A82: Долгая окупаемость (> 6 лет напрямую) | B82: Криосауна (~4 года), банный комплекс (~6–8 лет смешанно), Виши/хаммам (~10–15 лет напрямую).
A83: Надбавка к ADR / обеспечивающая инфраструктура | B83: Гидротерапевтический бассейн, полный комплект Technogym, пилатес-студия, кухня и F&B, МИС, полный стек PMS+ИТ , окупаются через ADR, цены пакетов, маржу F&B либо обеспечивают инфраструктуру. Lokomat помечен как нишевый/маржинальный , целесообразно отложить.

Sheet Региональные факторы стоимости
A1: РЕГИОНАЛЬНЫЕ ФАКТОРЫ СТОИМОСТИ
A2: Справочный документ , основан на Phase 6 исследования. Российский раздел проработан наиболее детально с учётом санкционной сложности.
A4: 1. ЗАПАДНАЯ ЕВРОПА
A5: Базовый прайс OEM | B5: Западная Европа (Германия, Швейцария, Австрия, Италия, Франция, Испания) фактически выступает базовой шкалой OEM-цен по основным производителям медицинского и SPA-оборудования для сегмента longevity-резортов: Siemens Healthineers, GE HealthCare (продажи в ЕС), Philips, Drägerwerk, Storz, Olympus, Hologic, Technogym, Klafs, Starpool, Iyashi Dôme, Cosmed, Schiller, Mindray-Europe. Прайс в EUR обычно служит ориентиром для трансграничных бенчмарков.
A6: Дистрибьюторская наценка | B6: Типичная наценка локального дистрибьютора над прайсом OEM , 15–25%. Прямые контракты с OEM на крупные пакеты (от €1 млн) часто дают скидку 8–15% от прайса; единичные покупки оплачиваются по полному прайсу с дистрибьюторской наценкой.
A7: Уровень затрат на обслуживание | B7: Сервисные контракты в среднем составляют 6–10% CapEx для визуализации (МРТ, КТ, УЗИ) и 4–7% для SPA и оборудования восстановления. Многолетние пакеты (5–7 лет) обычно согласуются по эффективной ставке 5–7%.
A8: Рынок б/у и refurb | B8: Сильный вторичный рынок: восстановленные МРТ и КТ обычно стоят 40–60% от прайса нового, восстановленный ультразвук , 35–50%, DEXA , 50–65%. Block Imaging, Oxford Instruments, Soma Tech и Avante Health Solutions , основные брокеры с присутствием в ЕС. По SPA-оборудованию (криосауна, ИГГТ, гипербарика, Technogym) refurb-рынок тоньше: 60–80% от нового и ограниченное предложение.
A9: Ключевые замечания | B9: Возмещение НДС обычно доступно лицам с медицинской лицензией (Германия 19%, Австрия 20%, Швейцария 8,1%, Испания 21%, Италия 22%). Для медицинских изделий обязательна маркировка CE в рамках MDR (EU 2017/745); сроки перехода 2022–2024 годов привели к удорожанию изделий Class II/III на 5–8%. Энергетическая и трудовая инфляция 2022–2024 годов добавила примерно 10–15% к стоимости SPA-проектов.
A10: Замечания по валютам | B10: База , EUR; премия CHF к EUR обычно 10–15% для оборудования швейцарского производства.
A12: 2. СЕВЕРНАЯ АМЕРИКА
A13: Цены относительно Европы | B13: Прайс в USD обычно на 10–20% выше европейского по визуализации и лабораторной технике (до перевода валют); для SPA и эстетики , на 5–15%. Связано с более высокой маржей дилеров, регуляторными издержками и премией за tort-litigation, заложенной в цены.
A14: Регуляторика FDA | B14: Требуется одобрение FDA 510(k) или PMA; срок вывода на рынок длиннее (обычно +6–18 месяцев против CE), и регуляторные издержки OEM включаются в американский прайс. Часть моделей, доступных в ЕС, недоступна в США, что приводит к выбору альтернативных SKU по более высокой цене. МРТ всего тела с одобрением FDA (Prenuvo, Ezra) развивается как сегмент прямой оплаты.
A15: Лизинговый рынок | B15: Сильно развитый рынок equipment finance и операционного лизинга; большинство премиальных велнес-операторов лизингует визуализацию (типичный срок 60 месяцев, эффективная ставка 4–7%). DLL, Siemens Financial Services и GE HealthCare Financial Services занимают доминирующие позиции. Доля лизинга по визуализации , около 50–60%, по SPA , 25–35%.
A16: Сервисная сеть | B16: Плотное сервисное покрытие OEM; в крупных метрополиях доступен SLA с откликом 4 часа за ~10–12% CapEx в год.
A17: Ключевые замечания | B17: Налог с продаж по штатам , 0–9,5%. Тарифные риски в 2024–2026 годах повышены (тарифы Section 301 на Китай затронули Mindray/Edan, отдельные SKU Technogym, собираемые в Азии). Соответствие HIPAA и интеграция МИС добавляют 5–10% к ИТ-CapEx.
A19: 3. АЗИЯ
A20: Региональное производство | B20: Mindray (Китай, Шэньчжэнь) , №3 в мире по мониторам пациента и УЗИ; Edan (Китай) , ЭКГ, УЗИ, мониторы; Samsung Medison (Корея) , УЗИ, рентген; United Imaging (Китай) , МРТ/КТ, конкурентные с Siemens/GE/Philips, на 30–50% дешевле; Esaote (итальянская, производство в АТР) , УЗИ. Ниже стоимость по мониторингу, ЭКГ, УЗИ и базовой лаборатории; почти паритет по продвинутой визуализации.
A21: Импортные пошлины | B21: Сингапур: 0% на большинство медицинских изделий (HSA-перечень); Таиланд: 0–10% (большинство , освобождено по FDA-TH); ОАЭ: 0–5% (DHA/MOHAP); Япония: 0%; Корея: 0–8%; Китай: 0–4% при НДС 13% (медицина обычно по сниженной ставке 9% или освобождена); Гонконг: 0%.
A22: Сервисная сеть | B22: Сильная в Сингапуре, Гонконге, ОАЭ, Японии и Сеуле; слабее в Индонезии, Вьетнаме и второстепенных городах Китая. Mindray заявляет о сервисной сети в более чем 190 странах с региональными хабами.
A23: Ключевые замечания | B23: Оборудование азиатского производства (УЗИ Mindray и Samsung, диагностика сна BMC) после 2022 года всё чаще выступает заменителем в России. ОАЭ стали хабом параллельного реэкспорта. Индия предлагает оборудование Wipro GE с дисконтом 10–25% к европейскому прайсу.
A25: 4. РОССИЯ , наиболее детальная глубина: санкции, параллельный импорт, отечественные альтернативы
A26: Таможенные пошлины | B26: Медицинское оборудование по ТН ВЭД 9018–9022 , обычно 0–5% (большая часть визуализации, ЭКГ, УЗИ и хирургический инструмент 0–5%); отдельные категории 5–10%. Постановление №1042 (2008, с поправками) перечисляет конкретное медицинское оборудование, освобождаемое от пошлины. Статус необходимо перепроверять по коду ТН ВЭД при таможенной декларации.
A27: НДС | B27: Стандартная ставка НДС , 20%; многие медицинские изделия из правительственного перечня (Постановление №1042 / перечень жизненно необходимых) освобождены от НДС либо облагаются по сниженной ставке 10%. Оператору следует подтверждать освобождение по каждому изделию через российского таможенного брокера.
A28: Волатильность RUB | B28: RUB ослаб с ~89/USD на конец 2023 года до ~110/USD на конец 2024 года (~23%). Модели CapEx должны учитывать запас 15–25% на ослабление RUB на горизонте 5 лет , с FX-хеджированием либо контрактами в USD/EUR, где это возможно. Многотраншевая закупка по этапам строительства снижает FX-шок.
A29: Категории, затронутые санкциями | B29: Ограничено (EU 833/2014 и US BIS): высокотехнологичная визуализация при стоимости свыше $750 тыс. либо с компонентами двойного назначения (продвинутые МРТ от 3 Тл и выше, ПЭТ-КТ, отдельные КТ, ИИ-диагностические платформы, зависящие от облака на западных серверах). Допущено по лицензиям/исключениям: стандартные УЗИ, ЭКГ, мониторы пациента, базовые лабораторные анализаторы, диагностика сна, большая часть SPA и оборудования восстановления. Лицензионное исключение US BIS MED (апрель 2024, 15 CFR 740.23) разрешает экспорт медицинских устройств класса EAR99 в Россию без лицензии. EU 833/2014 содержит медицинское исключение для лекарств и большинства медицинских изделий.
A30: Механика параллельного импорта | B30: Постановление Правительства №506 (29 марта 2022) и приказ Минпромторга №1532 (апрель 2022, с изменениями в 2024–2025 годах) разрешают параллельный импорт по многим категориям медицинской техники без согласия правообладателя. Механизм продлён до 2025 года и далее. Побочные эффекты: гарантия OEM аннулируется, заводской сервисный контракт отсутствует, обновления ПО и удалённая диагностика часто отключены, сроки поставки запчастей через серый канал , 3–6 месяцев.
A31: Сервис OEM после 2022 года | B31: Siemens Healthineers, GE HealthCare и Philips приостановили новые продажи и большую часть сервисных контрактов в России после февраля 2022 года. Сервис установленной базы ведётся частично (по гуманитарным/жизненно необходимым исключениям). Российские системные интеграторы (например, Medtech-M, Medrobotics, ММЦ, Intelmed, R-Pharm) поставляют запчасти и оказывают сторонний сервис. Сроки поставки запчастей , 8–24 недели; поддержка ПО и прошивок ненадёжна.
A32: Б/у и refurb по России | B32: Активный отечественный и параллельный refurb-рынок: типично 40–60% от европейского прайса по визуализации и 50–70% по SPA. Предложение по западным брендам сокращается; растёт предложение новых и восстановленных китайских изделий. Контроль качества затруднён без сервиса OEM.
A33: Отечественные альтернативы и заменители | B33: ЭКГ/Холтер: Aktiv-Med, Medical Computer Systems (Нейрософт), Schiller-Реомед (СП). УЗИ: ограниченные отечественные мощности; параллельный импорт замещают Mindray (Китай) и Samsung (Корея). Мониторы пациента: «Тритон Электронные Системы», «Квазар». Стерилизаторы и автоклавы: «Озон-Мед», «КАСИМОВ-МЕДИН», Tuttnauer (параллельный). Лабораторные анализаторы: АО «ЭЙЛИТОН», «Реамед»; в премиум-сегменте доминируют Mindray и Roche-cobas (параллельный). Гипербарика и кислород: производители на базе Хруничевского, аффилированные с Сеченовским университетом. Криотерапия: отечественных мало; CryoBuilt и Mecotec , параллельный импорт. SPA и восстановление (сауны, ИК, соляные комнаты): сильные отечественные мощности (лицензионная сборка TyloHelo, аналоги Helo, KLAFS , параллельный). Российские лаборатории биомаркеров и долголетия: Atlas, Genotek, MyGenetics , эпигенетика и микробиом по цене 30–50% от европейской розницы.
A35: МЕТОДОЛОГИЧЕСКАЯ ЗАМЕТКА
A36: Кросс-региональная корректировка | B36: Региональные корректировки к базовому EUR-прайсу OEM применяются следующим образом. (1) Стартовая точка , EUR-прайс (база Западной Европы). (2) Применяется категорийная российская надбавка: визуализация , +25–40% к EUR-прайсу (параллельный импорт, логистика, FX-буфер, премия серого канала); SPA и восстановление , +15–25%; лаборатория и ИТ , +10–20%; локально закупаемое FF&E , −10…−25% к ЕС. (3) Добавляется FX-буфер 15–25% на CapEx, распределённый на 24–36 месяцев строительства. (4) Добавляется 8–12% премии за монтаж и пусконаладку для санкционного оборудования, требующего стороннего сервисного развёртывания. (5) Для международных бенчмарков уровня Tier-1 (Lanserhof, CLP, Chenot) используется база Западной Европы напрямую , эти операторы закупают по прайсу OEM с европейскими сервисными контрактами. (6) Годовое обслуживание (OPEX): 8–12% CapEx для базы в России (против 6–10% в ЕС) с учётом стоимости запчастей через серый канал. (7) Для аудиторского следа методологии каждая позиция документируется по источнику: прайс OEM, котировка дистрибьютора, котировка refurb-брокера, сопоставимая цена peer, либо триангулированная оценка по (а) глобальному прайсу, (б) российскому коэффициенту надбавки, (в) FX-предположению.
A37: СВОДКА РИСКОВ ПО РОССИИ
A38: Таможня и НДС | B38: Пошлина 0–5% по ТН ВЭД 9018–9022 с исключениями по Постановлению №1042; стандартный НДС 20%, сниженная ставка 10% или освобождение для многих медицинских изделий из правительственного перечня. Оператор обязан проверять освобождение по каждому коду ТН ВЭД через российского таможенного брокера.
A39: Затронуто санкциями | B39: ОГРАНИЧЕНО (EU 833/2014 и US BIS): премиальные МРТ от 3 Тл, ПЭТ-КТ, продвинутая КТ, ИИ-диагностические платформы, зависящие от облака. РАЗРЕШЕНО по лицензии/исключению: стандартные УЗИ, ЭКГ, мониторы пациента, базовые лабораторные анализаторы, диагностика сна, большая часть SPA и оборудования восстановления. Лицензионное исключение US BIS MED разрешает медицинские устройства класса EAR99 с апреля 2024 года.
A40: Параллельный импорт и сервисный риск | B40: Постановление №506 (2022) разрешает параллельный импорт без согласия правообладателя до 2025 года и далее. Побочные эффекты: гарантия OEM аннулируется, заводской сервисный контракт отсутствует, обновления ПО и удалённая диагностика часто отключены, запчасти через серый канал , 3–6 месяцев (8–24 недели). По визуализации , премия 25–40%.
A41: Отечественные альтернативы | B41: Mindray / United Imaging / Samsung Medison (УЗИ, КТ, МРТ через параллельный импорт); Нейрософт / Aktiv-Med / Schiller-Реомед СП (ЭКГ, Холтер); TyloHelo / KLAFS-сборка (сауна); «Тритон» / «Квазар» (мониторы); Atlas / Genotek / MyGenetics (эпигенетика, микробиом, биомаркеры по цене 30–50% от европейской розницы).

Sheet Источники и методология
A1: ИСТОЧНИКИ И МЕТОДОЛОГИЯ
A2: Библиография из 56 цитируемых источников, оценка достоверности и рекомендации по верификации.
A4: Название | B4: Тип | C4: Использовано для | D4: URL | E4: Дата обращения
A5: Lanserhof Tegernsee , Package Longevity | B5: Публикация цен оператором | C5: Цена надстройки Longevity (€5 113), базовая Classic-терапия (€2 940), пакет «Здоровый мозг» | D5: https://lanserhof.com/en/lanserhof-tegernsee/treatments/package-longevity-tegernsee/ | E5: 2026-05-03
A6: Lanserhof Lans , Package Longevity | B6: Публикация цен оператором | C6: Lanserhof Longevity отдельно , €6 618 без проживания | D6: https://lanserhof.com/en/lanserhof-lans/treatments/package-longevity-lans/ | E6: 2026-05-03
A7: SerenityWays , Lanserhof Tegernsee profile | B7: Отраслевой агрегатор | C7: Перекрёстная проверка цен программ и итогов (€8 175 , стартовая стоимость 7 ночей) | D7: https://www.serenityways.com/clinics/lanserhof-tegernsee | E7: 2026-05-03
A8: SHA Wellness Clinic , Advanced Longevity programme page | B8: Публикация цен оператором | C8: Advanced Longevity 7 ночей , €7 500; 10 ночей , €9 500; 14 ночей , €12 000 | D8: https://shawellness.com/en/advanced-longevity/ | E8: 2026-05-03
A9: SerenityWays , SHA Spain prices | B9: Отраслевой агрегатор | C9: Полная стоимость пребывания SHA с проживанием (€12 520 за 7 ночей на 2 гостей в Deluxe Suite) | D9: https://www.serenityways.com/clinics/sha-spain | E9: 2026-05-03
A10: Clinique La Prairie , Master Detox programme | B10: Публикация цен оператором | C10: Master Detox: 20 950 CHF за 7 дней / 6 ночей | D10: https://www.cliniquelaprairie.com/programs/master-detox/ | E10: 2026-05-03
A11: SwissMedExpert , Clinique La Prairie pricing summary | B11: Отраслевой агрегатор | C11: Программный диапазон CLP: 5 000–48 520 CHF (от Detox до Legendary Premium Revitalisation) | D11: https://swissmedexpert.com/clinic-la-prairie | E11: 2026-05-03
A12: Chenot Palace Weggis , Programmes & brochure | B12: Публикация цен оператором | C12: Advanced Detox 5 500 CHF за 7 ночей только программа; Nest Room 410 CHF за ночь; общий старт 8 370 CHF | D12: https://www.chenot.com/chenot-palace/weggis/programmes/ | E12: 2026-05-03
A13: Chenot Palace Weggis , 2024 Brochure (PDF) | B13: Публикация оператора | C13: Структура программы и состав | D13: https://www.chenot.com/wp-content/uploads/2024/05/Chenot-Palace-Weggis-Brochure-EN.pdf | E13: 2026-05-03
A14: VIVAMAYR , Downloads (price lists) | B14: Публикация оператора | C14: Modern Mayr Cure Classic: Maria Wörth , €3 825; Altaussee , €4 385; уровни проживания | D14: https://www.vivamayr.com/en/downloads/ | E14: 2026-05-03
A15: VIVAMAYR Maria Worth pricelist (PDF, Jan 2024) | B15: Публикация оператора | C15: Цены программ и проживания в EUR | D15: https://www.vivamayr.com/app/uploads/2025/01/VIVAMAYR_MW_Preisliste_E_inkl.-Programme_15.01.2024.pdf | E15: 2026-05-03
... A60: Globetrender , Six Senses to open three urban wellness resorts in 2026 | B60: Отраслевое освещение | C60: Six Senses London (Whiteley) , мощность 109 номеров и 14 резиденций; открытие в 2026 году | D60: https://globetrender.com/2025/12/02/four-new-six-senses-resorts-2026/ | E60: 2026-05-03
A63: ОЦЕНКА ДОСТОВЕРНОСТИ
A64: Наиболее надёжно | C64: Цены по Западной Европе (€) и Северной Америке (USD) для кухни, спортзала, SPA и ИТ/PMS , взяты с актуальных страниц дилеров и из прайсов OEM (Rational, Technogym, Pilates, Klafs, Mews, Salesforce). Расхождение с фактической котировкой обычно ±10%.
A65: Умеренно надёжно | C65: Визуализация (МРТ, КТ, DEXA), лабораторные анализаторы и медицинская инфраструктура для ЕС и Северной Америки , взяты из прайсов refurb-брокеров (Block Imaging, Avante, Soma Tech) и публичных котировок OEM. По новому оборудованию расхождение составляет ±15%; refurb-предложения точнее.
A66: Самая слабая колонка , Россия (₽) | C66: Российские цены ТРИАНГУЛИРОВАНЫ, а не получены прямой котировкой. Метод: европейский прайс EUR + надбавка 25–40% по визуализации (премия параллельного импорта плюс FX-буфер) + 15–25% по SPA и восстановлению + 10–20% по лаборатории и ИТ; минус 10–25% на локально закупаемом FF&E. Достоверность: средняя для SPA/ИТ, низкая для санкционной визуализации. Расхождение с фактической котировкой ±25–40%.
A67: Pass-through позиции | C67: Расширенные биомаркерные панели, киты CGM, киты микробиома, эпигенетические тесты возраста , это позиции с нулевым CapEx (расходники, оплачиваемые на гостя), учитываются как pass-through. Объёмы влияют на маржу, а не на CapEx.
A69: РЕКОМЕНДАЦИИ ПО ВЕРИФИКАЦИИ ПЕРЕД ФИКСАЦИЕЙ CapEx
A70: Российская визуализация , ОБЯЗАТЕЛЬНО | C70: Запросить котировку у российского брокера медицинской техники до фиксации CapEx. Рекомендованы: M-Equipment (Москва), MedTechMarket, Medtech-M либо консультант по закупкам, аффилированный с Сеченовским университетом. Особенно по позициям: МРТ 3 Тл, КТ 128 срезов, DEXA, маммография. Расхождение с оценками этой книги составит 25–40%.
A71: Российские SPA и баня , РЕКОМЕНДУЕТСЯ | C71: Подтвердить с российским SPA-генподрядчиком (Termopark, «Русская баня», Banya Project), поскольку цена банного комплекса варьируется в 2–3 раза в зависимости от технологии и породы (кедр, липа, дуб). Оценки в RUB предполагают поставку «под ключ» из бруса и могут занижать стоимость премиального кедра на 15–30%.
A72: Визуализация в Западной Европе , ОПЦИОНАЛЬНО | C72: Сверить с Block Imaging, Avante или Soma Tech по refurb-аналогам того же класса; прайс OEM обычно даёт скидку 10–15% на пакеты от €1 млн.
A73: ИТ / ПО , ОПЦИОНАЛЬНО | C73: Цены Mews, Salesforce и Athenahealth масштабируются количеством номеров и числом специалистов. Подтвердить котировкой поставщика на момент подписания. Подписочный рост обычно 5–8% в год.
A74: Цены процедур и пакетов , ОПЦИОНАЛЬНО | C74: Цены процедур привязаны к публичным данным Lanserhof, CLP и SHA, а также к самостоятельным европейским клиникам (Anova IRM, Radiologie Dr Jung, Prenuvo, Ezra). Российские целевые цены , позиционные оценки; следует свериться с публичными прайсами Сеченовского центра и клиники «Рассвет».

Sheet Биомаркеры
A1: ПАКЕТЫ БИОМАРКЕРОВ
A3: Пакет | B3: Цена ЕС, EUR | C3: Цена в РФ, EUR | D3: Цена в РФ, RUB | E3: Кейс применения | F3: Маркеры
A4: Foundation Longevity Panel | B4: 1850 | C4: 2050 | D4: 188600 | E4: Базовая оценка при поступлении на любую программу долголетия, повтор ежегодно. Диагностическая основа, обосновывающая каждый последующий протокол. | F4: TruAge Complete (Horvath, GrimAge2, DunedinPACE, OMICmAge, SYMPHONYAge); Glycan age; PhenoAge (расчётный); hsCRP, IL-6, фибриноген; Глюкоза натощак, инсулин натощак, HOMA-IR, HbA1c; Полная липидограмма, ApoB, Lp(a); Тестостерон общий и свободный, SHBG, estradiol, DHEA-S; TSH, free T3, free T4; IGF-1; Cortisol AM/PM; 25-OH vitamin D, holotranscobalamin B12, RBC folate; Омега-3 индекс; Liver and kidney panels; Heavy metals (4-metal whole blood); APOE, MTHFR (однократно)
A5: Inflammaging Panel | B5: 580 | C5: 620 | D5: 57040 | E5: Контроль программы Inflammaging Reversal на 90-й и 180-й день; повтор ежегодно. | F5: Glycan age; hsCRP, IL-6, TNF-alpha, IL-1beta, фибриноген; GDF15 (суррогат SASP); oxLDL; Омега-3 индекс
A6: Mitochondrial / NAD+ Panel | B6: 480 | C6: 620 | D6: 57040 | E6: Программа Mitochondrial Reset; измерение до и после инфузии NAD+; повтор на 30-й и 90-й день. | F6: Внутриклеточный NAD+ (Jinfiniti); Лактат (натощак, после нагрузки); Пируват; Органические кислоты в моче (Genova или локальный эквивалент); Убихинон (CoQ10) в плазме; Carnitine free and total
A7: Metabolic / Time-Restricted Eating Panel | B7: 420 | C7: 350 | D7: 32200 | E7: Программы Metabolic Renewal и TRE; CGM при поступлении и на 90-й день. | F7: Глюкоза натощак, инсулин натощак, HOMA-IR, HbA1c; ПГТТ 75 г с инсулином (3 часа); ApoB, Lp(a), small dense LDL, oxLDL; CGM на 14 дней (FreeStyle Libre 2); Печёночная панель (ALT, AST, GGT); Адипонектин и лептин
A8: Hormone and HPA Axis Panel | B8: 480 | C8: 380 | D8: 34960 | E8: Кандидатура на ЗГТ, программа Stress and Sleep, Adrenal Reset; повтор через 90 дней после начала ЗГТ. | F8: Тестостерон общий и свободный, SHBG; Эстрадиол, прогестерон, DHEA-S; Кортизол 4 точки в слюне (Genova или DUTCH); IGF-1; TSH, свободный T3, свободный T4, reverse T3; Прегненолон, 17-OH прогестерон
A9: Premium Cellular Renewal Panel (top tier) | B9: 3800 | C9: 4500 | D9: 414000 | E9: Ежегодное углублённое обследование для членов с высоким уровнем дохода во флагманской программе Cellular Renewal. Маркетинг-уровень комплексной панели, сопоставимой с Lanserhof Lans Med Concept и Clinique La Prairie Master Diagnosis. | F9: Полная Foundation Longevity Panel; Длина теломер (Life Length TAT); SASP / Olink Inflammation 96; LDL-P NMR LipoProfile; Микробиом shotgun (Viome или Genova GI Effects); Heavy metals 8-metal extended; Pharmacogenomics CYP panel; Дополнительные маркеры исследования сенесценции
A12: ПОЛНЫЙ РЕЕСТР 54 МАРКЕРОВ
A14: Маркер | B14: Биологический путь | C14: Метод | D14: Вендор | E14: Цена ЕС, EUR | F14: Цена РФ landed, RUB | G14: Доступность РФ | H14: Evidence | I14: Использовано в программах
A15: Epigenetic age, Horvath multi-tissue clock | B15: DNA methylation drift, cellular senescence accumulation, mortality risk | C15: Whole blood or buccal swab, Illumina EPIC methylation array (850K CpG sites) | D15: TruDiagnostic (Lexington KY) TruAge Complete; alternative myDNAge (Epimorphy/Zymo) | E15: 460 | F15: 43240 | G15: No domestic provider with validated Horvath clock. Sample (DBS card or EDTA whole blood) must ship out. Workflow: kit imported via Astana, sample drawn at resort, return courier via DHL Medical Express ex-Almaty or Istanbul. | H15: B (mechanistic strong; intervention reversibility growing) | I15: Cellular Renewal; Epigenetic Age Reduction; Intake baseline
A16: Epigenetic age, GrimAge2 | B16: Mortality and morbidity prediction via DNAm surrogates of plasma proteins (GDF15, PAI-1, B2M, leptin) and smoking pack-years | C16: Bundled in TruAge Complete, same EPIC array | D16: TruDiagnostic (licensed by Lu and Horvath); also Elysium Index | E16: 0 | F16: 0 | G16: Bundled in TruAge Complete, see Horvath row | H16: A (most predictive of all-cause mortality among published clocks) | I16: Cellular Renewal; Epigenetic Age Reduction
A17: DunedinPACE pace-of-aging | B17: Pace of biological aging per chronological year, derived from Dunedin birth cohort | C17: Bundled in TruAge Complete | D17: TruDiagnostic (exclusive license); also Elysium Index | E17: 0 | F17: 0 | G17: Bundled, see Horvath row | H17: A (most responsive clock to lifestyle intervention in CALERIE trial) | I17: Cellular Renewal; Epigenetic Age Reduction; follow-up at 12 months
A18: PhenoAge (Levine) | B18: Composite of 9 routine clinical biomarkers (albumin, creatinine, glucose, hsCRP, lymphocyte percent, MCV, RDW, alkaline phosphatase, WBC) plus chronological age, mapped to a methylation clock | C18: Phenotypic version: standard chemistry (in Russia via INVITRO or KDL). DNAm version: Illumina EPIC. | D18: Calculated in-house from standard chemistry; methylation version bundled in TruAge | E18: 0 | F18: 0 | G18: Phenotypic version fully calculable from Russian lab data at zero incremental cost. Marketing-grade win. | H18: A (validated against NHANES mortality) | I18: all programs (free add-on)
A19: Glycan age (IgG glycosylation) | B19: IgG N-glycan profile (galactosylation, sialylation, bisecting GlcNAc) reflects systemic chronic low-grade inflammation | C19: Dried blood spot, UPLC analysis of released IgG N-glycans | D19: GlycanAge Ltd (UK) | E19: 295 | F19: 23000 | G19: Sample export required. DBS card friendly to courier. Route via Istanbul or Yerevan. GlycanAge accepts samples globally. | H19: B (mechanistic strong, reversible with intervention) | I19: Inflammaging Reversal; Cellular Renewal
A20: Telomere length (median and percent critically short) | B20: Replicative senescence; telomere attrition is a primary hallmark of aging | C20: EDTA whole blood, high-throughput Q-FISH at single-cell resolution | D20: Life Length S.L. (Madrid, TAT high-throughput Q-FISH); alternative TeloYears qPCR | E20: 399 | F20: 41400 | G20: Whole blood ships to Madrid via DHL Medical Express ex-Istanbul or Almaty. Stability requires 5 day cold chain. Risk of sample rejection if transit is delayed; build 24-hour pickup-to-courier SLA. | H20: B (associated with mortality; intervention-responsive in some studies) | I20: Cellular Renewal; annual repeat
A21: Intracellular NAD+ level | B21: NAD+ is co-substrate for sirtuins, PARPs, CD38; declines roughly 50 percent from age 30 to 70 and is rate-limiting for mitochondrial and DNA-repair function | C21: Capillary blood DBS, LC-MS/MS quantification of intracellular NAD+ | D21: Jinfiniti Precision Medicine (CLIA, Augusta GA); ChromaDex Niagen+ (HCP-only); Vibrant America Methylation/NAD profile | E21: 230 | F21: 20240 | G21: DBS card is courier-tolerant (room-temp stable 14 days). Ship via EMS or DHL ex-Almaty. Jinfiniti accepts international samples. | H21: B (NAD+ decline well documented; supplementation response measurable) | I21: Mitochondrial Reset; NAD+ infusion program follow-up
A22: Senescence-associated secretory phenotype (SASP) panel | B22: Senescent cells secrete pro-inflammatory cytokines and proteases (IL-6, IL-8, MMP-3, MCP-1, GDF15, PAI-1) that drive inflammaging and tissue dysfunction | C22: Plasma, multiplex immunoassay (Luminex, Olink) or aptamer (SomaScan) | D22: Quest Cardio IQ plus GDF15 add-on (US); SomaLogic SomaScan (research-grade, 7000 proteins); Olink Target 96 Inflammation | E22: 450 | F22: 55200 | G22: Plasma must ship frozen on dry ice. Logistically the hardest marker class to deliver from Russia. Two-temperature courier via Astana possible but cost is high. Alternative: surrogate panel (IL-6, hsCRP, GDF15, fibrinogen) measured in Russia at INVITRO or KDL with SASP interpretation overlay. | H22: C (panel composition not standardized; clinical thresholds emerging) | I22: Inflammaging Reversal; Senolytic protocol monitoring
A23: p16INK4a expression (CDKN2A) | B23: Cyclin-dependent kinase inhibitor; canonical senescence marker, upregulated in T cells with age | C23: PBMC isolation, qPCR for CDKN2A mRNA | D23: Research-only (UNC Lineberger, SiRNAxiome); not a routine commercial CLIA test in 2026 | E23: 0 | F23: 0 | G23: Not commercially routinely available. Flag as research-grade only. | H23: C (research only) | I23: future research collaboration
A24: hsCRP (high-sensitivity C-reactive protein) | B24: Acute-phase reactant; tracks chronic low-grade inflammation and CV risk | C24: Immunoturbidimetric, serum | D24: INVITRO, KDL, Helix, CMD (all Russia); Quest, Labcorp (US) | E24: 9 | F24: 750 | G24: Routine in every Russian lab. INVITRO Moscow approx 750 RUB consumer (about EUR 8). | H24: A | I24: Inflammaging Reversal; Cellular Renewal; Metabolic; all baselines
A25: Interleukin-6 (IL-6) | B25: Pro-inflammatory cytokine; key SASP component; mortality predictor in elderly | C25: ECLIA or chemiluminescence, serum | D25: INVITRO, KDL, Helix (Russia); Quest, Labcorp (US) | E25: 30 | F25: 2200 | G25: Routine in major Russian labs. INVITRO catalog approx 2200 RUB (about EUR 24). | H25: A | I25: Inflammaging Reversal; Senolytic monitoring
A26: TNF-alpha | B26: Pro-inflammatory cytokine; SASP component | C26: ELISA or chemiluminescence, serum | D26: INVITRO, KDL (Russia); Quest, Labcorp (US) | E26: 35 | F26: 2400 | G26: Available at INVITRO, KDL. Approx 2400 RUB. | H26: B | I26: Inflammaging Reversal
... A68: Pharmacogenomics basic panel (CYP2D6, CYP2C19, CYP3A4, VKORC1) | B68: Drug metabolism polymorphisms; relevant for HRT, statins, anticoagulants, antidepressants | C68: PCR or array genotyping, buccal swab or whole blood | D68: MyGenetics (Russia), Atlas Biomed, INVITRO partnerships | E68: 195 | F68: 17000 | G68: Available at MyGenetics and INVITRO. Approx 17000 RUB. | H68: A | I68: Pre-pharmacotherapy; HRT programs

Sheet Программы
A1: ПРОДУКТОВЫЙ СЛОЙ, 4 ПРОГРАММЫ
A3: Поле | B3: Cellular Renewal | C3: Mitochondrial Reset | D3: Inflammaging Reversal | E3: Epigenetic Age Reduction
A4: Слоган | B4: Активация аутофагии, перезагрузка метаболической гибкости, формирование измеримой базовой линии долголетия. | C4: Восстановление клеточной энергии, рост VO2 max, обратимое преодоление функционального спада, ощутимое физически. | D4: Усмирение хронического воспаления, разгоняющего старение, восстановление кишечно-иммунной устойчивости за 14 ночей. | E4: 12-недельный протокол с 7-ночным курортным интенсивом плюс ежеквартальные чек-ины, разработанный для смещения ваших эпигенетических часов.
A5: Длительность | B5: 10 ночей | C5: 7 ночей | D5: 14 ночей | E5: 7 ночей курортного интенсива плюс 12-недельный домашний протокол с 2 ежеквартальными чек-инами (3-й месяц и 6-й месяц, телемед-перетестирование панели)
A6: Целевой гость | B6: Руководитель 45-65 лет, метаболически здоровый, но ощущающий замедление; хочет получить защищённую биологическую перезагрузку и чистую базовую линию, которую можно отслеживать годами. | C6: Руководитель 50-70 лет с жалобами на утомляемость, постковидный или постбёрнаут-спад, снижение спортивной формы, туман в голове. Подходит для high-performer, упёршегося в плато. | D6: Гость 50-75 лет с повышенным hsCRP или IL-6, признаками метаболического синдрома, симптомами со стороны ЖКТ, скованностью суставов или поствоспалительным шлейфом после инфекции. Пациент с ощущением «постарел», у которого скрининг показывает измеримое инфламэйджинг. | E6: Трекер, чаще 40-60 лет. Уже тестировал эпигенетический возраст (TruDiagnostic, Elysium, GlycanAge), готов к структурированной 12-недельной интервенции и хочет получить измеримое снижение DunedinPACE или GrimAge2. Готов соблюдать удалённые протоколы и делиться данными с носимых устройств.
A7: Биологическая логика | B7: Сочетает временные окна питания (TRE) с 5-дневным протоколом диеты, имитирующей голодание (FMD), ежедневным гормезис-стеком (финская сауна, ледяная купель, ИГГТ) и силовыми тренировками. Активирует аутофагию и AMPK, подавляет mTOR, смещает утилизацию субстратов в сторону окисления жиров и запускает биогенез митохондрий. Подкреплено исследованиями Longo по FMD, когортой Laukkanen по сауне и литературой по аутофагии. | C7: Протокол, центрированный на NAD+, в стеке с гипербарической оксигенацией, ИГГТ и аэробной нагрузкой по CPET в Зоне 2 плюс поляризованные тренировки. Нацелен на биогенез митохондрий, ёмкость электронно-транспортной цепи и сигнальный путь PGC-1 alpha. Инфузия NAD+ обеспечивает доступность субстрата для сиртуинов (SIRT1, SIRT3) и поддерживает репарацию ДНК (PARP). Аэробное предписание привязано к индивидуальным вентиляционным порогам, полученным по CPET. HBOT рекрутирует ангиогенез и мобилизует стволовые клетки согласно протоколу Efrati. | D7: Двухнедельная интенсивная программа, нацеленная на ось инфламэйджинга: хроническое низкоинтенсивное воспаление, накопление сенесцентных клеток, дисфункция кишечного барьера и нагрузка цитокинов SASP. Стек включает противовоспалительное питание (средиземноморская диета плюс целевые полифенолы), восстановление микробиома кишечника, тренировку вагального тонуса (HRV-биообратная связь, медитация, сауна), лёгкую аэробную нагрузку и сенолитически осведомлённую нутрицевтику. Сильная опора на Inflammaging Panel (hsCRP, IL-6, TNF-alpha, фибриноген, GlycA) для демонстрации измеримой обратной динамики на выходе и повторно через 90 дней. | E7: Смоделирован по дизайну Younger Trial Fitzgerald 2021 (снижение DNAm-PhenoAge за 8 недель за счёт питания с метильными донорами, оптимизации сна, тренировок и снижения стресса), расширен до 12 недель и привязан к TruAge Complete (Horvath, GrimAge2, DunedinPACE, OMICmAge). Курортный интенсив фронт-загружает соблюдение (CGM, носимые устройства, входная панель, калибровка протокола). Удалённый слой обеспечивает консистентность по переменным, которые двигают метилирование: сон, устойчивая умеренная аэробная нагрузка, поступление метильных доноров (фолат, B12, бетаин, холин), полифенолы и снижение стресса. Перетестирование на 12-й неделе через TruAge плюс вторичные панели.
A8: Часы практиков | B8: {'Врач превентивной медицины (старший)': 4.5, 'Нутрициолог (с подготовкой по долголетию)': 5.0, 'Врач-физиолог нагрузок (интерпретация CPET)': 3.5, 'Медсестра внутривенной терапии (с подготовкой по NAD+)': 3.0, 'Специалист по поведенческим изменениям / health-коуч': 6.0, 'СПА-терапевт (продвинутая мануальная терапия)': 4.0, 'Флеботомист / диагностическая медсестра': 1.5, 'Тренер по силовой и общефизической подготовке': 3.0, 'Коуч по протоколам голодания': 5.0} | C8: {'Врач превентивной медицины (старший)': 3.5, 'Кардиолог (сертифицирован по CPET)': 1.5, 'Врач-физиолог нагрузок (интерпретация CPET)': 4.5, 'Медсестра внутривенной терапии (с подготовкой по NAD+)': 8.0, 'Врач anti-aging / регенеративной медицины': 1.5, 'Техник по гипербарической оксигенации': 3.0, 'Тренер по силовой и общефизической подготовке': 3.0, 'Нутрициолог (с подготовкой по долголетию)': 2.5, 'Специалист по поведенческим изменениям / health-коуч': 3.0, 'СПА-терапевт (продвинутая мануальная терапия)': 2.5, 'Флеботомист / диагностическая медсестра': 1.5} | D8: {'Врач превентивной медицины (старший)': 5.5, 'Врач функциональной медицины': 4.0, 'Эндокринолог (гормональная оптимизация)': 1.5, 'Врач anti-aging / регенеративной медицины': 2.0, 'Нутрициолог (с подготовкой по долголетию)': 7.0, 'Клинический диетолог': 2.0, 'Специалист по поведенческим изменениям / health-коуч': 8.0, 'СПА-терапевт (продвинутая мануальная терапия)': 8.0, 'Преподаватель mindfulness / медитации': 4.0, 'Специалист по сну (сертифицирован по PSG)': 1.5, 'Техник по сну': 4.0, 'Тренер по силовой и общефизической подготовке': 4.5, 'Терапевт по пилатесу / движению': 4.0, 'Флеботомист / диагностическая медсестра': 2.0, 'Медсестра внутривенной терапии (с подготовкой по NAD+)': 2.5, 'Психолог / специалист по ментальной производительности': 2.0} | E8: {'Медицинский директор по долголетию': 1.5, 'Врач превентивной медицины (старший)': 4.5, 'Врач функциональной медицины': 1.5, 'Эндокринолог (гормональная оптимизация)': 1.5, 'Нутрициолог (с подготовкой по долголетию)': 5.0, 'Врач-физиолог нагрузок (интерпретация CPET)': 3.0, 'Тренер по силовой и общефизической подготовке': 2.5, 'Специалист по поведенческим изменениям / health-коуч': 12.0, 'Преподаватель mindfulness / медитации': 2.0, 'СПА-терапевт (продвинутая мануальная терапия)': 3.0, 'Медсестра внутривенной терапии (с подготовкой по NAD+)': 3.0, 'Флеботомист / диагностическая медсестра': 2.0, 'Медицинский патиент-координатор': 6.0, 'Специалист по сну (сертифицирован по PSG)': 0.5, 'Техник по сну': 1.0}
A9: F&B стоимость | B9: {'type': 'Терапевтическая кухня, меню в соответствии с FMD (рецепты, выровненные с ProLon, приготовление на месте), сок-бар, протоколы электролитов', 'protein_targeting': '0,8-1,0 г на кг тощей массы в дни TRE и рефида; ограничение калорий до приблизительно 750 ккал в дни FMD 4-8', 'supplements_dispensed': ['NMN 500 мг ежедневно', 'спермидин 5 мг', 'берберин 500 мг', 'магния глицинат 400 мг', 'омега-3 EPA/DHA 2 г', 'электролитная смесь в дни FMD']} | C9: {'type': 'Средиземноморско-митохондриальное меню, насыщенное полифенолами, акцент на омега-3, умеренные углеводы, периодизированные вокруг тренировок', 'protein_targeting': '1,4-1,6 г на кг массы тела, распределённые на 3-4 приёма пищи для поддержки тренировочной адаптации', 'supplements_dispensed': ['NMN 1 г ежедневно', 'CoQ10 убихинол 200 мг', 'PQQ 20 мг', 'L-карнитин 2 г', 'креатин моногидрат 5 г', 'магния глицинат 400 мг', 'омега-3 EPA/DHA 3 г']} | D9: {'type': 'Средиземноморский противовоспалительный рацион плюс опциональный low-FODMAP трек, насыщенный полифенолами (оливковое масло extra virgin, ягоды, крестоцветные), реинтродукция ферментированных продуктов на 2-й неделе, без алкоголя, низкогликемический', 'protein_targeting': '1,2-1,4 г на кг массы тела, с акцентом на растительные источники, рыба 3 раза в неделю, яйца и птица по переносимости', 'supplements_dispensed': ['фисетин 1500 мг пульс на 8-й и 15-й день', 'кверцетин 500 мг ежедневно на 2-й неделе', 'куркумин (фитосомы) 500 мг дважды в день', 'омега-3 с высоким EPA 3 г', 'витамин D3 + K2 (доза до 25-OH-D 40-60 нг/мл)', 'споровый пробиотик', 'L-глутамин 5 г (для ЖКТ)', 'NMN 500 мг']} | E9: {'type': 'Средиземноморская диета плюс акцент на метильные доноры (яйца, листовая зелень, свёкла, рыба), насыщенная полифенолами, временное окно питания 14:10 по умолчанию. Пакет рецептов и список покупок на каждую неделю с собой.', 'protein_targeting': '1,2-1,4 г на кг массы тела, распределённые', 'supplements_dispensed': ['NMN 1 г ежедневно', 'метилированный B-комплекс (5-MTHF, метилкобаламин)', 'TMG (бетаин) 1 г', 'холин 500 мг', 'спермидин 5 мг', 'омега-3 с высоким EPA 3 г', 'полифенольный комплекс (ресвератрол 250 мг, фисетин 100 мг, птеростильбен)', 'витамин D3+K2', 'магния глицинат']}
A10: Прайс EUR | B10: 19500 | C10: 15500 | D10: 24500 | E10: 28500
A11: Прайс RUB | B11: 1794000 | C11: 1426000 | D11: 2254000 | E11: 2622000
A12: COGS EUR (suma) | B12: 14106 | C12: 14938 | D12: 21642 | E12: 29314
A13: Контрибуционная маржа EUR | B13: 12447 | C13: 8031 | D13: 13679 | E13: 13843
A14: Контрибуционная маржа % | B14: 0.638 | C14: 0.518 | D14: 0.558 | E14: 0.486
A15: Биомаркер пакет | B15: Foundation на входе + Inflammaging / Mitochondrial / Hormone в зависимости от программы; контроль через 8, 12 недель | C15: Foundation на входе + Inflammaging / Mitochondrial / Hormone в зависимости от программы; контроль через 8, 12 недель | D15: Foundation на входе + Inflammaging / Mitochondrial / Hormone в зависимости от программы; контроль через 8, 12 недель | E15: Foundation на входе + Inflammaging / Mitochondrial / Hormone в зависимости от программы; контроль через 8, 12 недель
A16: Оборудование (ключевые точки) | B16: {'Премиум финская сауна (коммерческая, на 8-12 персон, Klafs/Tylo)': 9, 'Бассейн с ледяной купелью (с охлаждением, 4-10 °C, на 2-3 персоны)': 9, 'Премиум селекторная силовая линия (15 единиц)': 5, 'Функциональный риг + кабельные системы': 3, 'Студийный комплект Pilates Reformer': 3, 'DEXA-сканер состава тела и плотности костей': 1, 'Анализатор состава тела медицинского класса (BIA)': 3, 'Метаболическая тележка CPET / VO2 max': 1, '12-канальная ЭКГ покоя': 1, 'Аппарат интервальной гипоксически-гипероксической тренировки (ИГГТ)': 4, 'Кресло-реклайнер для внутривенной терапии (клиническое)': 2, 'Комплекты непрерывного мониторинга глюкозы (расходники)': 1, 'Премиум кухня, заготовка FMD (порции и блюда)': 30, 'Премиум массажные столы СПА (электрические, с подогревом)': 4, 'Анализ пульсовой волны / артериальная жёсткость': 2, 'Анализатор базального уровня метаболизма': 1} | C16: {'Кресло-реклайнер для внутривенной терапии (клиническое)': 5, 'Умный инфузионный насос': 5, 'Барокамера гипербарической оксигенации (мягкая, 1,3-2,0 ATA)': 5, 'Аппарат интервальной гипоксически-гипероксической тренировки (ИГГТ)': 3, 'Метаболическая тележка CPET / VO2 max': 2, 'Стресс-ЭКГ с беговой дорожкой': 1, '12-канальная ЭКГ покоя': 2, 'Премиум кардиолиния (беговые дорожки/велотренажёры/эллипсоиды)': 5, 'Премиум селекторная силовая линия (15 единиц)': 3, 'Премиум финская сауна': 5, 'Бассейн с ледяной купелью': 5, 'Анализ пульсовой волны / артериальная жёсткость': 2, 'Анализатор состава тела медицинского класса (BIA)': 2, 'Премиум массажные столы СПА (электрические, с подогревом)': 3, 'Премиум кухня, блюда': 21} | D16: {'Премиум финская сауна (коммерческая)': 12, 'Бассейн с ледяной купелью': 12, 'Премиум инфракрасная сауна (полный спектр)': 4, 'Премиум русская банная парная': 2, 'Галотерапевтическая соляная комната / пещера': 3, 'Флоатинг-капсула': 2, 'Гидротерапевтический стол Vichy (мультиджет)': 3, 'Контур Кнейпп (горячие/холодные ножные ванны)': 5, 'Хаммам, паровая комната': 3, 'Камера общей криотерапии': 4, 'Студийный комплект Pilates Reformer': 5, 'Премиум селекторная силовая линия (15 единиц)': 5, 'Функциональный риг + кабельные системы': 4, 'Премиум кардиолиния': 6, 'DEXA-сканер состава тела и плотности костей': 1, 'Эластография печени (FibroScan)': 1, 'Кабинет полисомнографии (PSG)': 1, 'Анализатор водородно-метанового дыхательного теста (СИБР)': 1, 'Визуализация сетчатки / OCT': 1, 'Анализ пульсовой волны / артериальная жёсткость': 2, 'Кресло-реклайнер для внутривенной терапии (клиническое)': 2, 'Генератор медицинской озонотерапии': 1, 'Аппарат гидроколонотерапии': 2, 'Премиум массажные столы СПА (электрические, с подогревом)': 8, 'Кровать / панель LED-светотерапии (медицинская)': 4, 'Премиум кухня, блюда': 42} | E16: {'DEXA-сканер состава тела и плотности костей': 2, 'Метаболическая тележка CPET / VO2 max': 1, 'Анализ пульсовой волны / артериальная жёсткость': 2, 'Визуализация сетчатки / OCT': 1, 'Анализатор состава тела медицинского класса (BIA)': 3, 'Комплекты непрерывного мониторинга глюкозы (расходники)': 4, 'Премиум парк носимых устройств (Oura / Whoop / Apple Watch)': 1, 'Премиум финская сауна': 6, 'Бассейн с ледяной купелью': 6, 'Премиум селекторная силовая линия (15 единиц)': 3, 'Функциональный риг + кабельные системы': 2, 'Премиум кардиолиния': 4, 'Студийный комплект Pilates Reformer': 2, 'Кресло-реклайнер для внутривенной терапии (клиническое)': 2, 'Умный инфузионный насос': 2, 'Кабинет полисомнографии (PSG)': 1, 'Премиум кухня, блюда': 21, 'Премиум массажные столы СПА (электрические, с подогревом)': 3}
A19: ГОДОВОЙ ПРОГНОЗ ВЫРУЧКИ ПРОГРАММ, ГОД 5
A20: Гостей программ в год | B20: 1281
A21: Средневзвешенная цена, EUR | B21: 21100
A22: Выручка программ, EUR | B22: 27029100
A23: Выручка программ, RUB | B23: 2486677200
A24: Доля от общей выручки резорта | B24: 0.682
A25: Допущения | B25: 90 ключей, 65% загрузки на 5-й год, средняя длительность пребывания 10 ночей, 60% гостевых пребываний на программе долголетия (против только лечебно-оздоровительных). Курс 92 RUB/EUR.

Sheet Персонал
A1: КЛИНИЧЕСКИЙ ПЕРСОНАЛ, 28 РОЛЕЙ
A3: Роль | B3: Квалификации | C3: FTE Lanserhof / CLP | D3: FTE SHA / Chenot | E3: FTE Six Senses | F3: Годовая ЗП ЕС, EUR | G3: Годовая ЗП РФ, RUB | H3: Доступность кадров
A4: Longevity Medical Director | B4: Диплом врача со специализацией в регенеративной медицине, anti-aging медицине или терапии; предпочтительна сертификация A4M (American Academy of Anti-Aging Medicine) или IFM (Institute for Functional Medicine); клинический стаж от 15 лет; свободное владение клеточной биологией, включая сигнальные пути mTOR, AMPK, NAD+ и механизмы клеточного старения; приветствуются научные публикации. | C4: 1 | D4: 1 | E4: 1 | F4: 280000 | G4: 18000000 | H4: Кадровый ресурс крайне ограничен. Источники кандидатов: ведущие врачи Сеченовского Первого МГМУ, медицинского факультета МГИМО, РНИМУ им. Пирогова; частные клиники Lechu, K+31, EMC, GMS Clinic, AtlasBiomed. Настоятельно рекомендуется привлечение экспатов из Израиля, Германии, ОАЭ, с Кипра и из Сербии. Найм экспатов после 2022 года затруднён; целесообразно рассматривать кандидатов с двойным гражданством (российско-израильское, российско-немецкое).
A5: Longevity Physician (Senior) | B5: Диплом врача, сертификат специалиста по терапии или гериатрии; сертификация A4M или IFM; клинический стаж от 8 лет; уверенная интерпретация панелей биомаркеров (GlycanAge, TruDiagnostic, Galleri, орган-специфические эпигенетические часы старения). | C5: 2 | D5: 1 | E5: 0 | F5: 180000 | G5: 11000000 | H5: Дефицитная позиция. Лучшие кандидаты, по нашим оценкам, доступны в EMC, GMS, Lechu (Москва) и в Скандинавия Клиник (Санкт-Петербург). Реалистично закрыть 1-2 позиции в течение 12 месяцев; для дополнительной нагрузки целесообразна работа по locum-модели или приглашение приезжающих специалистов.
A6: Anti-aging / Regenerative Medicine Physician | B6: Диплом врача со специализацией в регенеративной медицине, экзосомной терапии и PRP, гормональной оптимизации; предпочтительна сертификация ISSAM или WOSAAM. | C6: 1 | D6: 1 | E6: 0 | F6: 160000 | G6: 9500000 | H6: Умеренный кадровый пул в эстетической медицине; глубокие знания клеточной биологии встречаются редко. Потребуется переподготовка. Источники: Estelab, Frau Klinik, RHANA в Москве.
A7: Cardiologist (CPET-certified) | B7: Диплом врача, сертификат специалиста по кардиологии; предпочтительна сертификация ESC; опыт интерпретации CPET (кардиопульмонального нагрузочного тестирования); понимание показателей VO2max, лактатного порога и вентиляторных порогов. | C7: 1 | D7: 1 | E7: 0 | F7: 200000 | G7: 10500000 | H7: Достаточный кадровый пул кардиологов из НМИЦ им. Бакулева, НМИЦ им. Алмазова (Санкт-Петербург), НМИЦ кардиологии им. Чазова. Кардиологи с подготовкой по CPET встречаются реже; субспециализация по спортивной кардиологии развита слабо. Целесообразна переподготовка в рамках программ ESC по спортивной кардиологии.
A8: Endocrinologist (Hormone Optimisation) | B8: Диплом врача, сертификат специалиста по эндокринологии; опыт оптимизации функции щитовидной железы, надпочечников, половых гормонов; знакомство с пептидной терапией, протоколами агонистов GLP-1, осью IGF-1 / гормон роста. | C8: 1 | D8: 1 | E8: 0 | F8: 170000 | G8: 9000000 | H8: Уверенный кадровый пул из НМИЦ эндокринологии (Москва), Сеченовского университета. Российская практика гормональной оптимизации (HRT, TRT) более консервативна; требуется врач, владеющий международными протоколами.
A9: Sports Medicine Physician | B9: Диплом врача, специализация в спортивной медицине; предпочтительна подготовка по программам FIMS или ECSS; глубокие знания опорно-двигательного аппарата и физиологии физических нагрузок. | C9: 1 | D9: 1 | E9: 0 | F9: 140000 | G9: 7500000 | H9: Кадровый ресурс приемлемый. Источники: РУСАДА, сеть спортивной медицины ФМБА, выпускники медицинских служб олимпийских сборных. Близость Сысерти к Екатеринбургу даёт преимущество (региональный центр спортивной медицины).
A10: Functional Medicine Physician | B10: Диплом врача с сертификацией IFM или эквивалентной; компетенции в области микробиоты кишечника, пищевой непереносимости, экологической медицины, митохондриальной дисфункции. | C10: 1 | D10: 0 | E10: 0 | F10: 165000 | G10: 9000000 | H10: Кадровый ресурс крайне ограничен. Функциональная медицина в России формально не признана. Поиск через частные клиники, в которых работают врачи с подготовкой IFM (по нашим оценкам, менее 50 человек по стране). Предпочтительно привлечение экспатов.
A11: IV Therapy Specialist Nurse (NAD+ trained) | B11: Диплом медсестры со стажем работы от 5 лет; сертификат на проведение внутривенных инфузий; специализированная подготовка по инфузиям NAD+ (титрование дозы, купирование побочных эффектов); опыт работы с высокодозной инфузионной терапией витамином C, глутатионом, NAD+, а также с приготовлением пептидных растворов. | C11: 5 | D11: 3 | E11: 1 | F11: 65000 | G11: 2400000 | H11: Уверенный пул медсестёр, однако специализированная подготовка по NAD+ в России практически отсутствует. Необходимо запланировать внешнее обучение продолжительностью 4-6 недель (через партнёрства с Drip Hydration USA, Reviv Global, Get A Drip UK); обязательно наличие внутреннего протокола работы.
A12: Phlebotomist / Diagnostic Nurse | B12: Среднее медицинское образование или диплом медсестры со стажем флеботомии от 3 лет; опыт расширенных заборов (50+ пробирок за сессию для лонжевити-панелей); навыки соблюдения холодовой цепи. | C12: 3 | D12: 2 | E12: 1 | F12: 42000 | G12: 1400000 | H12: Кадровый ресурс достаточный. Опора на выпускников Свердловского областного медицинского колледжа. Самая простая для локального найма позиция.
A13: Exercise Physiologist (CPET interpretation) | B13: Магистр (MSc) физиологии физических нагрузок или спортивной науки; аккредитация ACSM-EP-C или BASES; опыт интерпретации CPET, включая VO2max, вентиляторные пороги, анализ RER; компетенции в тестировании лактатного порога. | C13: 3 | D13: 2 | E13: 1 | F13: 80000 | G13: 3200000 | H13: Кадровый ресурс крайне ограничен. Сильная академическая база в спортивной науке (РГУФК, НГУ им. Лесгафта в Санкт-Петербурге), но мало практиков с опытом CPET в частном секторе. Источники: выпускники ФМБА и центров олимпийской подготовки; возможно дополнение ресурсами контрактных специалистов из ЕС.
A14: Strength and Conditioning Coach | B14: Бакалавр (BSc) спортивной науки или кинезиологии; аккредитация NSCA-CSCS или UKSCA; опыт работы с детренированным контингентом и с программами лонжевити-направленности (Zone 2, интервалы для развития VO2max, силовая работа для профилактики саркопении). | C14: 4 | D14: 3 | E14: 2 | F14: 60000 | G14: 2200000 | H14: Сильный кадровый пул в России (наследие советской спортивной науки); зрелый частный фитнес-сектор в Москве и Санкт-Петербурге. В Екатеринбурге также имеется приличная база специалистов.
A15: Pilates / Movement Therapist | B15: Сертифицированный инструктор по пилатесу (Polestar, Stott, BASI) с дополнительным сертификатом по скринингу движения (FMS, SFMA); предпочтителен опыт реабилитации. | C15: 4 | D15: 3 | E15: 2 | F15: 50000 | G15: 1900000 | H15: Сильный кадровый пул в Москве и Санкт-Петербурге; в Екатеринбурге кадры найти сложнее. Целесообразен ввоз 1-2 старших инструкторов и развитие местных специалистов.
... A31: Hyperbaric Oxygen Therapy Technician | B31: Среднее медицинское образование (медицинский техник) с сертификацией по эксплуатации барокамеры HBOT (UHMS или эквивалент); подготовка по технике безопасности. | C31: 2 | D31: 1 | E31: 0 | F31: 50000 | G31: 1700000 | H31: Нишевая позиция. Источники подготовки: военная и водолазная медицина (выпускники ФМБА, ВМФ). Кадровый ресурс достаточный.
A32: ИТОГО | C32: 81 | D32: 58 | E32: 28 | F32: 3883000 | G32: 357271000 | H32: ФОТ: SHA EUR 2 953 000; Six Senses EUR 1 061 000
